Workbook

Sheet Cas 2011-2025
A1: Année | B1: Catégorie | C1: Station | D1: SSP n° | E1: SSP | F1: Plainte | G1: Diagnostic générique | H1: Diagnstic principal | I1: Diagnostics différentiels | J1: Description | K1: Anamnèse | L1: Status | M1: Management | N1: Diagnstic principal (original) | O1: SSP attendu (par n°) | P1: Concordance n° ↔ libellé | Q1: Écart vs backup (Feuil1!E) | R1: À vérifier | S1: Cohérence diag. générique ↔ principal | T1: Détails cohérence | U1: Key (2013-2017 match) | V1: Desc (C13-17) | W1: Anamnèse (C13-17) | X1: Status (C13-17) | Y1: DD (C13-17) | Z1: PEC (C13-17) | AA1: Examens compl. (C13-17) | AB1: Key (norm) | AC1: Diag norm (1) | AD1: Diag norm (2) | AE1: Diag norm (3) | AF1: Diag norm (4)
A2: 2011 | B2: ❤️ Cardiologie / Vasculaire | D2: 10 | E2: =IF(D2="","",IFERROR(INDEX(SSP!$E$2:$E$266, MATCH(D2, SSP!$F$2:$F$266, 0)),"")) -> Douleur (toutes localisations et types confondus) | F2: =Feuil1!E2 -> Douleur jambe | G2: Artériopathie des membres inférieurs | H2: AOMI | J2: Homme d'âge moyen avec douleur soudaine et intense à la jambe droite depuis 2 heures pendant le jardinage. Allongé sur le lit et incapable de marcher. | K2: Anamnèse, examen, procédures supplémentaires. Héparine administrée, transfert au laboratoire de cathétérisme. Disparition des pulsations à la jambe droite, héparine administrée. | N2: AOMI | O2: =IFERROR(_xlfn.XLOOKUP($D2, SSP!$F:$F, SSP!$E:$E, "Inconnu"), "") -> Douleur (toutes localisations et types confondus) | P2: =IF(OR(E2="", O2=""), "", IF(LOWER(E2)=LOWER(O2), "OK", "⚠️ Libellé ≠ n°")) -> OK | Q2: =IF(Feuil1!$E2="", "", IF(LOWER(Feuil1!$E2)=LOWER(E2), "Identique", "Différent")) -> Différent | R2: =IF(OR(P2="⚠️ Libellé ≠ n°", O2="Inconnu"), "⚠️", IF(Q2="Différent", "ℹ️", "")) -> ℹ️ | S2: {=_xlfn.LET(_xlpm.genCat,IFERROR(LOWER(TRIM(G2)),""),_xlpm.principal,IFERROR(LOWER(TRIM(H2)),""),_xlpm.orig,IFERROR(LOWER(TRIM(N2)),""),IF(OR(_xlpm.genCat="",_xlpm.principal=""),"",IF(LEFT(LOWER(G2),5)="autre","OK (Autre)",IF(OR(ISNUMBER(SEARCH(_xlpm.genCat,_xlpm.principal)),ISNUMBER(SEARCH(_xlpm.principal,_xlpm.genCat)),AND(_xlpm.orig<>"",OR(ISNUMBER(SEARCH(_xlpm.genCat,_xlpm.orig)),ISNUMBER(SEARCH(_xlpm.orig,_xlpm.genCat))))),"OK","⚠️ À vérifier"))))} -> ⚠️ À vérifier | T2: =IF(S2="","",IF(S2="OK (Autre)","Diagnostic générique = 'Autre – …'",IF(S2="OK","Concordance générique/principal","Écart entre générique et principal"))) -> Écart entre générique et principal | U2: {=_xlfn.LET(_xlpm.yr, A2, _xlpm.diag, IF(N2<>"", N2, H2), _xlpm.base, TRIM(SUBSTITUTE(SUBSTITUTE(SUBSTITUTE(SUBSTITUTE(_xlpm.diag,"•"," "),CHAR(160)," "),CHAR(10)," ")," "," ")), LOWER(_xlpm.yr&"|"&_xlpm.base))} -> 2011|aomi | V2: =IFERROR(_xlfn.XLOOKUP($AB2,'Cas 2013-2017'!$K:$K,'Cas 2013-2017'!$D:$D,""),"") | W2: =IFERROR(_xlfn.XLOOKUP($AB2,'Cas 2013-2017'!$K:$K,'Cas 2013-2017'!$E:$E,""),"") | X2: =IFERROR(_xlfn.XLOOKUP($AB2,'Cas 2013-2017'!$K:$K,'Cas 2013-2017'!$F:$F,""),"") | Y2: =IFERROR(_xlfn.XLOOKUP($AB2,'Cas 2013-2017'!$K:$K,'Cas 2013-2017'!$G:$G,""),"") | Z2: =IFERROR(_xlfn.XLOOKUP($AB2,'Cas 2013-2017'!$K:$K,'Cas 2013-2017'!$I:$I,""),"") | AA2: =IFERROR(_xlfn.XLOOKUP($AB2,'Cas 2013-2017'!$K:$K,'Cas 2013-2017'!$H:$H,""),"") | AB2: =LOWER($A2 & "|" & $AF2) -> 2011|arteriopathie des membres inferieurs | AC2: =TRIM(SUBSTITUTE(SUBSTITUTE(SUBSTITUTE(SUBSTITUTE(" " & LOWER(TRIM(IF($N2<>"", $N2, $H2))) & " ", " aomi ", " arteriopathie des membres inferieurs "), " hta ", " hypertension arterielle "), " saos ", " syndrome d'apnees obstructives du sommeil "), " rgo ", " reflux gastro-oesophagien ") ) -> arteriopathie des membres inferieurs | AD2: =TRIM(SUBSTITUTE(SUBSTITUTE(SUBSTITUTE(SUBSTITUTE(" " & LOWER(TRIM($AC2)) & " ", " oacr ", " occlusion de l'artere centrale de la retine "), " hsd ", " hematome sous-dural "), " fa ", " fibrillation auriculaire "), " ep ", " embolie pulmonaire ") ) -> arteriopathie des membres inferieurs | AE2: {=_xlfn.LET(_xlpm.base, " " & LOWER(TRIM($AD2)) & " ", _xlpm.s1, SUBSTITUTE(_xlpm.base, " ic ", " insuffisance cardiaque "), _xlpm.s2, SUBSTITUTE(_xlpm.s1, " avc ", " accident vasculaire cerebral "), _xlpm.s3, SUBSTITUTE(_xlpm.s2, " hsa ", " hemorragie sous-arachnoidienne "), _xlpm.s4, SUBSTITUTE(_xlpm.s3, " htp ", " hypertension pulmonaire "), _xlpm.s5, SUBSTITUTE(_xlpm.s4, " bpco ", " bronchopneumopathie chronique obstructive "), _xlpm.s6, SUBSTITUTE(_xlpm.s5, " dmla ", " degenerescence maculaire liee a l age "), TRIM(_xlpm.s6))} -> arteriopathie des membres inferieurs | AF2: {=_xlfn.LET(_xlpm.base, " " & LOWER(TRIM($AE2)) & " ", _xlpm.s1, SUBSTITUTE(_xlpm.base, " omi ", " oedemes des membres inferieurs "), _xlpm.s2, SUBSTITUTE(_xlpm.s1, " idm ", " infarctus du myocarde "), _xlpm.s3, SUBSTITUTE(_xlpm.s2, " tvp ", " thrombose veineuse profonde "), _xlpm.s4, SUBSTITUTE(_xlpm.s3, " geu ", " grossesse extra-uterine "), _xlpm.s5, SUBSTITUTE(_xlpm.s4, " fuo ", " fievre d origine indeterminee "), TRIM(_xlpm.s5))} -> arteriopathie des membres inferieurs
A3: 2011 | B3: ❤️ Cardiologie / Vasculaire | D3: 44 | E3: =IF(D3="","",IFERROR(INDEX(SSP!$E$2:$E$266, MATCH(D3, SSP!$F$2:$F$266, 0)),"")) -> Douleur thoracique | F3: =Feuil1!E3 -> Douleur thoracique | G3: Péricardite | H3: Péricardite | J3: Homme au service des urgences avec douleur thoracique, respiratoire, améliorée par la flexion en avant. | K3: À l'ECG, élévation du segment ST de V1 à V6, ne peut être examiné en position allongée. Antécédents d'infection. | N3: Péricardite | O3: =IFERROR(_xlfn.XLOOKUP($D3, SSP!$F:$F, SSP!$E:$E, "Inconnu"), "") -> Douleur thoracique | P3: =IF(OR(E3="", O3=""), "", IF(LOWER(E3)=LOWER(O3), "OK", "⚠️ Libellé ≠ n°")) -> OK | Q3: =IF(Feuil1!$E3="", "", IF(LOWER(Feuil1!$E3)=LOWER(E3), "Identique", "Différent")) -> Identique | R3: =IF(OR(P3="⚠️ Libellé ≠ n°", O3="Inconnu"), "⚠️", IF(Q3="Différent", "ℹ️", "")) | S3: {=_xlfn.LET(_xlpm.genCat,IFERROR(LOWER(TRIM(G3)),""),_xlpm.principal,IFERROR(LOWER(TRIM(H3)),""),_xlpm.orig,IFERROR(LOWER(TRIM(N3)),""),IF(OR(_xlpm.genCat="",_xlpm.principal=""),"",IF(LEFT(LOWER(G3),5)="autre","OK (Autre)",IF(OR(ISNUMBER(SEARCH(_xlpm.genCat,_xlpm.principal)),ISNUMBER(SEARCH(_xlpm.principal,_xlpm.genCat)),AND(_xlpm.orig<>"",OR(ISNUMBER(SEARCH(_xlpm.genCat,_xlpm.orig)),ISNUMBER(SEARCH(_xlpm.orig,_xlpm.genCat))))),"OK","⚠️ À vérifier"))))} -> OK | T3: =IF(S3="","",IF(S3="OK (Autre)","Diagnostic générique = 'Autre – …'",IF(S3="OK","Concordance générique/principal","Écart entre générique et principal"))) -> Concordance générique/principal | U3: {=_xlfn.LET(_xlpm.yr, A3, _xlpm.diag, IF(N3<>"", N3, H3), _xlpm.base, TRIM(SUBSTITUTE(SUBSTITUTE(SUBSTITUTE(SUBSTITUTE(_xlpm.diag,"•"," "),CHAR(160)," "),CHAR(10)," ")," "," ")), LOWER(_xlpm.yr&"|"&_xlpm.base))} -> 2011|péricardite | V3: =IFERROR(_xlfn.XLOOKUP($AB3,'Cas 2013-2017'!$K:$K,'Cas 2013-2017'!$D:$D,""),"") | W3: =IFERROR(_xlfn.XLOOKUP($AB3,'Cas 2013-2017'!$K:$K,'Cas 2013-2017'!$E:$E,""),"") | X3: =IFERROR(_xlfn.XLOOKUP($AB3,'Cas 2013-2017'!$K:$K,'Cas 2013-2017'!$F:$F,""),"") | Y3: =IFERROR(_xlfn.XLOOKUP($AB3,'Cas 2013-2017'!$K:$K,'Cas 2013-2017'!$G:$G,""),"") | Z3: =IFERROR(_xlfn.XLOOKUP($AB3,'Cas 2013-2017'!$K:$K,'Cas 2013-2017'!$I:$I,""),"") | AA3: =IFERROR(_xlfn.XLOOKUP($AB3,'Cas 2013-2017'!$K:$K,'Cas 2013-2017'!$H:$H,""),"") | AB3: =LOWER($A3 & "|" & $AF3) -> 2011|péricardite | AC3: =TRIM(SUBSTITUTE(SUBSTITUTE(SUBSTITUTE(SUBSTITUTE(" " & LOWER(TRIM(IF($N3<>"", $N3, $H3))) & " ", " aomi ", " arteriopathie des membres inferieurs "), " hta ", " hypertension arterielle "), " saos ", " syndrome d'apnees obstructives du sommeil "), " rgo ", " reflux gastro-oesophagien ") ) -> péricardite | AD3: =TRIM(SUBSTITUTE(SUBSTITUTE(SUBSTITUTE(SUBSTITUTE(" " & LOWER(TRIM($AC3)) & " ", " oacr ", " occlusion de l'artere centrale de la retine "), " hsd ", " hematome sous-dural "), " fa ", " fibrillation auriculaire "), " ep ", " embolie pulmonaire ") ) -> péricardite | AE3: {=_xlfn.LET(_xlpm.base, " " & LOWER(TRIM($AD3)) & " ", _xlpm.s1, SUBSTITUTE(_xlpm.base, " ic ", " insuffisance cardiaque "), _xlpm.s2, SUBSTITUTE(_xlpm.s1, " avc ", " accident vasculaire cerebral "), _xlpm.s3, SUBSTITUTE(_xlpm.s2, " hsa ", " hemorragie sous-arachnoidienne "), _xlpm.s4, SUBSTITUTE(_xlpm.s3, " htp ", " hypertension pulmonaire "), _xlpm.s5, SUBSTITUTE(_xlpm.s4, " bpco ", " bronchopneumopathie chronique obstructive "), _xlpm.s6, SUBSTITUTE(_xlpm.s5, " dmla ", " degenerescence maculaire liee a l age "), TRIM(_xlpm.s6))} -> péricardite | AF3: {=_xlfn.LET(_xlpm.base, " " & LOWER(TRIM($AE3)) & " ", _xlpm.s1, SUBSTITUTE(_xlpm.base, " omi ", " oedemes des membres inferieurs "), _xlpm.s2, SUBSTITUTE(_xlpm.s1, " idm ", " infarctus du myocarde "), _xlpm.s3, SUBSTITUTE(_xlpm.s2, " tvp ", " thrombose veineuse profonde "), _xlpm.s4, SUBSTITUTE(_xlpm.s3, " geu ", " grossesse extra-uterine "), _xlpm.s5, SUBSTITUTE(_xlpm.s4, " fuo ", " fievre d origine indeterminee "), TRIM(_xlpm.s5))} -> péricardite
A4: 2011 | B4: ❤️ Cardiologie / Vasculaire | D4: 50 | E4: =IF(D4="","",IFERROR(INDEX(SSP!$E$2:$E$266, MATCH(D4, SSP!$F$2:$F$266, 0)),"")) -> Palpitations | F4: =Feuil1!E4 -> Palpitations | G4: Autre – ️ Cardiologie / Vasculaire | H4: Tachycardie psychogène | I4: Hyperthyroïdie | J4: Jeune femme présentant des palpitations et des tachycardies | K4: ECG normal | N4: Tachycardie psychogène | O4: =IFERROR(_xlfn.XLOOKUP($D4, SSP!$F:$F, SSP!$E:$E, "Inconnu"), "") -> Palpitations | P4: =IF(OR(E4="", O4=""), "", IF(LOWER(E4)=LOWER(O4), "OK", "⚠️ Libellé ≠ n°")) -> OK | Q4: =IF(Feuil1!$E4="", "", IF(LOWER(Feuil1!$E4)=LOWER(E4), "Identique", "Différent")) -> Identique | R4: =IF(OR(P4="⚠️ Libellé ≠ n°", O4="Inconnu"), "⚠️", IF(Q4="Différent", "ℹ️", "")) | S4: {=_xlfn.LET(_xlpm.genCat,IFERROR(LOWER(TRIM(G4)),""),_xlpm.principal,IFERROR(LOWER(TRIM(H4)),""),_xlpm.orig,IFERROR(LOWER(TRIM(N4)),""),IF(OR(_xlpm.genCat="",_xlpm.principal=""),"",IF(LEFT(LOWER(G4),5)="autre","OK (Autre)",IF(OR(ISNUMBER(SEARCH(_xlpm.genCat,_xlpm.principal)),ISNUMBER(SEARCH(_xlpm.principal,_xlpm.genCat)),AND(_xlpm.orig<>"",OR(ISNUMBER(SEARCH(_xlpm.genCat,_xlpm.orig)),ISNUMBER(SEARCH(_xlpm.orig,_xlpm.genCat))))),"OK","⚠️ À vérifier"))))} -> OK (Autre) | T4: =IF(S4="","",IF(S4="OK (Autre)","Diagnostic générique = 'Autre – …'",IF(S4="OK","Concordance générique/principal","Écart entre générique et principal"))) -> Diagnostic générique = 'Autre – …' | U4: {=_xlfn.LET(_xlpm.yr, A4, _xlpm.diag, IF(N4<>"", N4, H4), _xlpm.base, TRIM(SUBSTITUTE(SUBSTITUTE(SUBSTITUTE(SUBSTITUTE(_xlpm.diag,"•"," "),CHAR(160)," "),CHAR(10)," ")," "," ")), LOWER(_xlpm.yr&"|"&_xlpm.base))} -> 2011|tachycardie psychogène | V4: =IFERROR(_xlfn.XLOOKUP($AB4,'Cas 2013-2017'!$K:$K,'Cas 2013-2017'!$D:$D,""),"") | W4: =IFERROR(_xlfn.XLOOKUP($AB4,'Cas 2013-2017'!$K:$K,'Cas 2013-2017'!$E:$E,""),"") | X4: =IFERROR(_xlfn.XLOOKUP($AB4,'Cas 2013-2017'!$K:$K,'Cas 2013-2017'!$F:$F,""),"") | Y4: =IFERROR(_xlfn.XLOOKUP($AB4,'Cas 2013-2017'!$K:$K,'Cas 2013-2017'!$G:$G,""),"") | Z4: =IFERROR(_xlfn.XLOOKUP($AB4,'Cas 2013-2017'!$K:$K,'Cas 2013-2017'!$I:$I,""),"") | AA4: =IFERROR(_xlfn.XLOOKUP($AB4,'Cas 2013-2017'!$K:$K,'Cas 2013-2017'!$H:$H,""),"") | AB4: =LOWER($A4 & "|" & $AF4) -> 2011|tachycardie psychogène | AC4: =TRIM(SUBSTITUTE(SUBSTITUTE(SUBSTITUTE(SUBSTITUTE(" " & LOWER(TRIM(IF($N4<>"", $N4, $H4))) & " ", " aomi ", " arteriopathie des membres inferieurs "), " hta ", " hypertension arterielle "), " saos ", " syndrome d'apnees obstructives du sommeil "), " rgo ", " reflux gastro-oesophagien ") ) -> tachycardie psychogène | AD4: =TRIM(SUBSTITUTE(SUBSTITUTE(SUBSTITUTE(SUBSTITUTE(" " & LOWER(TRIM($AC4)) & " ", " oacr ", " occlusion de l'artere centrale de la retine "), " hsd ", " hematome sous-dural "), " fa ", " fibrillation auriculaire "), " ep ", " embolie pulmonaire ") ) -> tachycardie psychogène | AE4: {=_xlfn.LET(_xlpm.base, " " & LOWER(TRIM($AD4)) & " ", _xlpm.s1, SUBSTITUTE(_xlpm.base, " ic ", " insuffisance cardiaque "), _xlpm.s2, SUBSTITUTE(_xlpm.s1, " avc ", " accident vasculaire cerebral "), _xlpm.s3, SUBSTITUTE(_xlpm.s2, " hsa ", " hemorragie sous-arachnoidienne "), _xlpm.s4, SUBSTITUTE(_xlpm.s3, " htp ", " hypertension pulmonaire "), _xlpm.s5, SUBSTITUTE(_xlpm.s4, " bpco ", " bronchopneumopathie chronique obstructive "), _xlpm.s6, SUBSTITUTE(_xlpm.s5, " dmla ", " degenerescence maculaire liee a l age "), TRIM(_xlpm.s6))} -> tachycardie psychogène | AF4: {=_xlfn.LET(_xlpm.base, " " & LOWER(TRIM($AE4)) & " ", _xlpm.s1, SUBSTITUTE(_xlpm.base, " omi ", " oedemes des membres inferieurs "), _xlpm.s2, SUBSTITUTE(_xlpm.s1, " idm ", " infarctus du myocarde "), _xlpm.s3, SUBSTITUTE(_xlpm.s2, " tvp ", " thrombose veineuse profonde "), _xlpm.s4, SUBSTITUTE(_xlpm.s3, " geu ", " grossesse extra-uterine "), _xlpm.s5, SUBSTITUTE(_xlpm.s4, " fuo ", " fievre d origine indeterminee "), TRIM(_xlpm.s5))} -> tachycardie psychogène
A5: 2011 | B5: ❤️ Cardiologie / Vasculaire | D5: 178 | E5: =IF(D5="","",IFERROR(INDEX(SSP!$E$2:$E$266, MATCH(D5, SSP!$F$2:$F$266, 0)),"")) -> Complications maternelles pendant la grossesse (fièvre, œdème, hypertension, travail prématuré) | F5: =Feuil1!E5 -> Hypertension | G5: Hypertension artérielle | H5: Hypertension artérielle (HTA) | J5: Patient d'environ 57 ans vient en consultation pour un contrôle de la tension artérielle. | K5: Hypertension artérielle depuis 5 ans. Examiner d'autres signes d'insuffisance cardiaque (état pulmonaire et cardiaque complet). Tension artérielle actuellement élevée (environ 159/112), antécédents d'insuffisance cardiaque. Suivi IC et HTA + réadaptation médicamenteuse | N5: HTA | O5: =IFERROR(_xlfn.XLOOKUP($D5, SSP!$F:$F, SSP!$E:$E, "Inconnu"), "") -> Complications maternelles pendant la grossesse (fièvre, œdème, hypertension, travail prématuré) | P5: =IF(OR(E5="", O5=""), "", IF(LOWER(E5)=LOWER(O5), "OK", "⚠️ Libellé ≠ n°")) -> OK | Q5: =IF(Feuil1!$E5="", "", IF(LOWER(Feuil1!$E5)=LOWER(E5), "Identique", "Différent")) -> Différent | R5: =IF(OR(P5="⚠️ Libellé ≠ n°", O5="Inconnu"), "⚠️", IF(Q5="Différent", "ℹ️", "")) -> ℹ️ | S5: {=_xlfn.LET(_xlpm.genCat,IFERROR(LOWER(TRIM(G5)),""),_xlpm.principal,IFERROR(LOWER(TRIM(H5)),""),_xlpm.orig,IFERROR(LOWER(TRIM(N5)),""),IF(OR(_xlpm.genCat="",_xlpm.principal=""),"",IF(LEFT(LOWER(G5),5)="autre","OK (Autre)",IF(OR(ISNUMBER(SEARCH(_xlpm.genCat,_xlpm.principal)),ISNUMBER(SEARCH(_xlpm.principal,_xlpm.genCat)),AND(_xlpm.orig<>"",OR(ISNUMBER(SEARCH(_xlpm.genCat,_xlpm.orig)),ISNUMBER(SEARCH(_xlpm.orig,_xlpm.genCat))))),"OK","⚠️ À vérifier"))))} -> OK | T5: =IF(S5="","",IF(S5="OK (Autre)","Diagnostic générique = 'Autre – …'",IF(S5="OK","Concordance générique/principal","Écart entre générique et principal"))) -> Concordance générique/principal | U5: {=_xlfn.LET(_xlpm.yr, A5, _xlpm.diag, IF(N5<>"", N5, H5), _xlpm.base, TRIM(SUBSTITUTE(SUBSTITUTE(SUBSTITUTE(SUBSTITUTE(_xlpm.diag,"•"," "),CHAR(160)," "),CHAR(10)," ")," "," ")), LOWER(_xlpm.yr&"|"&_xlpm.base))} -> 2011|hta | V5: =IFERROR(_xlfn.XLOOKUP($AB5,'Cas 2013-2017'!$K:$K,'Cas 2013-2017'!$D:$D,""),"") | W5: =IFERROR(_xlfn.XLOOKUP($AB5,'Cas 2013-2017'!$K:$K,'Cas 2013-2017'!$E:$E,""),"") | X5: =IFERROR(_xlfn.XLOOKUP($AB5,'Cas 2013-2017'!$K:$K,'Cas 2013-2017'!$F:$F,""),"") | Y5: =IFERROR(_xlfn.XLOOKUP($AB5,'Cas 2013-2017'!$K:$K,'Cas 2013-2017'!$G:$G,""),"") | Z5: =IFERROR(_xlfn.XLOOKUP($AB5,'Cas 2013-2017'!$K:$K,'Cas 2013-2017'!$I:$I,""),"") | AA5: =IFERROR(_xlfn.XLOOKUP($AB5,'Cas 2013-2017'!$K:$K,'Cas 2013-2017'!$H:$H,""),"") | AB5: =LOWER($A5 & "|" & $AF5) -> 2011|hypertension arterielle | AC5: =TRIM(SUBSTITUTE(SUBSTITUTE(SUBSTITUTE(SUBSTITUTE(" " & LOWER(TRIM(IF($N5<>"", $N5, $H5))) & " ", " aomi ", " arteriopathie des membres inferieurs "), " hta ", " hypertension arterielle "), " saos ", " syndrome d'apnees obstructives du sommeil "), " rgo ", " reflux gastro-oesophagien ") ) -> hypertension arterielle | AD5: =TRIM(SUBSTITUTE(SUBSTITUTE(SUBSTITUTE(SUBSTITUTE(" " & LOWER(TRIM($AC5)) & " ", " oacr ", " occlusion de l'artere centrale de la retine "), " hsd ", " hematome sous-dural "), " fa ", " fibrillation auriculaire "), " ep ", " embolie pulmonaire ") ) -> hypertension arterielle | AE5: {=_xlfn.LET(_xlpm.base, " " & LOWER(TRIM($AD5)) & " ", _xlpm.s1, SUBSTITUTE(_xlpm.base, " ic ", " insuffisance cardiaque "), _xlpm.s2, SUBSTITUTE(_xlpm.s1, " avc ", " accident vasculaire cerebral "), _xlpm.s3, SUBSTITUTE(_xlpm.s2, " hsa ", " hemorragie sous-arachnoidienne "), _xlpm.s4, SUBSTITUTE(_xlpm.s3, " htp ", " hypertension pulmonaire "), _xlpm.s5, SUBSTITUTE(_xlpm.s4, " bpco ", " bronchopneumopathie chronique obstructive "), _xlpm.s6, SUBSTITUTE(_xlpm.s5, " dmla ", " degenerescence maculaire liee a l age "), TRIM(_xlpm.s6))} -> hypertension arterielle | AF5: {=_xlfn.LET(_xlpm.base, " " & LOWER(TRIM($AE5)) & " ", _xlpm.s1, SUBSTITUTE(_xlpm.base, " omi ", " oedemes des membres inferieurs "), _xlpm.s2, SUBSTITUTE(_xlpm.s1, " idm ", " infarctus du myocarde "), _xlpm.s3, SUBSTITUTE(_xlpm.s2, " tvp ", " thrombose veineuse profonde "), _xlpm.s4, SUBSTITUTE(_xlpm.s3, " geu ", " grossesse extra-uterine "), _xlpm.s5, SUBSTITUTE(_xlpm.s4, " fuo ", " fievre d origine indeterminee "), TRIM(_xlpm.s5))} -> hypertension arterielle
A6: 2011 | B6: 🧴 Dermatologie | D6: 93 | E6: =IF(D6="","",IFERROR(INDEX(SSP!$E$2:$E$266, MATCH(D6, SSP!$F$2:$F$266, 0)),"")) -> Macules, papules, pustules, vésicules, ulcères, abcès, bulles, épaississement cutané, nécrose, tumeur cutanée | F6: =Feuil1!E6 -> Éruption cutanée | G6: Psoriasis | H6: Psoriasis | J6: Patient avec psoriasis | K6: Diagnostic avec les images nécessaires. | N6: Psoriasis | O6: =IFERROR(_xlfn.XLOOKUP($D6, SSP!$F:$F, SSP!$E:$E, "Inconnu"), "") -> Macules, papules, pustules, vésicules, ulcères, abcès, bulles, épaississement cutané, nécrose, tumeur cutanée | P6: =IF(OR(E6="", O6=""), "", IF(LOWER(E6)=LOWER(O6), "OK", "⚠️ Libellé ≠ n°")) -> OK | Q6: =IF(Feuil1!$E6="", "", IF(LOWER(Feuil1!$E6)=LOWER(E6), "Identique", "Différent")) -> Différent | R6: =IF(OR(P6="⚠️ Libellé ≠ n°", O6="Inconnu"), "⚠️", IF(Q6="Différent", "ℹ️", "")) -> ℹ️ | S6: {=_xlfn.LET(_xlpm.genCat,IFERROR(LOWER(TRIM(G6)),""),_xlpm.principal,IFERROR(LOWER(TRIM(H6)),""),_xlpm.orig,IFERROR(LOWER(TRIM(N6)),""),IF(OR(_xlpm.genCat="",_xlpm.principal=""),"",IF(LEFT(LOWER(G6),5)="autre","OK (Autre)",IF(OR(ISNUMBER(SEARCH(_xlpm.genCat,_xlpm.principal)),ISNUMBER(SEARCH(_xlpm.principal,_xlpm.genCat)),AND(_xlpm.orig<>"",OR(ISNUMBER(SEARCH(_xlpm.genCat,_xlpm.orig)),ISNUMBER(SEARCH(_xlpm.orig,_xlpm.genCat))))),"OK","⚠️ À vérifier"))))} -> OK | T6: =IF(S6="","",IF(S6="OK (Autre)","Diagnostic générique = 'Autre – …'",IF(S6="OK","Concordance générique/principal","Écart entre générique et principal"))) -> Concordance générique/principal | U6: {=_xlfn.LET(_xlpm.yr, A6, _xlpm.diag, IF(N6<>"", N6, H6), _xlpm.base, TRIM(SUBSTITUTE(SUBSTITUTE(SUBSTITUTE(SUBSTITUTE(_xlpm.diag,"•"," "),CHAR(160)," "),CHAR(10)," ")," "," ")), LOWER(_xlpm.yr&"|"&_xlpm.base))} -> 2011|psoriasis | V6: =IFERROR(_xlfn.XLOOKUP($AB6,'Cas 2013-2017'!$K:$K,'Cas 2013-2017'!$D:$D,""),"") | W6: =IFERROR(_xlfn.XLOOKUP($AB6,'Cas 2013-2017'!$K:$K,'Cas 2013-2017'!$E:$E,""),"") | X6: =IFERROR(_xlfn.XLOOKUP($AB6,'Cas 2013-2017'!$K:$K,'Cas 2013-2017'!$F:$F,""),"") | Y6: =IFERROR(_xlfn.XLOOKUP($AB6,'Cas 2013-2017'!$K:$K,'Cas 2013-2017'!$G:$G,""),"") | Z6: =IFERROR(_xlfn.XLOOKUP($AB6,'Cas 2013-2017'!$K:$K,'Cas 2013-2017'!$I:$I,""),"") | AA6: =IFERROR(_xlfn.XLOOKUP($AB6,'Cas 2013-2017'!$K:$K,'Cas 2013-2017'!$H:$H,""),"") | AB6: =LOWER($A6 & "|" & $AF6) -> 2011|psoriasis | AC6: =TRIM(SUBSTITUTE(SUBSTITUTE(SUBSTITUTE(SUBSTITUTE(" " & LOWER(TRIM(IF($N6<>"", $N6, $H6))) & " ", " aomi ", " arteriopathie des membres inferieurs "), " hta ", " hypertension arterielle "), " saos ", " syndrome d'apnees obstructives du sommeil "), " rgo ", " reflux gastro-oesophagien ") ) -> psoriasis | AD6: =TRIM(SUBSTITUTE(SUBSTITUTE(SUBSTITUTE(SUBSTITUTE(" " & LOWER(TRIM($AC6)) & " ", " oacr ", " occlusion de l'artere centrale de la retine "), " hsd ", " hematome sous-dural "), " fa ", " fibrillation auriculaire "), " ep ", " embolie pulmonaire ") ) -> psoriasis | AE6: {=_xlfn.LET(_xlpm.base, " " & LOWER(TRIM($AD6)) & " ", _xlpm.s1, SUBSTITUTE(_xlpm.base, " ic ", " insuffisance cardiaque "), _xlpm.s2, SUBSTITUTE(_xlpm.s1, " avc ", " accident vasculaire cerebral "), _xlpm.s3, SUBSTITUTE(_xlpm.s2, " hsa ", " hemorragie sous-arachnoidienne "), _xlpm.s4, SUBSTITUTE(_xlpm.s3, " htp ", " hypertension pulmonaire "), _xlpm.s5, SUBSTITUTE(_xlpm.s4, " bpco ", " bronchopneumopathie chronique obstructive "), _xlpm.s6, SUBSTITUTE(_xlpm.s5, " dmla ", " degenerescence maculaire liee a l age "), TRIM(_xlpm.s6))} -> psoriasis | AF6: {=_xlfn.LET(_xlpm.base, " " & LOWER(TRIM($AE6)) & " ", _xlpm.s1, SUBSTITUTE(_xlpm.base, " omi ", " oedemes des membres inferieurs "), _xlpm.s2, SUBSTITUTE(_xlpm.s1, " idm ", " infarctus du myocarde "), _xlpm.s3, SUBSTITUTE(_xlpm.s2, " tvp ", " thrombose veineuse profonde "), _xlpm.s4, SUBSTITUTE(_xlpm.s3, " geu ", " grossesse extra-uterine "), _xlpm.s5, SUBSTITUTE(_xlpm.s4, " fuo ", " fievre d origine indeterminee "), TRIM(_xlpm.s5))} -> psoriasis
A7: 2011 | C7: Entretien motivationnel | D7: 130 | E7: =IF(D7="","",IFERROR(INDEX(SSP!$E$2:$E$266, MATCH(D7, SSP!$F$2:$F$266, 0)),"")) -> Usage non médical de substances, dépendance (tabac, alcool, drogues, jeux, etc.) | F7: =Feuil1!E7 -> Abus d'alcool | G7: Trouble lié aux substances | H7: Addiction | J7: Abus d'alcool | K7: Faire revenir le patient, il voyait pas le problème puisqu'il "ne buvait pas au travail", que 0.51 de vin le soir et ça plus des bières le wee. | N7: Addiction | O7: =IFERROR(_xlfn.XLOOKUP($D7, SSP!$F:$F, SSP!$E:$E, "Inconnu"), "") -> Usage non médical de substances, dépendance (tabac, alcool, drogues, jeux, etc.) | P7: =IF(OR(E7="", O7=""), "", IF(LOWER(E7)=LOWER(O7), "OK", "⚠️ Libellé ≠ n°")) -> OK | Q7: =IF(Feuil1!$E7="", "", IF(LOWER(Feuil1!$E7)=LOWER(E7), "Identique", "Différent")) -> Différent | R7: =IF(OR(P7="⚠️ Libellé ≠ n°", O7="Inconnu"), "⚠️", IF(Q7="Différent", "ℹ️", "")) -> ℹ️ | S7: {=_xlfn.LET(_xlpm.genCat,IFERROR(LOWER(TRIM(G7)),""),_xlpm.principal,IFERROR(LOWER(TRIM(H7)),""),_xlpm.orig,IFERROR(LOWER(TRIM(N7)),""),IF(OR(_xlpm.genCat="",_xlpm.principal=""),"",IF(LEFT(LOWER(G7),5)="autre","OK (Autre)",IF(OR(ISNUMBER(SEARCH(_xlpm.genCat,_xlpm.principal)),ISNUMBER(SEARCH(_xlpm.principal,_xlpm.genCat)),AND(_xlpm.orig<>"",OR(ISNUMBER(SEARCH(_xlpm.genCat,_xlpm.orig)),ISNUMBER(SEARCH(_xlpm.orig,_xlpm.genCat))))),"OK","⚠️ À vérifier"))))} -> ⚠️ À vérifier | T7: =IF(S7="","",IF(S7="OK (Autre)","Diagnostic générique = 'Autre – …'",IF(S7="OK","Concordance générique/principal","Écart entre générique et principal"))) -> Écart entre générique et principal | U7: {=_xlfn.LET(_xlpm.yr, A7, _xlpm.diag, IF(N7<>"", N7, H7), _xlpm.base, TRIM(SUBSTITUTE(SUBSTITUTE(SUBSTITUTE(SUBSTITUTE(_xlpm.diag,"•"," "),CHAR(160)," "),CHAR(10)," ")," "," ")), LOWER(_xlpm.yr&"|"&_xlpm.base))} -> 2011|addiction | V7: =IFERROR(_xlfn.XLOOKUP($AB7,'Cas 2013-2017'!$K:$K,'Cas 2013-2017'!$D:$D,""),"") | W7: =IFERROR(_xlfn.XLOOKUP($AB7,'Cas 2013-2017'!$K:$K,'Cas 2013-2017'!$E:$E,""),"") | X7: =IFERROR(_xlfn.XLOOKUP($AB7,'Cas 2013-2017'!$K:$K,'Cas 2013-2017'!$F:$F,""),"") | Y7: =IFERROR(_xlfn.XLOOKUP($AB7,'Cas 2013-2017'!$K:$K,'Cas 2013-2017'!$G:$G,""),"") | Z7: =IFERROR(_xlfn.XLOOKUP($AB7,'Cas 2013-2017'!$K:$K,'Cas 2013-2017'!$I:$I,""),"") | AA7: =IFERROR(_xlfn.XLOOKUP($AB7,'Cas 2013-2017'!$K:$K,'Cas 2013-2017'!$H:$H,""),"") | AB7: =LOWER($A7 & "|" & $AF7) -> 2011|addiction | AC7: =TRIM(SUBSTITUTE(SUBSTITUTE(SUBSTITUTE(SUBSTITUTE(" " & LOWER(TRIM(IF($N7<>"", $N7, $H7))) & " ", " aomi ", " arteriopathie des membres inferieurs "), " hta ", " hypertension arterielle "), " saos ", " syndrome d'apnees obstructives du sommeil "), " rgo ", " reflux gastro-oesophagien ") ) -> addiction | AD7: =TRIM(SUBSTITUTE(SUBSTITUTE(SUBSTITUTE(SUBSTITUTE(" " & LOWER(TRIM($AC7)) & " ", " oacr ", " occlusion de l'artere centrale de la retine "), " hsd ", " hematome sous-dural "), " fa ", " fibrillation auriculaire "), " ep ", " embolie pulmonaire ") ) -> addiction | AE7: {=_xlfn.LET(_xlpm.base, " " & LOWER(TRIM($AD7)) & " ", _xlpm.s1, SUBSTITUTE(_xlpm.base, " ic ", " insuffisance cardiaque "), _xlpm.s2, SUBSTITUTE(_xlpm.s1, " avc ", " accident vasculaire cerebral "), _xlpm.s3, SUBSTITUTE(_xlpm.s2, " hsa ", " hemorragie sous-arachnoidienne "), _xlpm.s4, SUBSTITUTE(_xlpm.s3, " htp ", " hypertension pulmonaire "), _xlpm.s5, SUBSTITUTE(_xlpm.s4, " bpco ", " bronchopneumopathie chronique obstructive "), _xlpm.s6, SUBSTITUTE(_xlpm.s5, " dmla ", " degenerescence maculaire liee a l age "), TRIM(_xlpm.s6))} -> addiction | AF7: {=_xlfn.LET(_xlpm.base, " " & LOWER(TRIM($AE7)) & " ", _xlpm.s1, SUBSTITUTE(_xlpm.base, " omi ", " oedemes des membres inferieurs "), _xlpm.s2, SUBSTITUTE(_xlpm.s1, " idm ", " infarctus du myocarde "), _xlpm.s3, SUBSTITUTE(_xlpm.s2, " tvp ", " thrombose veineuse profonde "), _xlpm.s4, SUBSTITUTE(_xlpm.s3, " geu ", " grossesse extra-uterine "), _xlpm.s5, SUBSTITUTE(_xlpm.s4, " fuo ", " fievre d origine indeterminee "), TRIM(_xlpm.s5))} -> addiction
A8: 2011 | B8: 🧪 Endocrinologie / Métabolisme | D8: 4 | E8: =IF(D8="","",IFERROR(INDEX(SSP!$E$2:$E$266, MATCH(D8, SSP!$F$2:$F$266, 0)),"")) -> Fatigue, asthénie | F8: =Feuil1!E8 -> Fatigue | G8: Hypothyroïdie | H8: Hypothyroïdie | J8: Jeune femme avec histoire classique : Fatigue, froid, chute de cheveux, sécheresse, bradycardie, prise de poids | N8: Hypothyroidie | O8: =IFERROR(_xlfn.XLOOKUP($D8, SSP!$F:$F, SSP!$E:$E, "Inconnu"), "") -> Fatigue, asthénie | P8: =IF(OR(E8="", O8=""), "", IF(LOWER(E8)=LOWER(O8), "OK", "⚠️ Libellé ≠ n°")) -> OK | Q8: =IF(Feuil1!$E8="", "", IF(LOWER(Feuil1!$E8)=LOWER(E8), "Identique", "Différent")) -> Différent | R8: =IF(OR(P8="⚠️ Libellé ≠ n°", O8="Inconnu"), "⚠️", IF(Q8="Différent", "ℹ️", "")) -> ℹ️ | S8: {=_xlfn.LET(_xlpm.genCat,IFERROR(LOWER(TRIM(G8)),""),_xlpm.principal,IFERROR(LOWER(TRIM(H8)),""),_xlpm.orig,IFERROR(LOWER(TRIM(N8)),""),IF(OR(_xlpm.genCat="",_xlpm.principal=""),"",IF(LEFT(LOWER(G8),5)="autre","OK (Autre)",IF(OR(ISNUMBER(SEARCH(_xlpm.genCat,_xlpm.principal)),ISNUMBER(SEARCH(_xlpm.principal,_xlpm.genCat)),AND(_xlpm.orig<>"",OR(ISNUMBER(SEARCH(_xlpm.genCat,_xlpm.orig)),ISNUMBER(SEARCH(_xlpm.orig,_xlpm.genCat))))),"OK","⚠️ À vérifier"))))} -> OK | T8: =IF(S8="","",IF(S8="OK (Autre)","Diagnostic générique = 'Autre – …'",IF(S8="OK","Concordance générique/principal","Écart entre générique et principal"))) -> Concordance générique/principal | U8: {=_xlfn.LET(_xlpm.yr, A8, _xlpm.diag, IF(N8<>"", N8, H8), _xlpm.base, TRIM(SUBSTITUTE(SUBSTITUTE(SUBSTITUTE(SUBSTITUTE(_xlpm.diag,"•"," "),CHAR(160)," "),CHAR(10)," ")," "," ")), LOWER(_xlpm.yr&"|"&_xlpm.base))} -> 2011|hypothyroidie | V8: =IFERROR(_xlfn.XLOOKUP($AB8,'Cas 2013-2017'!$K:$K,'Cas 2013-2017'!$D:$D,""),"") | W8: =IFERROR(_xlfn.XLOOKUP($AB8,'Cas 2013-2017'!$K:$K,'Cas 2013-2017'!$E:$E,""),"") | X8: =IFERROR(_xlfn.XLOOKUP($AB8,'Cas 2013-2017'!$K:$K,'Cas 2013-2017'!$F:$F,""),"") | Y8: =IFERROR(_xlfn.XLOOKUP($AB8,'Cas 2013-2017'!$K:$K,'Cas 2013-2017'!$G:$G,""),"") | Z8: =IFERROR(_xlfn.XLOOKUP($AB8,'Cas 2013-2017'!$K:$K,'Cas 2013-2017'!$I:$I,""),"") | AA8: =IFERROR(_xlfn.XLOOKUP($AB8,'Cas 2013-2017'!$K:$K,'Cas 2013-2017'!$H:$H,""),"") | AB8: =LOWER($A8 & "|" & $AF8) -> 2011|hypothyroidie | AC8: =TRIM(SUBSTITUTE(SUBSTITUTE(SUBSTITUTE(SUBSTITUTE(" " & LOWER(TRIM(IF($N8<>"", $N8, $H8))) & " ", " aomi ", " arteriopathie des membres inferieurs "), " hta ", " hypertension arterielle "), " saos ", " syndrome d'apnees obstructives du sommeil "), " rgo ", " reflux gastro-oesophagien ") ) -> hypothyroidie | AD8: =TRIM(SUBSTITUTE(SUBSTITUTE(SUBSTITUTE(SUBSTITUTE(" " & LOWER(TRIM($AC8)) & " ", " oacr ", " occlusion de l'artere centrale de la retine "), " hsd ", " hematome sous-dural "), " fa ", " fibrillation auriculaire "), " ep ", " embolie pulmonaire ") ) -> hypothyroidie | AE8: {=_xlfn.LET(_xlpm.base, " " & LOWER(TRIM($AD8)) & " ", _xlpm.s1, SUBSTITUTE(_xlpm.base, " ic ", " insuffisance cardiaque "), _xlpm.s2, SUBSTITUTE(_xlpm.s1, " avc ", " accident vasculaire cerebral "), _xlpm.s3, SUBSTITUTE(_xlpm.s2, " hsa ", " hemorragie sous-arachnoidienne "), _xlpm.s4, SUBSTITUTE(_xlpm.s3, " htp ", " hypertension pulmonaire "), _xlpm.s5, SUBSTITUTE(_xlpm.s4, " bpco ", " bronchopneumopathie chronique obstructive "), _xlpm.s6, SUBSTITUTE(_xlpm.s5, " dmla ", " degenerescence maculaire liee a l age "), TRIM(_xlpm.s6))} -> hypothyroidie | AF8: {=_xlfn.LET(_xlpm.base, " " & LOWER(TRIM($AE8)) & " ", _xlpm.s1, SUBSTITUTE(_xlpm.base, " omi ", " oedemes des membres inferieurs "), _xlpm.s2, SUBSTITUTE(_xlpm.s1, " idm ", " infarctus du myocarde "), _xlpm.s3, SUBSTITUTE(_xlpm.s2, " tvp ", " thrombose veineuse profonde "), _xlpm.s4, SUBSTITUTE(_xlpm.s3, " geu ", " grossesse extra-uterine "), _xlpm.s5, SUBSTITUTE(_xlpm.s4, " fuo ", " fievre d origine indeterminee "), TRIM(_xlpm.s5))} -> hypothyroidie
A9: 2011 | B9: 🧬 Oncologie / Hématologie | D9: 91 | E9: =IF(D9="","",IFERROR(INDEX(SSP!$E$2:$E$266, MATCH(D9, SSP!$F$2:$F$266, 0)),"")) -> Ictère | F9: =Feuil1!E9 -> Ictère | G9: Cancer | H9: Carcinome hépatocellulaire | J9: Homme avec ictère, consommation d'alcool et perte de poids. | N9: Carcinome hépatocellulaire | O9: =IFERROR(_xlfn.XLOOKUP($D9, SSP!$F:$F, SSP!$E:$E, "Inconnu"), "") -> Ictère | P9: =IF(OR(E9="", O9=""), "", IF(LOWER(E9)=LOWER(O9), "OK", "⚠️ Libellé ≠ n°")) -> OK | Q9: =IF(Feuil1!$E9="", "", IF(LOWER(Feuil1!$E9)=LOWER(E9), "Identique", "Différent")) -> Identique | R9: =IF(OR(P9="⚠️ Libellé ≠ n°", O9="Inconnu"), "⚠️", IF(Q9="Différent", "ℹ️", "")) | S9: {=_xlfn.LET(_xlpm.genCat,IFERROR(LOWER(TRIM(G9)),""),_xlpm.principal,IFERROR(LOWER(TRIM(H9)),""),_xlpm.orig,IFERROR(LOWER(TRIM(N9)),""),IF(OR(_xlpm.genCat="",_xlpm.principal=""),"",IF(LEFT(LOWER(G9),5)="autre","OK (Autre)",IF(OR(ISNUMBER(SEARCH(_xlpm.genCat,_xlpm.principal)),ISNUMBER(SEARCH(_xlpm.principal,_xlpm.genCat)),AND(_xlpm.orig<>"",OR(ISNUMBER(SEARCH(_xlpm.genCat,_xlpm.orig)),ISNUMBER(SEARCH(_xlpm.orig,_xlpm.genCat))))),"OK","⚠️ À vérifier"))))} -> ⚠️ À vérifier | T9: =IF(S9="","",IF(S9="OK (Autre)","Diagnostic générique = 'Autre – …'",IF(S9="OK","Concordance générique/principal","Écart entre générique et principal"))) -> Écart entre générique et principal | U9: {=_xlfn.LET(_xlpm.yr, A9, _xlpm.diag, IF(N9<>"", N9, H9), _xlpm.base, TRIM(SUBSTITUTE(SUBSTITUTE(SUBSTITUTE(SUBSTITUTE(_xlpm.diag,"•"," "),CHAR(160)," "),CHAR(10)," ")," "," ")), LOWER(_xlpm.yr&"|"&_xlpm.base))} -> 2011|carcinome hépatocellulaire | V9: =IFERROR(_xlfn.XLOOKUP($AB9,'Cas 2013-2017'!$K:$K,'Cas 2013-2017'!$D:$D,""),"") | W9: =IFERROR(_xlfn.XLOOKUP($AB9,'Cas 2013-2017'!$K:$K,'Cas 2013-2017'!$E:$E,""),"") | X9: =IFERROR(_xlfn.XLOOKUP($AB9,'Cas 2013-2017'!$K:$K,'Cas 2013-2017'!$F:$F,""),"") | Y9: =IFERROR(_xlfn.XLOOKUP($AB9,'Cas 2013-2017'!$K:$K,'Cas 2013-2017'!$G:$G,""),"") | Z9: =IFERROR(_xlfn.XLOOKUP($AB9,'Cas 2013-2017'!$K:$K,'Cas 2013-2017'!$I:$I,""),"") | AA9: =IFERROR(_xlfn.XLOOKUP($AB9,'Cas 2013-2017'!$K:$K,'Cas 2013-2017'!$H:$H,""),"") | AB9: =LOWER($A9 & "|" & $AF9) -> 2011|carcinome hépatocellulaire | AC9: =TRIM(SUBSTITUTE(SUBSTITUTE(SUBSTITUTE(SUBSTITUTE(" " & LOWER(TRIM(IF($N9<>"", $N9, $H9))) & " ", " aomi ", " arteriopathie des membres inferieurs "), " hta ", " hypertension arterielle "), " saos ", " syndrome d'apnees obstructives du sommeil "), " rgo ", " reflux gastro-oesophagien ") ) -> carcinome hépatocellulaire | AD9: =TRIM(SUBSTITUTE(SUBSTITUTE(SUBSTITUTE(SUBSTITUTE(" " & LOWER(TRIM($AC9)) & " ", " oacr ", " occlusion de l'artere centrale de la retine "), " hsd ", " hematome sous-dural "), " fa ", " fibrillation auriculaire "), " ep ", " embolie pulmonaire ") ) -> carcinome hépatocellulaire | AE9: {=_xlfn.LET(_xlpm.base, " " & LOWER(TRIM($AD9)) & " ", _xlpm.s1, SUBSTITUTE(_xlpm.base, " ic ", " insuffisance cardiaque "), _xlpm.s2, SUBSTITUTE(_xlpm.s1, " avc ", " accident vasculaire cerebral "), _xlpm.s3, SUBSTITUTE(_xlpm.s2, " hsa ", " hemorragie sous-arachnoidienne "), _xlpm.s4, SUBSTITUTE(_xlpm.s3, " htp ", " hypertension pulmonaire "), _xlpm.s5, SUBSTITUTE(_xlpm.s4, " bpco ", " bronchopneumopathie chronique obstructive "), _xlpm.s6, SUBSTITUTE(_xlpm.s5, " dmla ", " degenerescence maculaire liee a l age "), TRIM(_xlpm.s6))} -> carcinome hépatocellulaire | AF9: {=_xlfn.LET(_xlpm.base, " " & LOWER(TRIM($AE9)) & " ", _xlpm.s1, SUBSTITUTE(_xlpm.base, " omi ", " oedemes des membres inferieurs "), _xlpm.s2, SUBSTITUTE(_xlpm.s1, " idm ", " infarctus du myocarde "), _xlpm.s3, SUBSTITUTE(_xlpm.s2, " tvp ", " thrombose veineuse profonde "), _xlpm.s4, SUBSTITUTE(_xlpm.s3, " geu ", " grossesse extra-uterine "), _xlpm.s5, SUBSTITUTE(_xlpm.s4, " fuo ", " fievre d origine indeterminee "), TRIM(_xlpm.s5))} -> carcinome hépatocellulaire
A10: 2011 | B10: 🍴 Gastro-entérologie / Hépatologie | D10: 59 | E10: =IF(D10="","",IFERROR(INDEX(SSP!$E$2:$E$266, MATCH(D10, SSP!$F$2:$F$266, 0)),"")) -> Diarrhée | F10: =Feuil1!E10 -> Diarrhée | G10: Gastro-entérite | H10: Diarrhée du voyageur | J10: Jeune femme avec antécédents de voyage, désire un médicament. | N10: Diarrhée du voyageur | O10: =IFERROR(_xlfn.XLOOKUP($D10, SSP!$F:$F, SSP!$E:$E, "Inconnu"), "") -> Diarrhée | P10: =IF(OR(E10="", O10=""), "", IF(LOWER(E10)=LOWER(O10), "OK", "⚠️ Libellé ≠ n°")) -> OK | Q10: =IF(Feuil1!$E10="", "", IF(LOWER(Feuil1!$E10)=LOWER(E10), "Identique", "Différent")) -> Identique | R10: =IF(OR(P10="⚠️ Libellé ≠ n°", O10="Inconnu"), "⚠️", IF(Q10="Différent", "ℹ️", "")) | S10: {=_xlfn.LET(_xlpm.genCat,IFERROR(LOWER(TRIM(G10)),""),_xlpm.principal,IFERROR(LOWER(TRIM(H10)),""),_xlpm.orig,IFERROR(LOWER(TRIM(N10)),""),IF(OR(_xlpm.genCat="",_xlpm.principal=""),"",IF(LEFT(LOWER(G10),5)="autre","OK (Autre)",IF(OR(ISNUMBER(SEARCH(_xlpm.genCat,_xlpm.principal)),ISNUMBER(SEARCH(_xlpm.principal,_xlpm.genCat)),AND(_xlpm.orig<>"",OR(ISNUMBER(SEARCH(_xlpm.genCat,_xlpm.orig)),ISNUMBER(SEARCH(_xlpm.orig,_xlpm.genCat))))),"OK","⚠️ À vérifier"))))} -> ⚠️ À vérifier | T10: =IF(S10="","",IF(S10="OK (Autre)","Diagnostic générique = 'Autre – …'",IF(S10="OK","Concordance générique/principal","Écart entre générique et principal"))) -> Écart entre générique et principal | U10: {=_xlfn.LET(_xlpm.yr, A10, _xlpm.diag, IF(N10<>"", N10, H10), _xlpm.base, TRIM(SUBSTITUTE(SUBSTITUTE(SUBSTITUTE(SUBSTITUTE(_xlpm.diag,"•"," "),CHAR(160)," "),CHAR(10)," ")," "," ")), LOWER(_xlpm.yr&"|"&_xlpm.base))} -> 2011|diarrhée du voyageur | V10: =IFERROR(_xlfn.XLOOKUP($AB10,'Cas 2013-2017'!$K:$K,'Cas 2013-2017'!$D:$D,""),"") | W10: =IFERROR(_xlfn.XLOOKUP($AB10,'Cas 2013-2017'!$K:$K,'Cas 2013-2017'!$E:$E,""),"") | X10: =IFERROR(_xlfn.XLOOKUP($AB10,'Cas 2013-2017'!$K:$K,'Cas 2013-2017'!$F:$F,""),"") | Y10: =IFERROR(_xlfn.XLOOKUP($AB10,'Cas 2013-2017'!$K:$K,'Cas 2013-2017'!$G:$G,""),"") | Z10: =IFERROR(_xlfn.XLOOKUP($AB10,'Cas 2013-2017'!$K:$K,'Cas 2013-2017'!$I:$I,""),"") | AA10: =IFERROR(_xlfn.XLOOKUP($AB10,'Cas 2013-2017'!$K:$K,'Cas 2013-2017'!$H:$H,""),"") | AB10: =LOWER($A10 & "|" & $AF10) -> 2011|diarrhée du voyageur | AC10: =TRIM(SUBSTITUTE(SUBSTITUTE(SUBSTITUTE(SUBSTITUTE(" " & LOWER(TRIM(IF($N10<>"", $N10, $H10))) & " ", " aomi ", " arteriopathie des membres inferieurs "), " hta ", " hypertension arterielle "), " saos ", " syndrome d'apnees obstructives du sommeil "), " rgo ", " reflux gastro-oesophagien ") ) -> diarrhée du voyageur | AD10: =TRIM(SUBSTITUTE(SUBSTITUTE(SUBSTITUTE(SUBSTITUTE(" " & LOWER(TRIM($AC10)) & " ", " oacr ", " occlusion de l'artere centrale de la retine "), " hsd ", " hematome sous-dural "), " fa ", " fibrillation auriculaire "), " ep ", " embolie pulmonaire ") ) -> diarrhée du voyageur | AE10: {=_xlfn.LET(_xlpm.base, " " & LOWER(TRIM($AD10)) & " ", _xlpm.s1, SUBSTITUTE(_xlpm.base, " ic ", " insuffisance cardiaque "), _xlpm.s2, SUBSTITUTE(_xlpm.s1, " avc ", " accident vasculaire cerebral "), _xlpm.s3, SUBSTITUTE(_xlpm.s2, " hsa ", " hemorragie sous-arachnoidienne "), _xlpm.s4, SUBSTITUTE(_xlpm.s3, " htp ", " hypertension pulmonaire "), _xlpm.s5, SUBSTITUTE(_xlpm.s4, " bpco ", " bronchopneumopathie chronique obstructive "), _xlpm.s6, SUBSTITUTE(_xlpm.s5, " dmla ", " degenerescence maculaire liee a l age "), TRIM(_xlpm.s6))} -> diarrhée du voyageur | AF10: {=_xlfn.LET(_xlpm.base, " " & LOWER(TRIM($AE10)) & " ", _xlpm.s1, SUBSTITUTE(_xlpm.base, " omi ", " oedemes des membres inferieurs "), _xlpm.s2, SUBSTITUTE(_xlpm.s1, " idm ", " infarctus du myocarde "), _xlpm.s3, SUBSTITUTE(_xlpm.s2, " tvp ", " thrombose veineuse profonde "), _xlpm.s4, SUBSTITUTE(_xlpm.s3, " geu ", " grossesse extra-uterine "), _xlpm.s5, SUBSTITUTE(_xlpm.s4, " fuo ", " fievre d origine indeterminee "), TRIM(_xlpm.s5))} -> diarrhée du voyageur
A11: 2011 | B11: 🧪 Endocrinologie / Métabolisme | D11: 224 | E11: =IF(D11="","",IFERROR(INDEX(SSP!$E$2:$E$266, MATCH(D11, SSP!$F$2:$F$266, 0)),"")) -> Demande de bilan de santé, d’examens radiologiques ou biologiques | F11: =Feuil1!E11 -> Bilan | G11: Trouble du métabolisme du fer | H11: Hémochromatose | I11: Hépatite virale / Maladie de Wilson | J11: Homme de 50 ans, visite de contrôle à cause d'un infarctus du myocarde chez son frère. | K11: Transaminases augmentées de 3 fois. Confusion sur la cause, aucun antécédent hépatique familial, consommation d'alcool modérée. Investigation nécessaire de toutes les causes possibles. | N11: Hémochromatose | O11: =IFERROR(_xlfn.XLOOKUP($D11, SSP!$F:$F, SSP!$E:$E, "Inconnu"), "") -> Demande de bilan de santé, d’examens radiologiques ou biologiques | P11: =IF(OR(E11="", O11=""), "", IF(LOWER(E11)=LOWER(O11), "OK", "⚠️ Libellé ≠ n°")) -> OK | Q11: =IF(Feuil1!$E11="", "", IF(LOWER(Feuil1!$E11)=LOWER(E11), "Identique", "Différent")) -> Différent | R11: =IF(OR(P11="⚠️ Libellé ≠ n°", O11="Inconnu"), "⚠️", IF(Q11="Différent", "ℹ️", "")) -> ℹ️ | S11: {=_xlfn.LET(_xlpm.genCat,IFERROR(LOWER(TRIM(G11)),""),_xlpm.principal,IFERROR(LOWER(TRIM(H11)),""),_xlpm.orig,IFERROR(LOWER(TRIM(N11)),""),IF(OR(_xlpm.genCat="",_xlpm.principal=""),"",IF(LEFT(LOWER(G11),5)="autre","OK (Autre)",IF(OR(ISNUMBER(SEARCH(_xlpm.genCat,_xlpm.principal)),ISNUMBER(SEARCH(_xlpm.principal,_xlpm.genCat)),AND(_xlpm.orig<>"",OR(ISNUMBER(SEARCH(_xlpm.genCat,_xlpm.orig)),ISNUMBER(SEARCH(_xlpm.orig,_xlpm.genCat))))),"OK","⚠️ À vérifier"))))} -> ⚠️ À vérifier | T11: =IF(S11="","",IF(S11="OK (Autre)","Diagnostic générique = 'Autre – …'",IF(S11="OK","Concordance générique/principal","Écart entre générique et principal"))) -> Écart entre générique et principal | U11: {=_xlfn.LET(_xlpm.yr, A11, _xlpm.diag, IF(N11<>"", N11, H11), _xlpm.base, TRIM(SUBSTITUTE(SUBSTITUTE(SUBSTITUTE(SUBSTITUTE(_xlpm.diag,"•"," "),CHAR(160)," "),CHAR(10)," ")," "," ")), LOWER(_xlpm.yr&"|"&_xlpm.base))} -> 2011|hémochromatose | V11: =IFERROR(_xlfn.XLOOKUP($AB11,'Cas 2013-2017'!$K:$K,'Cas 2013-2017'!$D:$D,""),"") | W11: =IFERROR(_xlfn.XLOOKUP($AB11,'Cas 2013-2017'!$K:$K,'Cas 2013-2017'!$E:$E,""),"") | X11: =IFERROR(_xlfn.XLOOKUP($AB11,'Cas 2013-2017'!$K:$K,'Cas 2013-2017'!$F:$F,""),"") | Y11: =IFERROR(_xlfn.XLOOKUP($AB11,'Cas 2013-2017'!$K:$K,'Cas 2013-2017'!$G:$G,""),"") | Z11: =IFERROR(_xlfn.XLOOKUP($AB11,'Cas 2013-2017'!$K:$K,'Cas 2013-2017'!$I:$I,""),"") | AA11: =IFERROR(_xlfn.XLOOKUP($AB11,'Cas 2013-2017'!$K:$K,'Cas 2013-2017'!$H:$H,""),"") | AB11: =LOWER($A11 & "|" & $AF11) -> 2011|hémochromatose | AC11: =TRIM(SUBSTITUTE(SUBSTITUTE(SUBSTITUTE(SUBSTITUTE(" " & LOWER(TRIM(IF($N11<>"", $N11, $H11))) & " ", " aomi ", " arteriopathie des membres inferieurs "), " hta ", " hypertension arterielle "), " saos ", " syndrome d'apnees obstructives du sommeil "), " rgo ", " reflux gastro-oesophagien ") ) -> hémochromatose | AD11: =TRIM(SUBSTITUTE(SUBSTITUTE(SUBSTITUTE(SUBSTITUTE(" " & LOWER(TRIM($AC11)) & " ", " oacr ", " occlusion de l'artere centrale de la retine "), " hsd ", " hematome sous-dural "), " fa ", " fibrillation auriculaire "), " ep ", " embolie pulmonaire ") ) -> hémochromatose | AE11: {=_xlfn.LET(_xlpm.base, " " & LOWER(TRIM($AD11)) & " ", _xlpm.s1, SUBSTITUTE(_xlpm.base, " ic ", " insuffisance cardiaque "), _xlpm.s2, SUBSTITUTE(_xlpm.s1, " avc ", " accident vasculaire cerebral "), _xlpm.s3, SUBSTITUTE(_xlpm.s2, " hsa ", " hemorragie sous-arachnoidienne "), _xlpm.s4, SUBSTITUTE(_xlpm.s3, " htp ", " hypertension pulmonaire "), _xlpm.s5, SUBSTITUTE(_xlpm.s4, " bpco ", " bronchopneumopathie chronique obstructive "), _xlpm.s6, SUBSTITUTE(_xlpm.s5, " dmla ", " degenerescence maculaire liee a l age "), TRIM(_xlpm.s6))} -> hémochromatose | AF11: {=_xlfn.LET(_xlpm.base, " " & LOWER(TRIM($AE11)) & " ", _xlpm.s1, SUBSTITUTE(_xlpm.base, " omi ", " oedemes des membres inferieurs "), _xlpm.s2, SUBSTITUTE(_xlpm.s1, " idm ", " infarctus du myocarde "), _xlpm.s3, SUBSTITUTE(_xlpm.s2, " tvp ", " thrombose veineuse profonde "), _xlpm.s4, SUBSTITUTE(_xlpm.s3, " geu ", " grossesse extra-uterine "), _xlpm.s5, SUBSTITUTE(_xlpm.s4, " fuo ", " fievre d origine indeterminee "), TRIM(_xlpm.s5))} -> hémochromatose
A12: 2011 | B12: 🍴 Gastro-entérologie / Hépatologie | D12: 52 | E12: =IF(D12="","",IFERROR(INDEX(SSP!$E$2:$E$266, MATCH(D12, SSP!$F$2:$F$266, 0)),"")) -> Douleur abdominale ou épigastrique | F12: =Feuil1!E12 -> Douleur abdominale | G12: Hépatite | H12: Hépatite alcoolique | J12: Homme âgé avec douleur pressante dans l'hypocondre droit, antécédents de consommation d'alcool. | K12: Examen important et complet nécessaire. | N12: Hépatite alcoolique. | O12: =IFERROR(_xlfn.XLOOKUP($D12, SSP!$F:$F, SSP!$E:$E, "Inconnu"), "") -> Douleur abdominale ou épigastrique | P12: =IF(OR(E12="", O12=""), "", IF(LOWER(E12)=LOWER(O12), "OK", "⚠️ Libellé ≠ n°")) -> OK | Q12: =IF(Feuil1!$E12="", "", IF(LOWER(Feuil1!$E12)=LOWER(E12), "Identique", "Différent")) -> Différent | R12: =IF(OR(P12="⚠️ Libellé ≠ n°", O12="Inconnu"), "⚠️", IF(Q12="Différent", "ℹ️", "")) -> ℹ️ | S12: {=_xlfn.LET(_xlpm.genCat,IFERROR(LOWER(TRIM(G12)),""),_xlpm.principal,IFERROR(LOWER(TRIM(H12)),""),_xlpm.orig,IFERROR(LOWER(TRIM(N12)),""),IF(OR(_xlpm.genCat="",_xlpm.principal=""),"",IF(LEFT(LOWER(G12),5)="autre","OK (Autre)",IF(OR(ISNUMBER(SEARCH(_xlpm.genCat,_xlpm.principal)),ISNUMBER(SEARCH(_xlpm.principal,_xlpm.genCat)),AND(_xlpm.orig<>"",OR(ISNUMBER(SEARCH(_xlpm.genCat,_xlpm.orig)),ISNUMBER(SEARCH(_xlpm.orig,_xlpm.genCat))))),"OK","⚠️ À vérifier"))))} -> OK | T12: =IF(S12="","",IF(S12="OK (Autre)","Diagnostic générique = 'Autre – …'",IF(S12="OK","Concordance générique/principal","Écart entre générique et principal"))) -> Concordance générique/principal | U12: {=_xlfn.LET(_xlpm.yr, A12, _xlpm.diag, IF(N12<>"", N12, H12), _xlpm.base, TRIM(SUBSTITUTE(SUBSTITUTE(SUBSTITUTE(SUBSTITUTE(_xlpm.diag,"•"," "),CHAR(160)," "),CHAR(10)," ")," "," ")), LOWER(_xlpm.yr&"|"&_xlpm.base))} -> 2011|hépatite alcoolique. | V12: =IFERROR(_xlfn.XLOOKUP($AB12,'Cas 2013-2017'!$K:$K,'Cas 2013-2017'!$D:$D,""),"") | W12: =IFERROR(_xlfn.XLOOKUP($AB12,'Cas 2013-2017'!$K:$K,'Cas 2013-2017'!$E:$E,""),"") | X12: =IFERROR(_xlfn.XLOOKUP($AB12,'Cas 2013-2017'!$K:$K,'Cas 2013-2017'!$F:$F,""),"") | Y12: =IFERROR(_xlfn.XLOOKUP($AB12,'Cas 2013-2017'!$K:$K,'Cas 2013-2017'!$G:$G,""),"") | Z12: =IFERROR(_xlfn.XLOOKUP($AB12,'Cas 2013-2017'!$K:$K,'Cas 2013-2017'!$I:$I,""),"") | AA12: =IFERROR(_xlfn.XLOOKUP($AB12,'Cas 2013-2017'!$K:$K,'Cas 2013-2017'!$H:$H,""),"") | AB12: =LOWER($A12 & "|" & $AF12) -> 2011|hépatite alcoolique. | AC12: =TRIM(SUBSTITUTE(SUBSTITUTE(SUBSTITUTE(SUBSTITUTE(" " & LOWER(TRIM(IF($N12<>"", $N12, $H12))) & " ", " aomi ", " arteriopathie des membres inferieurs "), " hta ", " hypertension arterielle "), " saos ", " syndrome d'apnees obstructives du sommeil "), " rgo ", " reflux gastro-oesophagien ") ) -> hépatite alcoolique. | AD12: =TRIM(SUBSTITUTE(SUBSTITUTE(SUBSTITUTE(SUBSTITUTE(" " & LOWER(TRIM($AC12)) & " ", " oacr ", " occlusion de l'artere centrale de la retine "), " hsd ", " hematome sous-dural "), " fa ", " fibrillation auriculaire "), " ep ", " embolie pulmonaire ") ) -> hépatite alcoolique. | AE12: {=_xlfn.LET(_xlpm.base, " " & LOWER(TRIM($AD12)) & " ", _xlpm.s1, SUBSTITUTE(_xlpm.base, " ic ", " insuffisance cardiaque "), _xlpm.s2, SUBSTITUTE(_xlpm.s1, " avc ", " accident vasculaire cerebral "), _xlpm.s3, SUBSTITUTE(_xlpm.s2, " hsa ", " hemorragie sous-arachnoidienne "), _xlpm.s4, SUBSTITUTE(_xlpm.s3, " htp ", " hypertension pulmonaire "), _xlpm.s5, SUBSTITUTE(_xlpm.s4, " bpco ", " bronchopneumopathie chronique obstructive "), _xlpm.s6, SUBSTITUTE(_xlpm.s5, " dmla ", " degenerescence maculaire liee a l age "), TRIM(_xlpm.s6))} -> hépatite alcoolique. | AF12: {=_xlfn.LET(_xlpm.base, " " & LOWER(TRIM($AE12)) & " ", _xlpm.s1, SUBSTITUTE(_xlpm.base, " omi ", " oedemes des membres inferieurs "), _xlpm.s2, SUBSTITUTE(_xlpm.s1, " idm ", " infarctus du myocarde "), _xlpm.s3, SUBSTITUTE(_xlpm.s2, " tvp ", " thrombose veineuse profonde "), _xlpm.s4, SUBSTITUTE(_xlpm.s3, " geu ", " grossesse extra-uterine "), _xlpm.s5, SUBSTITUTE(_xlpm.s4, " fuo ", " fievre d origine indeterminee "), TRIM(_xlpm.s5))} -> hépatite alcoolique.
A13: 2011 | B13: Autres diagnostics / non classés | D13: 52 | E13: =IF(D13="","",IFERROR(INDEX(SSP!$E$2:$E$266, MATCH(D13, SSP!$F$2:$F$266, 0)),"")) -> Douleur abdominale ou épigastrique | F13: =Feuil1!E13 -> Douleur abdominale | G13: Autre – Autre | H13: Syndrome du côlon irritable | J13: Femme de 23 ans avec douleur abdominale, signes vitaux normaux. | K13: Douleur abdominale associée à du stress, constipation, hydratation insuffisante. Douleur améliorée après les mouvements intestinaux, aucun signe d'appendicite, examen rectal OK. | N13: Syndrome du côlon irritable | O13: =IFERROR(_xlfn.XLOOKUP($D13, SSP!$F:$F, SSP!$E:$E, "Inconnu"), "") -> Douleur abdominale ou épigastrique | P13: =IF(OR(E13="", O13=""), "", IF(LOWER(E13)=LOWER(O13), "OK", "⚠️ Libellé ≠ n°")) -> OK | Q13: =IF(Feuil1!$E13="", "", IF(LOWER(Feuil1!$E13)=LOWER(E13), "Identique", "Différent")) -> Différent | R13: =IF(OR(P13="⚠️ Libellé ≠ n°", O13="Inconnu"), "⚠️", IF(Q13="Différent", "ℹ️", "")) -> ℹ️ | S13: {=_xlfn.LET(_xlpm.genCat,IFERROR(LOWER(TRIM(G13)),""),_xlpm.principal,IFERROR(LOWER(TRIM(H13)),""),_xlpm.orig,IFERROR(LOWER(TRIM(N13)),""),IF(OR(_xlpm.genCat="",_xlpm.principal=""),"",IF(LEFT(LOWER(G13),5)="autre","OK (Autre)",IF(OR(ISNUMBER(SEARCH(_xlpm.genCat,_xlpm.principal)),ISNUMBER(SEARCH(_xlpm.principal,_xlpm.genCat)),AND(_xlpm.orig<>"",OR(ISNUMBER(SEARCH(_xlpm.genCat,_xlpm.orig)),ISNUMBER(SEARCH(_xlpm.orig,_xlpm.genCat))))),"OK","⚠️ À vérifier"))))} -> OK (Autre) | T13: =IF(S13="","",IF(S13="OK (Autre)","Diagnostic générique = 'Autre – …'",IF(S13="OK","Concordance générique/principal","Écart entre générique et principal"))) -> Diagnostic générique = 'Autre – …' | U13: {=_xlfn.LET(_xlpm.yr, A13, _xlpm.diag, IF(N13<>"", N13, H13), _xlpm.base, TRIM(SUBSTITUTE(SUBSTITUTE(SUBSTITUTE(SUBSTITUTE(_xlpm.diag,"•"," "),CHAR(160)," "),CHAR(10)," ")," "," ")), LOWER(_xlpm.yr&"|"&_xlpm.base))} -> 2011|syndrome du côlon irritable | V13: =IFERROR(_xlfn.XLOOKUP($AB13,'Cas 2013-2017'!$K:$K,'Cas 2013-2017'!$D:$D,""),"") | W13: =IFERROR(_xlfn.XLOOKUP($AB13,'Cas 2013-2017'!$K:$K,'Cas 2013-2017'!$E:$E,""),"") | X13: =IFERROR(_xlfn.XLOOKUP($AB13,'Cas 2013-2017'!$K:$K,'Cas 2013-2017'!$F:$F,""),"") | Y13: =IFERROR(_xlfn.XLOOKUP($AB13,'Cas 2013-2017'!$K:$K,'Cas 2013-2017'!$G:$G,""),"") | Z13: =IFERROR(_xlfn.XLOOKUP($AB13,'Cas 2013-2017'!$K:$K,'Cas 2013-2017'!$I:$I,""),"") | AA13: =IFERROR(_xlfn.XLOOKUP($AB13,'Cas 2013-2017'!$K:$K,'Cas 2013-2017'!$H:$H,""),"") | AB13: =LOWER($A13 & "|" & $AF13) -> 2011|syndrome du côlon irritable | AC13: =TRIM(SUBSTITUTE(SUBSTITUTE(SUBSTITUTE(SUBSTITUTE(" " & LOWER(TRIM(IF($N13<>"", $N13, $H13))) & " ", " aomi ", " arteriopathie des membres inferieurs "), " hta ", " hypertension arterielle "), " saos ", " syndrome d'apnees obstructives du sommeil "), " rgo ", " reflux gastro-oesophagien ") ) -> syndrome du côlon irritable | AD13: =TRIM(SUBSTITUTE(SUBSTITUTE(SUBSTITUTE(SUBSTITUTE(" " & LOWER(TRIM($AC13)) & " ", " oacr ", " occlusion de l'artere centrale de la retine "), " hsd ", " hematome sous-dural "), " fa ", " fibrillation auriculaire "), " ep ", " embolie pulmonaire ") ) -> syndrome du côlon irritable | AE13: {=_xlfn.LET(_xlpm.base, " " & LOWER(TRIM($AD13)) & " ", _xlpm.s1, SUBSTITUTE(_xlpm.base, " ic ", " insuffisance cardiaque "), _xlpm.s2, SUBSTITUTE(_xlpm.s1, " avc ", " accident vasculaire cerebral "), _xlpm.s3, SUBSTITUTE(_xlpm.s2, " hsa ", " hemorragie sous-arachnoidienne "), _xlpm.s4, SUBSTITUTE(_xlpm.s3, " htp ", " hypertension pulmonaire "), _xlpm.s5, SUBSTITUTE(_xlpm.s4, " bpco ", " bronchopneumopathie chronique obstructive "), _xlpm.s6, SUBSTITUTE(_xlpm.s5, " dmla ", " degenerescence maculaire liee a l age "), TRIM(_xlpm.s6))} -> syndrome du côlon irritable | AF13: {=_xlfn.LET(_xlpm.base, " " & LOWER(TRIM($AE13)) & " ", _xlpm.s1, SUBSTITUTE(_xlpm.base, " omi ", " oedemes des membres inferieurs "), _xlpm.s2, SUBSTITUTE(_xlpm.s1, " idm ", " infarctus du myocarde "), _xlpm.s3, SUBSTITUTE(_xlpm.s2, " tvp ", " thrombose veineuse profonde "), _xlpm.s4, SUBSTITUTE(_xlpm.s3, " geu ", " grossesse extra-uterine "), _xlpm.s5, SUBSTITUTE(_xlpm.s4, " fuo ", " fievre d origine indeterminee "), TRIM(_xlpm.s5))} -> syndrome du côlon irritable
A14: 2011 | B14: 👩‍🦰 Gynéco / Obstétrique / Urologie | D14: 52 | E14: =IF(D14="","",IFERROR(INDEX(SSP!$E$2:$E$266, MATCH(D14, SSP!$F$2:$F$266, 0)),"")) -> Douleur abdominale ou épigastrique | F14: =Feuil1!E14 -> Douleur abdominale | G14: Autre – Autre | H14: Endométriose | J14: Jeune femme avec dyspareunie (douleur pendant les rapports sexuels). | K14: Anamnèse : douleur abdominale, dysménorrhée sévère. Résultats : taches livides-brunâtres sur le col/vagin, sensibilité à la pression dans le cul-de-sac de Douglas. | N14: Endométriose | O14: =IFERROR(_xlfn.XLOOKUP($D14, SSP!$F:$F, SSP!$E:$E, "Inconnu"), "") -> Douleur abdominale ou épigastrique | P14: =IF(OR(E14="", O14=""), "", IF(LOWER(E14)=LOWER(O14), "OK", "⚠️ Libellé ≠ n°")) -> OK | Q14: =IF(Feuil1!$E14="", "", IF(LOWER(Feuil1!$E14)=LOWER(E14), "Identique", "Différent")) -> Différent | R14: =IF(OR(P14="⚠️ Libellé ≠ n°", O14="Inconnu"), "⚠️", IF(Q14="Différent", "ℹ️", "")) -> ℹ️ | S14: {=_xlfn.LET(_xlpm.genCat,IFERROR(LOWER(TRIM(G14)),""),_xlpm.principal,IFERROR(LOWER(TRIM(H14)),""),_xlpm.orig,IFERROR(LOWER(TRIM(N14)),""),IF(OR(_xlpm.genCat="",_xlpm.principal=""),"",IF(LEFT(LOWER(G14),5)="autre","OK (Autre)",IF(OR(ISNUMBER(SEARCH(_xlpm.genCat,_xlpm.principal)),ISNUMBER(SEARCH(_xlpm.principal,_xlpm.genCat)),AND(_xlpm.orig<>"",OR(ISNUMBER(SEARCH(_xlpm.genCat,_xlpm.orig)),ISNUMBER(SEARCH(_xlpm.orig,_xlpm.genCat))))),"OK","⚠️ À vérifier"))))} -> OK (Autre) | T14: =IF(S14="","",IF(S14="OK (Autre)","Diagnostic générique = 'Autre – …'",IF(S14="OK","Concordance générique/principal","Écart entre générique et principal"))) -> Diagnostic générique = 'Autre – …' | U14: {=_xlfn.LET(_xlpm.yr, A14, _xlpm.diag, IF(N14<>"", N14, H14), _xlpm.base, TRIM(SUBSTITUTE(SUBSTITUTE(SUBSTITUTE(SUBSTITUTE(_xlpm.diag,"•"," "),CHAR(160)," "),CHAR(10)," ")," "," ")), LOWER(_xlpm.yr&"|"&_xlpm.base))} -> 2011|endométriose | V14: =IFERROR(_xlfn.XLOOKUP($AB14,'Cas 2013-2017'!$K:$K,'Cas 2013-2017'!$D:$D,""),"") | W14: =IFERROR(_xlfn.XLOOKUP($AB14,'Cas 2013-2017'!$K:$K,'Cas 2013-2017'!$E:$E,""),"") | X14: =IFERROR(_xlfn.XLOOKUP($AB14,'Cas 2013-2017'!$K:$K,'Cas 2013-2017'!$F:$F,""),"") | Y14: =IFERROR(_xlfn.XLOOKUP($AB14,'Cas 2013-2017'!$K:$K,'Cas 2013-2017'!$G:$G,""),"") | Z14: =IFERROR(_xlfn.XLOOKUP($AB14,'Cas 2013-2017'!$K:$K,'Cas 2013-2017'!$I:$I,""),"") | AA14: =IFERROR(_xlfn.XLOOKUP($AB14,'Cas 2013-2017'!$K:$K,'Cas 2013-2017'!$H:$H,""),"") | AB14: =LOWER($A14 & "|" & $AF14) -> 2011|endométriose | AC14: =TRIM(SUBSTITUTE(SUBSTITUTE(SUBSTITUTE(SUBSTITUTE(" " & LOWER(TRIM(IF($N14<>"", $N14, $H14))) & " ", " aomi ", " arteriopathie des membres inferieurs "), " hta ", " hypertension arterielle "), " saos ", " syndrome d'apnees obstructives du sommeil "), " rgo ", " reflux gastro-oesophagien ") ) -> endométriose | AD14: =TRIM(SUBSTITUTE(SUBSTITUTE(SUBSTITUTE(SUBSTITUTE(" " & LOWER(TRIM($AC14)) & " ", " oacr ", " occlusion de l'artere centrale de la retine "), " hsd ", " hematome sous-dural "), " fa ", " fibrillation auriculaire "), " ep ", " embolie pulmonaire ") ) -> endométriose | AE14: {=_xlfn.LET(_xlpm.base, " " & LOWER(TRIM($AD14)) & " ", _xlpm.s1, SUBSTITUTE(_xlpm.base, " ic ", " insuffisance cardiaque "), _xlpm.s2, SUBSTITUTE(_xlpm.s1, " avc ", " accident vasculaire cerebral "), _xlpm.s3, SUBSTITUTE(_xlpm.s2, " hsa ", " hemorragie sous-arachnoidienne "), _xlpm.s4, SUBSTITUTE(_xlpm.s3, " htp ", " hypertension pulmonaire "), _xlpm.s5, SUBSTITUTE(_xlpm.s4, " bpco ", " bronchopneumopathie chronique obstructive "), _xlpm.s6, SUBSTITUTE(_xlpm.s5, " dmla ", " degenerescence maculaire liee a l age "), TRIM(_xlpm.s6))} -> endométriose | AF14: {=_xlfn.LET(_xlpm.base, " " & LOWER(TRIM($AE14)) & " ", _xlpm.s1, SUBSTITUTE(_xlpm.base, " omi ", " oedemes des membres inferieurs "), _xlpm.s2, SUBSTITUTE(_xlpm.s1, " idm ", " infarctus du myocarde "), _xlpm.s3, SUBSTITUTE(_xlpm.s2, " tvp ", " thrombose veineuse profonde "), _xlpm.s4, SUBSTITUTE(_xlpm.s3, " geu ", " grossesse extra-uterine "), _xlpm.s5, SUBSTITUTE(_xlpm.s4, " fuo ", " fievre d origine indeterminee "), TRIM(_xlpm.s5))} -> endométriose
A15: 2011 | B15: 🧬 Maladies infectieuses | D15: 52 | E15: =IF(D15="","",IFERROR(INDEX(SSP!$E$2:$E$266, MATCH(D15, SSP!$F$2:$F$266, 0)),"")) -> Douleur abdominale ou épigastrique | F15: =Feuil1!E15 -> Douleur abdominale | G15: Infection sexuellement transmissible | H15: IST | J15: Femme avec douleur abdominale aiguë, suspicion de IST, examen vaginal à mentionner. | K15: Assurez-vous de demander un test de grossesse en cas d'abdomen peu clair. Pensez également à une GEU. | N15: IST | O15: =IFERROR(_xlfn.XLOOKUP($D15, SSP!$F:$F, SSP!$E:$E, "Inconnu"), "") -> Douleur abdominale ou épigastrique | P15: =IF(OR(E15="", O15=""), "", IF(LOWER(E15)=LOWER(O15), "OK", "⚠️ Libellé ≠ n°")) -> OK | Q15: =IF(Feuil1!$E15="", "", IF(LOWER(Feuil1!$E15)=LOWER(E15), "Identique", "Différent")) -> Différent | R15: =IF(OR(P15="⚠️ Libellé ≠ n°", O15="Inconnu"), "⚠️", IF(Q15="Différent", "ℹ️", "")) -> ℹ️ | S15: {=_xlfn.LET(_xlpm.genCat,IFERROR(LOWER(TRIM(G15)),""),_xlpm.principal,IFERROR(LOWER(TRIM(H15)),""),_xlpm.orig,IFERROR(LOWER(TRIM(N15)),""),IF(OR(_xlpm.genCat="",_xlpm.principal=""),"",IF(LEFT(LOWER(G15),5)="autre","OK (Autre)",IF(OR(ISNUMBER(SEARCH(_xlpm.genCat,_xlpm.principal)),ISNUMBER(SEARCH(_xlpm.principal,_xlpm.genCat)),AND(_xlpm.orig<>"",OR(ISNUMBER(SEARCH(_xlpm.genCat,_xlpm.orig)),ISNUMBER(SEARCH(_xlpm.orig,_xlpm.genCat))))),"OK","⚠️ À vérifier"))))} -> ⚠️ À vérifier | T15: =IF(S15="","",IF(S15="OK (Autre)","Diagnostic générique = 'Autre – …'",IF(S15="OK","Concordance générique/principal","Écart entre générique et principal"))) -> Écart entre générique et principal | U15: {=_xlfn.LET(_xlpm.yr, A15, _xlpm.diag, IF(N15<>"", N15, H15), _xlpm.base, TRIM(SUBSTITUTE(SUBSTITUTE(SUBSTITUTE(SUBSTITUTE(_xlpm.diag,"•"," "),CHAR(160)," "),CHAR(10)," ")," "," ")), LOWER(_xlpm.yr&"|"&_xlpm.base))} -> 2011|ist | V15: =IFERROR(_xlfn.XLOOKUP($AB15,'Cas 2013-2017'!$K:$K,'Cas 2013-2017'!$D:$D,""),"") | W15: =IFERROR(_xlfn.XLOOKUP($AB15,'Cas 2013-2017'!$K:$K,'Cas 2013-2017'!$E:$E,""),"") | X15: =IFERROR(_xlfn.XLOOKUP($AB15,'Cas 2013-2017'!$K:$K,'Cas 2013-2017'!$F:$F,""),"") | Y15: =IFERROR(_xlfn.XLOOKUP($AB15,'Cas 2013-2017'!$K:$K,'Cas 2013-2017'!$G:$G,""),"") | Z15: =IFERROR(_xlfn.XLOOKUP($AB15,'Cas 2013-2017'!$K:$K,'Cas 2013-2017'!$I:$I,""),"") | AA15: =IFERROR(_xlfn.XLOOKUP($AB15,'Cas 2013-2017'!$K:$K,'Cas 2013-2017'!$H:$H,""),"") | AB15: =LOWER($A15 & "|" & $AF15) -> 2011|ist | AC15: =TRIM(SUBSTITUTE(SUBSTITUTE(SUBSTITUTE(SUBSTITUTE(" " & LOWER(TRIM(IF($N15<>"", $N15, $H15))) & " ", " aomi ", " arteriopathie des membres inferieurs "), " hta ", " hypertension arterielle "), " saos ", " syndrome d'apnees obstructives du sommeil "), " rgo ", " reflux gastro-oesophagien ") ) -> ist | AD15: =TRIM(SUBSTITUTE(SUBSTITUTE(SUBSTITUTE(SUBSTITUTE(" " & LOWER(TRIM($AC15)) & " ", " oacr ", " occlusion de l'artere centrale de la retine "), " hsd ", " hematome sous-dural "), " fa ", " fibrillation auriculaire "), " ep ", " embolie pulmonaire ") ) -> ist | AE15: {=_xlfn.LET(_xlpm.base, " " & LOWER(TRIM($AD15)) & " ", _xlpm.s1, SUBSTITUTE(_xlpm.base, " ic ", " insuffisance cardiaque "), _xlpm.s2, SUBSTITUTE(_xlpm.s1, " avc ", " accident vasculaire cerebral "), _xlpm.s3, SUBSTITUTE(_xlpm.s2, " hsa ", " hemorragie sous-arachnoidienne "), _xlpm.s4, SUBSTITUTE(_xlpm.s3, " htp ", " hypertension pulmonaire "), _xlpm.s5, SUBSTITUTE(_xlpm.s4, " bpco ", " bronchopneumopathie chronique obstructive "), _xlpm.s6, SUBSTITUTE(_xlpm.s5, " dmla ", " degenerescence maculaire liee a l age "), TRIM(_xlpm.s6))} -> ist | AF15: {=_xlfn.LET(_xlpm.base, " " & LOWER(TRIM($AE15)) & " ", _xlpm.s1, SUBSTITUTE(_xlpm.base, " omi ", " oedemes des membres inferieurs "), _xlpm.s2, SUBSTITUTE(_xlpm.s1, " idm ", " infarctus du myocarde "), _xlpm.s3, SUBSTITUTE(_xlpm.s2, " tvp ", " thrombose veineuse profonde "), _xlpm.s4, SUBSTITUTE(_xlpm.s3, " geu ", " grossesse extra-uterine "), _xlpm.s5, SUBSTITUTE(_xlpm.s4, " fuo ", " fievre d origine indeterminee "), TRIM(_xlpm.s5))} -> ist
A16: 2011 | B16: 🧬 Maladies infectieuses | D16: 6 | E16: =IF(D16="","",IFERROR(INDEX(SSP!$E$2:$E$266, MATCH(D16, SSP!$F$2:$F$266, 0)),"")) -> Fièvre, frissons, hyperthermie | F16: =Feuil1!E16 -> Fièvre | G16: Fièvre d'origine indéterminée | H16: FUO | J16: Homme en neutropénie et fièvre | K16: Fièvre et neutropénie sans possibilité d'anamnèse. | N16: FUO | O16: =IFERROR(_xlfn.XLOOKUP($D16, SSP!$F:$F, SSP!$E:$E, "Inconnu"), "") -> Fièvre, frissons, hyperthermie | P16: =IF(OR(E16="", O16=""), "", IF(LOWER(E16)=LOWER(O16), "OK", "⚠️ Libellé ≠ n°")) -> OK | Q16: =IF(Feuil1!$E16="", "", IF(LOWER(Feuil1!$E16)=LOWER(E16), "Identique", "Différent")) -> Différent | R16: =IF(OR(P16="⚠️ Libellé ≠ n°", O16="Inconnu"), "⚠️", IF(Q16="Différent", "ℹ️", "")) -> ℹ️ | S16: {=_xlfn.LET(_xlpm.genCat,IFERROR(LOWER(TRIM(G16)),""),_xlpm.principal,IFERROR(LOWER(TRIM(H16)),""),_xlpm.orig,IFERROR(LOWER(TRIM(N16)),""),IF(OR(_xlpm.genCat="",_xlpm.principal=""),"",IF(LEFT(LOWER(G16),5)="autre","OK (Autre)",IF(OR(ISNUMBER(SEARCH(_xlpm.genCat,_xlpm.principal)),ISNUMBER(SEARCH(_xlpm.principal,_xlpm.genCat)),AND(_xlpm.orig<>"",OR(ISNUMBER(SEARCH(_xlpm.genCat,_xlpm.orig)),ISNUMBER(SEARCH(_xlpm.orig,_xlpm.genCat))))),"OK","⚠️ À vérifier"))))} -> ⚠️ À vérifier | T16: =IF(S16="","",IF(S16="OK (Autre)","Diagnostic générique = 'Autre – …'",IF(S16="OK","Concordance générique/principal","Écart entre générique et principal"))) -> Écart entre générique et principal | U16: {=_xlfn.LET(_xlpm.yr, A16, _xlpm.diag, IF(N16<>"", N16, H16), _xlpm.base, TRIM(SUBSTITUTE(SUBSTITUTE(SUBSTITUTE(SUBSTITUTE(_xlpm.diag,"•"," "),CHAR(160)," "),CHAR(10)," ")," "," ")), LOWER(_xlpm.yr&"|"&_xlpm.base))} -> 2011|fuo | V16: =IFERROR(_xlfn.XLOOKUP($AB16,'Cas 2013-2017'!$K:$K,'Cas 2013-2017'!$D:$D,""),"") | W16: =IFERROR(_xlfn.XLOOKUP($AB16,'Cas 2013-2017'!$K:$K,'Cas 2013-2017'!$E:$E,""),"") | X16: =IFERROR(_xlfn.XLOOKUP($AB16,'Cas 2013-2017'!$K:$K,'Cas 2013-2017'!$F:$F,""),"") | Y16: =IFERROR(_xlfn.XLOOKUP($AB16,'Cas 2013-2017'!$K:$K,'Cas 2013-2017'!$G:$G,""),"") | Z16: =IFERROR(_xlfn.XLOOKUP($AB16,'Cas 2013-2017'!$K:$K,'Cas 2013-2017'!$I:$I,""),"") | AA16: =IFERROR(_xlfn.XLOOKUP($AB16,'Cas 2013-2017'!$K:$K,'Cas 2013-2017'!$H:$H,""),"") | AB16: =LOWER($A16 & "|" & $AF16) -> 2011|fievre d origine indeterminee | AC16: =TRIM(SUBSTITUTE(SUBSTITUTE(SUBSTITUTE(SUBSTITUTE(" " & LOWER(TRIM(IF($N16<>"", $N16, $H16))) & " ", " aomi ", " arteriopathie des membres inferieurs "), " hta ", " hypertension arterielle "), " saos ", " syndrome d'apnees obstructives du sommeil "), " rgo ", " reflux gastro-oesophagien ") ) -> fuo | AD16: =TRIM(SUBSTITUTE(SUBSTITUTE(SUBSTITUTE(SUBSTITUTE(" " & LOWER(TRIM($AC16)) & " ", " oacr ", " occlusion de l'artere centrale de la retine "), " hsd ", " hematome sous-dural "), " fa ", " fibrillation auriculaire "), " ep ", " embolie pulmonaire ") ) -> fuo | AE16: {=_xlfn.LET(_xlpm.base, " " & LOWER(TRIM($AD16)) & " ", _xlpm.s1, SUBSTITUTE(_xlpm.base, " ic ", " insuffisance cardiaque "), _xlpm.s2, SUBSTITUTE(_xlpm.s1, " avc ", " accident vasculaire cerebral "), _xlpm.s3, SUBSTITUTE(_xlpm.s2, " hsa ", " hemorragie sous-arachnoidienne "), _xlpm.s4, SUBSTITUTE(_xlpm.s3, " htp ", " hypertension pulmonaire "), _xlpm.s5, SUBSTITUTE(_xlpm.s4, " bpco ", " bronchopneumopathie chronique obstructive "), _xlpm.s6, SUBSTITUTE(_xlpm.s5, " dmla ", " degenerescence maculaire liee a l age "), TRIM(_xlpm.s6))} -> fuo | AF16: {=_xlfn.LET(_xlpm.base, " " & LOWER(TRIM($AE16)) & " ", _xlpm.s1, SUBSTITUTE(_xlpm.base, " omi ", " oedemes des membres inferieurs "), _xlpm.s2, SUBSTITUTE(_xlpm.s1, " idm ", " infarctus du myocarde "), _xlpm.s3, SUBSTITUTE(_xlpm.s2, " tvp ", " thrombose veineuse profonde "), _xlpm.s4, SUBSTITUTE(_xlpm.s3, " geu ", " grossesse extra-uterine "), _xlpm.s5, SUBSTITUTE(_xlpm.s4, " fuo ", " fievre d origine indeterminee "), TRIM(_xlpm.s5))} -> fievre d origine indeterminee
A17: 2011 | B17: 🧠 Neurologie | D17: 103 | E17: =IF(D17="","",IFERROR(INDEX(SSP!$E$2:$E$266, MATCH(D17, SSP!$F$2:$F$266, 0)),"")) -> Paresie, paralysie | F17: =Feuil1!E17 -> Parésie | G17: Maladie cérébrovasculaire | H17: Accident ischémique transitoire (AIT) | J17: Faiblesse et parésie de la jambe droite | K17: La femme présentait une faiblesse et une parésie de la jambe droite avant l'Ih, mais elle ne se plaint actuellement d'aucun AIT. | N17: AIT | O17: =IFERROR(_xlfn.XLOOKUP($D17, SSP!$F:$F, SSP!$E:$E, "Inconnu"), "") -> Paresie, paralysie | P17: =IF(OR(E17="", O17=""), "", IF(LOWER(E17)=LOWER(O17), "OK", "⚠️ Libellé ≠ n°")) -> OK | Q17: =IF(Feuil1!$E17="", "", IF(LOWER(Feuil1!$E17)=LOWER(E17), "Identique", "Différent")) -> Différent | R17: =IF(OR(P17="⚠️ Libellé ≠ n°", O17="Inconnu"), "⚠️", IF(Q17="Différent", "ℹ️", "")) -> ℹ️ | S17: {=_xlfn.LET(_xlpm.genCat,IFERROR(LOWER(TRIM(G17)),""),_xlpm.principal,IFERROR(LOWER(TRIM(H17)),""),_xlpm.orig,IFERROR(LOWER(TRIM(N17)),""),IF(OR(_xlpm.genCat="",_xlpm.principal=""),"",IF(LEFT(LOWER(G17),5)="autre","OK (Autre)",IF(OR(ISNUMBER(SEARCH(_xlpm.genCat,_xlpm.principal)),ISNUMBER(SEARCH(_xlpm.principal,_xlpm.genCat)),AND(_xlpm.orig<>"",OR(ISNUMBER(SEARCH(_xlpm.genCat,_xlpm.orig)),ISNUMBER(SEARCH(_xlpm.orig,_xlpm.genCat))))),"OK","⚠️ À vérifier"))))} -> ⚠️ À vérifier | T17: =IF(S17="","",IF(S17="OK (Autre)","Diagnostic générique = 'Autre – …'",IF(S17="OK","Concordance générique/principal","Écart entre générique et principal"))) -> Écart entre générique et principal | U17: {=_xlfn.LET(_xlpm.yr, A17, _xlpm.diag, IF(N17<>"", N17, H17), _xlpm.base, TRIM(SUBSTITUTE(SUBSTITUTE(SUBSTITUTE(SUBSTITUTE(_xlpm.diag,"•"," "),CHAR(160)," "),CHAR(10)," ")," "," ")), LOWER(_xlpm.yr&"|"&_xlpm.base))} -> 2011|ait | V17: =IFERROR(_xlfn.XLOOKUP($AB17,'Cas 2013-2017'!$K:$K,'Cas 2013-2017'!$D:$D,""),"") | W17: =IFERROR(_xlfn.XLOOKUP($AB17,'Cas 2013-2017'!$K:$K,'Cas 2013-2017'!$E:$E,""),"") | X17: =IFERROR(_xlfn.XLOOKUP($AB17,'Cas 2013-2017'!$K:$K,'Cas 2013-2017'!$F:$F,""),"") | Y17: =IFERROR(_xlfn.XLOOKUP($AB17,'Cas 2013-2017'!$K:$K,'Cas 2013-2017'!$G:$G,""),"") | Z17: =IFERROR(_xlfn.XLOOKUP($AB17,'Cas 2013-2017'!$K:$K,'Cas 2013-2017'!$I:$I,""),"") | AA17: =IFERROR(_xlfn.XLOOKUP($AB17,'Cas 2013-2017'!$K:$K,'Cas 2013-2017'!$H:$H,""),"") | AB17: =LOWER($A17 & "|" & $AF17) -> 2011|ait | AC17: =TRIM(SUBSTITUTE(SUBSTITUTE(SUBSTITUTE(SUBSTITUTE(" " & LOWER(TRIM(IF($N17<>"", $N17, $H17))) & " ", " aomi ", " arteriopathie des membres inferieurs "), " hta ", " hypertension arterielle "), " saos ", " syndrome d'apnees obstructives du sommeil "), " rgo ", " reflux gastro-oesophagien ") ) -> ait | AD17: =TRIM(SUBSTITUTE(SUBSTITUTE(SUBSTITUTE(SUBSTITUTE(" " & LOWER(TRIM($AC17)) & " ", " oacr ", " occlusion de l'artere centrale de la retine "), " hsd ", " hematome sous-dural "), " fa ", " fibrillation auriculaire "), " ep ", " embolie pulmonaire ") ) -> ait | AE17: {=_xlfn.LET(_xlpm.base, " " & LOWER(TRIM($AD17)) & " ", _xlpm.s1, SUBSTITUTE(_xlpm.base, " ic ", " insuffisance cardiaque "), _xlpm.s2, SUBSTITUTE(_xlpm.s1, " avc ", " accident vasculaire cerebral "), _xlpm.s3, SUBSTITUTE(_xlpm.s2, " hsa ", " hemorragie sous-arachnoidienne "), _xlpm.s4, SUBSTITUTE(_xlpm.s3, " htp ", " hypertension pulmonaire "), _xlpm.s5, SUBSTITUTE(_xlpm.s4, " bpco ", " bronchopneumopathie chronique obstructive "), _xlpm.s6, SUBSTITUTE(_xlpm.s5, " dmla ", " degenerescence maculaire liee a l age "), TRIM(_xlpm.s6))} -> ait | AF17: {=_xlfn.LET(_xlpm.base, " " & LOWER(TRIM($AE17)) & " ", _xlpm.s1, SUBSTITUTE(_xlpm.base, " omi ", " oedemes des membres inferieurs "), _xlpm.s2, SUBSTITUTE(_xlpm.s1, " idm ", " infarctus du myocarde "), _xlpm.s3, SUBSTITUTE(_xlpm.s2, " tvp ", " thrombose veineuse profonde "), _xlpm.s4, SUBSTITUTE(_xlpm.s3, " geu ", " grossesse extra-uterine "), _xlpm.s5, SUBSTITUTE(_xlpm.s4, " fuo ", " fievre d origine indeterminee "), TRIM(_xlpm.s5))} -> ait
A18: 2011 | B18: 🧠 Neurologie | D18: 207 | E18: =IF(D18="","",IFERROR(INDEX(SSP!$E$2:$E$266, MATCH(D18, SSP!$F$2:$F$266, 0)),"")) -> Céphalée aiguë intense, syndrome méningé | F18: =Feuil1!E18 -> Céphalée | G18: Céphalée primaire | H18: Céphalées de tension | J18: Céphalées | N18: Céphalées de tension | O18: =IFERROR(_xlfn.XLOOKUP($D18, SSP!$F:$F, SSP!$E:$E, "Inconnu"), "") -> Céphalée aiguë intense, syndrome méningé | P18: =IF(OR(E18="", O18=""), "", IF(LOWER(E18)=LOWER(O18), "OK", "⚠️ Libellé ≠ n°")) -> OK | Q18: =IF(Feuil1!$E18="", "", IF(LOWER(Feuil1!$E18)=LOWER(E18), "Identique", "Différent")) -> Différent | R18: =IF(OR(P18="⚠️ Libellé ≠ n°", O18="Inconnu"), "⚠️", IF(Q18="Différent", "ℹ️", "")) -> ℹ️ | S18: {=_xlfn.LET(_xlpm.genCat,IFERROR(LOWER(TRIM(G18)),""),_xlpm.principal,IFERROR(LOWER(TRIM(H18)),""),_xlpm.orig,IFERROR(LOWER(TRIM(N18)),""),IF(OR(_xlpm.genCat="",_xlpm.principal=""),"",IF(LEFT(LOWER(G18),5)="autre","OK (Autre)",IF(OR(ISNUMBER(SEARCH(_xlpm.genCat,_xlpm.principal)),ISNUMBER(SEARCH(_xlpm.principal,_xlpm.genCat)),AND(_xlpm.orig<>"",OR(ISNUMBER(SEARCH(_xlpm.genCat,_xlpm.orig)),ISNUMBER(SEARCH(_xlpm.orig,_xlpm.genCat))))),"OK","⚠️ À vérifier"))))} -> ⚠️ À vérifier | T18: =IF(S18="","",IF(S18="OK (Autre)","Diagnostic générique = 'Autre – …'",IF(S18="OK","Concordance générique/principal","Écart entre générique et principal"))) -> Écart entre générique et principal | U18: {=_xlfn.LET(_xlpm.yr, A18, _xlpm.diag, IF(N18<>"", N18, H18), _xlpm.base, TRIM(SUBSTITUTE(SUBSTITUTE(SUBSTITUTE(SUBSTITUTE(_xlpm.diag,"•"," "),CHAR(160)," "),CHAR(10)," ")," "," ")), LOWER(_xlpm.yr&"|"&_xlpm.base))} -> 2011|céphalées de tension | V18: =IFERROR(_xlfn.XLOOKUP($AB18,'Cas 2013-2017'!$K:$K,'Cas 2013-2017'!$D:$D,""),"") | W18: =IFERROR(_xlfn.XLOOKUP($AB18,'Cas 2013-2017'!$K:$K,'Cas 2013-2017'!$E:$E,""),"") | X18: =IFERROR(_xlfn.XLOOKUP($AB18,'Cas 2013-2017'!$K:$K,'Cas 2013-2017'!$F:$F,""),"") | Y18: =IFERROR(_xlfn.XLOOKUP($AB18,'Cas 2013-2017'!$K:$K,'Cas 2013-2017'!$G:$G,""),"") | Z18: =IFERROR(_xlfn.XLOOKUP($AB18,'Cas 2013-2017'!$K:$K,'Cas 2013-2017'!$I:$I,""),"") | AA18: =IFERROR(_xlfn.XLOOKUP($AB18,'Cas 2013-2017'!$K:$K,'Cas 2013-2017'!$H:$H,""),"") | AB18: =LOWER($A18 & "|" & $AF18) -> 2011|céphalées de tension | AC18: =TRIM(SUBSTITUTE(SUBSTITUTE(SUBSTITUTE(SUBSTITUTE(" " & LOWER(TRIM(IF($N18<>"", $N18, $H18))) & " ", " aomi ", " arteriopathie des membres inferieurs "), " hta ", " hypertension arterielle "), " saos ", " syndrome d'apnees obstructives du sommeil "), " rgo ", " reflux gastro-oesophagien ") ) -> céphalées de tension | AD18: =TRIM(SUBSTITUTE(SUBSTITUTE(SUBSTITUTE(SUBSTITUTE(" " & LOWER(TRIM($AC18)) & " ", " oacr ", " occlusion de l'artere centrale de la retine "), " hsd ", " hematome sous-dural "), " fa ", " fibrillation auriculaire "), " ep ", " embolie pulmonaire ") ) -> céphalées de tension | AE18: {=_xlfn.LET(_xlpm.base, " " & LOWER(TRIM($AD18)) & " ", _xlpm.s1, SUBSTITUTE(_xlpm.base, " ic ", " insuffisance cardiaque "), _xlpm.s2, SUBSTITUTE(_xlpm.s1, " avc ", " accident vasculaire cerebral "), _xlpm.s3, SUBSTITUTE(_xlpm.s2, " hsa ", " hemorragie sous-arachnoidienne "), _xlpm.s4, SUBSTITUTE(_xlpm.s3, " htp ", " hypertension pulmonaire "), _xlpm.s5, SUBSTITUTE(_xlpm.s4, " bpco ", " bronchopneumopathie chronique obstructive "), _xlpm.s6, SUBSTITUTE(_xlpm.s5, " dmla ", " degenerescence maculaire liee a l age "), TRIM(_xlpm.s6))} -> céphalées de tension | AF18: {=_xlfn.LET(_xlpm.base, " " & LOWER(TRIM($AE18)) & " ", _xlpm.s1, SUBSTITUTE(_xlpm.base, " omi ", " oedemes des membres inferieurs "), _xlpm.s2, SUBSTITUTE(_xlpm.s1, " idm ", " infarctus du myocarde "), _xlpm.s3, SUBSTITUTE(_xlpm.s2, " tvp ", " thrombose veineuse profonde "), _xlpm.s4, SUBSTITUTE(_xlpm.s3, " geu ", " grossesse extra-uterine "), _xlpm.s5, SUBSTITUTE(_xlpm.s4, " fuo ", " fievre d origine indeterminee "), TRIM(_xlpm.s5))} -> céphalées de tension
A19: 2011 | D19: 18 | E19: =IF(D19="","",IFERROR(INDEX(SSP!$E$2:$E$266, MATCH(D19, SSP!$F$2:$F$266, 0)),"")) -> Perte de vision aiguë ou progressive (brutale, lente, transitoire, partielle) | F19: =Feuil1!E19 -> Amaurose | G19: Artérite à cellules géantes | H19: Horton | J19: Symptômes d'artérite temporale | K19: Anamnèse et symptômes classiques de l'artérite temporale | N19: Horton | O19: =IFERROR(_xlfn.XLOOKUP($D19, SSP!$F:$F, SSP!$E:$E, "Inconnu"), "") -> Perte de vision aiguë ou progressive (brutale, lente, transitoire, partielle) | P19: =IF(OR(E19="", O19=""), "", IF(LOWER(E19)=LOWER(O19), "OK", "⚠️ Libellé ≠ n°")) -> OK | Q19: =IF(Feuil1!$E19="", "", IF(LOWER(Feuil1!$E19)=LOWER(E19), "Identique", "Différent")) -> Différent | R19: =IF(OR(P19="⚠️ Libellé ≠ n°", O19="Inconnu"), "⚠️", IF(Q19="Différent", "ℹ️", "")) -> ℹ️ | S19: {=_xlfn.LET(_xlpm.genCat,IFERROR(LOWER(TRIM(G19)),""),_xlpm.principal,IFERROR(LOWER(TRIM(H19)),""),_xlpm.orig,IFERROR(LOWER(TRIM(N19)),""),IF(OR(_xlpm.genCat="",_xlpm.principal=""),"",IF(LEFT(LOWER(G19),5)="autre","OK (Autre)",IF(OR(ISNUMBER(SEARCH(_xlpm.genCat,_xlpm.principal)),ISNUMBER(SEARCH(_xlpm.principal,_xlpm.genCat)),AND(_xlpm.orig<>"",OR(ISNUMBER(SEARCH(_xlpm.genCat,_xlpm.orig)),ISNUMBER(SEARCH(_xlpm.orig,_xlpm.genCat))))),"OK","⚠️ À vérifier"))))} -> ⚠️ À vérifier | T19: =IF(S19="","",IF(S19="OK (Autre)","Diagnostic générique = 'Autre – …'",IF(S19="OK","Concordance générique/principal","Écart entre générique et principal"))) -> Écart entre générique et principal | U19: {=_xlfn.LET(_xlpm.yr, A19, _xlpm.diag, IF(N19<>"", N19, H19), _xlpm.base, TRIM(SUBSTITUTE(SUBSTITUTE(SUBSTITUTE(SUBSTITUTE(_xlpm.diag,"•"," "),CHAR(160)," "),CHAR(10)," ")," "," ")), LOWER(_xlpm.yr&"|"&_xlpm.base))} -> 2011|horton | V19: =IFERROR(_xlfn.XLOOKUP($AB19,'Cas 2013-2017'!$K:$K,'Cas 2013-2017'!$D:$D,""),"") | W19: =IFERROR(_xlfn.XLOOKUP($AB19,'Cas 2013-2017'!$K:$K,'Cas 2013-2017'!$E:$E,""),"") | X19: =IFERROR(_xlfn.XLOOKUP($AB19,'Cas 2013-2017'!$K:$K,'Cas 2013-2017'!$F:$F,""),"") | Y19: =IFERROR(_xlfn.XLOOKUP($AB19,'Cas 2013-2017'!$K:$K,'Cas 2013-2017'!$G:$G,""),"") | Z19: =IFERROR(_xlfn.XLOOKUP($AB19,'Cas 2013-2017'!$K:$K,'Cas 2013-2017'!$I:$I,""),"") | AA19: =IFERROR(_xlfn.XLOOKUP($AB19,'Cas 2013-2017'!$K:$K,'Cas 2013-2017'!$H:$H,""),"") | AB19: =LOWER($A19 & "|" & $AF19) -> 2011|horton | AC19: =TRIM(SUBSTITUTE(SUBSTITUTE(SUBSTITUTE(SUBSTITUTE(" " & LOWER(TRIM(IF($N19<>"", $N19, $H19))) & " ", " aomi ", " arteriopathie des membres inferieurs "), " hta ", " hypertension arterielle "), " saos ", " syndrome d'apnees obstructives du sommeil "), " rgo ", " reflux gastro-oesophagien ") ) -> horton | AD19: =TRIM(SUBSTITUTE(SUBSTITUTE(SUBSTITUTE(SUBSTITUTE(" " & LOWER(TRIM($AC19)) & " ", " oacr ", " occlusion de l'artere centrale de la retine "), " hsd ", " hematome sous-dural "), " fa ", " fibrillation auriculaire "), " ep ", " embolie pulmonaire ") ) -> horton | AE19: {=_xlfn.LET(_xlpm.base, " " & LOWER(TRIM($AD19)) & " ", _xlpm.s1, SUBSTITUTE(_xlpm.base, " ic ", " insuffisance cardiaque "), _xlpm.s2, SUBSTITUTE(_xlpm.s1, " avc ", " accident vasculaire cerebral "), _xlpm.s3, SUBSTITUTE(_xlpm.s2, " hsa ", " hemorragie sous-arachnoidienne "), _xlpm.s4, SUBSTITUTE(_xlpm.s3, " htp ", " hypertension pulmonaire "), _xlpm.s5, SUBSTITUTE(_xlpm.s4, " bpco ", " bronchopneumopathie chronique obstructive "), _xlpm.s6, SUBSTITUTE(_xlpm.s5, " dmla ", " degenerescence maculaire liee a l age "), TRIM(_xlpm.s6))} -> horton | AF19: {=_xlfn.LET(_xlpm.base, " " & LOWER(TRIM($AE19)) & " ", _xlpm.s1, SUBSTITUTE(_xlpm.base, " omi ", " oedemes des membres inferieurs "), _xlpm.s2, SUBSTITUTE(_xlpm.s1, " idm ", " infarctus du myocarde "), _xlpm.s3, SUBSTITUTE(_xlpm.s2, " tvp ", " thrombose veineuse profonde "), _xlpm.s4, SUBSTITUTE(_xlpm.s3, " geu ", " grossesse extra-uterine "), _xlpm.s5, SUBSTITUTE(_xlpm.s4, " fuo ", " fievre d origine indeterminee "), TRIM(_xlpm.s5))} -> horton
A20: 2011 | B20: 🧠 Neurologie | D20: 207 | E20: =IF(D20="","",IFERROR(INDEX(SSP!$E$2:$E$266, MATCH(D20, SSP!$F$2:$F$266, 0)),"")) -> Céphalée aiguë intense, syndrome méningé | F20: =Feuil1!E20 -> Céphalée | G20: Céphalée primaire | H20: Migraine | J20: Céphalées | K20: Femme 32 ans. Maux de tête, altération des signes vitaux, discussion des antécédents médicaux, du DD et des procédures. Aucun examen n'est requis (cf. fiche d'état neurologique). Antécédents : unilatérale, intermittente, sensible à la lumière/au bruit, sa mère en souffrait également, pas d'écoulement oculaire/de rougeur, a commencé un nouvel emploi et veut s'absenter le moins possible, associée au stress et à la menstruation. Interrogez-la sur tous les symptômes typiques de la migraine. Éliminez les autres maux de tête. | N20: Migraine | O20: =IFERROR(_xlfn.XLOOKUP($D20, SSP!$F:$F, SSP!$E:$E, "Inconnu"), "") -> Céphalée aiguë intense, syndrome méningé | P20: =IF(OR(E20="", O20=""), "", IF(LOWER(E20)=LOWER(O20), "OK", "⚠️ Libellé ≠ n°")) -> OK | Q20: =IF(Feuil1!$E20="", "", IF(LOWER(Feuil1!$E20)=LOWER(E20), "Identique", "Différent")) -> Différent | R20: =IF(OR(P20="⚠️ Libellé ≠ n°", O20="Inconnu"), "⚠️", IF(Q20="Différent", "ℹ️", "")) -> ℹ️ | S20: {=_xlfn.LET(_xlpm.genCat,IFERROR(LOWER(TRIM(G20)),""),_xlpm.principal,IFERROR(LOWER(TRIM(H20)),""),_xlpm.orig,IFERROR(LOWER(TRIM(N20)),""),IF(OR(_xlpm.genCat="",_xlpm.principal=""),"",IF(LEFT(LOWER(G20),5)="autre","OK (Autre)",IF(OR(ISNUMBER(SEARCH(_xlpm.genCat,_xlpm.principal)),ISNUMBER(SEARCH(_xlpm.principal,_xlpm.genCat)),AND(_xlpm.orig<>"",OR(ISNUMBER(SEARCH(_xlpm.genCat,_xlpm.orig)),ISNUMBER(SEARCH(_xlpm.orig,_xlpm.genCat))))),"OK","⚠️ À vérifier"))))} -> ⚠️ À vérifier | T20: =IF(S20="","",IF(S20="OK (Autre)","Diagnostic générique = 'Autre – …'",IF(S20="OK","Concordance générique/principal","Écart entre générique et principal"))) -> Écart entre générique et principal | U20: {=_xlfn.LET(_xlpm.yr, A20, _xlpm.diag, IF(N20<>"", N20, H20), _xlpm.base, TRIM(SUBSTITUTE(SUBSTITUTE(SUBSTITUTE(SUBSTITUTE(_xlpm.diag,"•"," "),CHAR(160)," "),CHAR(10)," ")," "," ")), LOWER(_xlpm.yr&"|"&_xlpm.base))} -> 2011|migraine | V20: =IFERROR(_xlfn.XLOOKUP($AB20,'Cas 2013-2017'!$K:$K,'Cas 2013-2017'!$D:$D,""),"") | W20: =IFERROR(_xlfn.XLOOKUP($AB20,'Cas 2013-2017'!$K:$K,'Cas 2013-2017'!$E:$E,""),"") | X20: =IFERROR(_xlfn.XLOOKUP($AB20,'Cas 2013-2017'!$K:$K,'Cas 2013-2017'!$F:$F,""),"") | Y20: =IFERROR(_xlfn.XLOOKUP($AB20,'Cas 2013-2017'!$K:$K,'Cas 2013-2017'!$G:$G,""),"") | Z20: =IFERROR(_xlfn.XLOOKUP($AB20,'Cas 2013-2017'!$K:$K,'Cas 2013-2017'!$I:$I,""),"") | AA20: =IFERROR(_xlfn.XLOOKUP($AB20,'Cas 2013-2017'!$K:$K,'Cas 2013-2017'!$H:$H,""),"") | AB20: =LOWER($A20 & "|" & $AF20) -> 2011|migraine | AC20: =TRIM(SUBSTITUTE(SUBSTITUTE(SUBSTITUTE(SUBSTITUTE(" " & LOWER(TRIM(IF($N20<>"", $N20, $H20))) & " ", " aomi ", " arteriopathie des membres inferieurs "), " hta ", " hypertension arterielle "), " saos ", " syndrome d'apnees obstructives du sommeil "), " rgo ", " reflux gastro-oesophagien ") ) -> migraine | AD20: =TRIM(SUBSTITUTE(SUBSTITUTE(SUBSTITUTE(SUBSTITUTE(" " & LOWER(TRIM($AC20)) & " ", " oacr ", " occlusion de l'artere centrale de la retine "), " hsd ", " hematome sous-dural "), " fa ", " fibrillation auriculaire "), " ep ", " embolie pulmonaire ") ) -> migraine | AE20: {=_xlfn.LET(_xlpm.base, " " & LOWER(TRIM($AD20)) & " ", _xlpm.s1, SUBSTITUTE(_xlpm.base, " ic ", " insuffisance cardiaque "), _xlpm.s2, SUBSTITUTE(_xlpm.s1, " avc ", " accident vasculaire cerebral "), _xlpm.s3, SUBSTITUTE(_xlpm.s2, " hsa ", " hemorragie sous-arachnoidienne "), _xlpm.s4, SUBSTITUTE(_xlpm.s3, " htp ", " hypertension pulmonaire "), _xlpm.s5, SUBSTITUTE(_xlpm.s4, " bpco ", " bronchopneumopathie chronique obstructive "), _xlpm.s6, SUBSTITUTE(_xlpm.s5, " dmla ", " degenerescence maculaire liee a l age "), TRIM(_xlpm.s6))} -> migraine | AF20: {=_xlfn.LET(_xlpm.base, " " & LOWER(TRIM($AE20)) & " ", _xlpm.s1, SUBSTITUTE(_xlpm.base, " omi ", " oedemes des membres inferieurs "), _xlpm.s2, SUBSTITUTE(_xlpm.s1, " idm ", " infarctus du myocarde "), _xlpm.s3, SUBSTITUTE(_xlpm.s2, " tvp ", " thrombose veineuse profonde "), _xlpm.s4, SUBSTITUTE(_xlpm.s3, " geu ", " grossesse extra-uterine "), _xlpm.s5, SUBSTITUTE(_xlpm.s4, " fuo ", " fievre d origine indeterminee "), TRIM(_xlpm.s5))} -> migraine
A21: 2011 | B21: 👁️👂 ORL / Ophtalmo | D21: 52 | E21: =IF(D21="","",IFERROR(INDEX(SSP!$E$2:$E$266, MATCH(D21, SSP!$F$2:$F$266, 0)),"")) -> Douleur abdominale ou épigastrique | F21: =Feuil1!E21 -> Amaurose | G21: Occlusion artérielle rétinienne | H21: Occlusion de l'artère centrale de la rétine (OACR) | J21: Perte du champ visuel unilatérale | K21: Occlusion aiguë de l'artère centrale de la rétine. Risque cardiaque. | N21: OACR | O21: =IFERROR(_xlfn.XLOOKUP($D21, SSP!$F:$F, SSP!$E:$E, "Inconnu"), "") -> Douleur abdominale ou épigastrique | P21: =IF(OR(E21="", O21=""), "", IF(LOWER(E21)=LOWER(O21), "OK", "⚠️ Libellé ≠ n°")) -> OK | Q21: =IF(Feuil1!$E21="", "", IF(LOWER(Feuil1!$E21)=LOWER(E21), "Identique", "Différent")) -> Différent | R21: =IF(OR(P21="⚠️ Libellé ≠ n°", O21="Inconnu"), "⚠️", IF(Q21="Différent", "ℹ️", "")) -> ℹ️ | S21: {=_xlfn.LET(_xlpm.genCat,IFERROR(LOWER(TRIM(G21)),""),_xlpm.principal,IFERROR(LOWER(TRIM(H21)),""),_xlpm.orig,IFERROR(LOWER(TRIM(N21)),""),IF(OR(_xlpm.genCat="",_xlpm.principal=""),"",IF(LEFT(LOWER(G21),5)="autre","OK (Autre)",IF(OR(ISNUMBER(SEARCH(_xlpm.genCat,_xlpm.principal)),ISNUMBER(SEARCH(_xlpm.principal,_xlpm.genCat)),AND(_xlpm.orig<>"",OR(ISNUMBER(SEARCH(_xlpm.genCat,_xlpm.orig)),ISNUMBER(SEARCH(_xlpm.orig,_xlpm.genCat))))),"OK","⚠️ À vérifier"))))} -> ⚠️ À vérifier | T21: =IF(S21="","",IF(S21="OK (Autre)","Diagnostic générique = 'Autre – …'",IF(S21="OK","Concordance générique/principal","Écart entre générique et principal"))) -> Écart entre générique et principal | U21: {=_xlfn.LET(_xlpm.yr, A21, _xlpm.diag, IF(N21<>"", N21, H21), _xlpm.base, TRIM(SUBSTITUTE(SUBSTITUTE(SUBSTITUTE(SUBSTITUTE(_xlpm.diag,"•"," "),CHAR(160)," "),CHAR(10)," ")," "," ")), LOWER(_xlpm.yr&"|"&_xlpm.base))} -> 2011|oacr | V21: =IFERROR(_xlfn.XLOOKUP($AB21,'Cas 2013-2017'!$K:$K,'Cas 2013-2017'!$D:$D,""),"") | W21: =IFERROR(_xlfn.XLOOKUP($AB21,'Cas 2013-2017'!$K:$K,'Cas 2013-2017'!$E:$E,""),"") | X21: =IFERROR(_xlfn.XLOOKUP($AB21,'Cas 2013-2017'!$K:$K,'Cas 2013-2017'!$F:$F,""),"") | Y21: =IFERROR(_xlfn.XLOOKUP($AB21,'Cas 2013-2017'!$K:$K,'Cas 2013-2017'!$G:$G,""),"") | Z21: =IFERROR(_xlfn.XLOOKUP($AB21,'Cas 2013-2017'!$K:$K,'Cas 2013-2017'!$I:$I,""),"") | AA21: =IFERROR(_xlfn.XLOOKUP($AB21,'Cas 2013-2017'!$K:$K,'Cas 2013-2017'!$H:$H,""),"") | AB21: =LOWER($A21 & "|" & $AF21) -> 2011|occlusion de l'artere centrale de la retine | AC21: =TRIM(SUBSTITUTE(SUBSTITUTE(SUBSTITUTE(SUBSTITUTE(" " & LOWER(TRIM(IF($N21<>"", $N21, $H21))) & " ", " aomi ", " arteriopathie des membres inferieurs "), " hta ", " hypertension arterielle "), " saos ", " syndrome d'apnees obstructives du sommeil "), " rgo ", " reflux gastro-oesophagien ") ) -> oacr | AD21: =TRIM(SUBSTITUTE(SUBSTITUTE(SUBSTITUTE(SUBSTITUTE(" " & LOWER(TRIM($AC21)) & " ", " oacr ", " occlusion de l'artere centrale de la retine "), " hsd ", " hematome sous-dural "), " fa ", " fibrillation auriculaire "), " ep ", " embolie pulmonaire ") ) -> occlusion de l'artere centrale de la retine | AE21: {=_xlfn.LET(_xlpm.base, " " & LOWER(TRIM($AD21)) & " ", _xlpm.s1, SUBSTITUTE(_xlpm.base, " ic ", " insuffisance cardiaque "), _xlpm.s2, SUBSTITUTE(_xlpm.s1, " avc ", " accident vasculaire cerebral "), _xlpm.s3, SUBSTITUTE(_xlpm.s2, " hsa ", " hemorragie sous-arachnoidienne "), _xlpm.s4, SUBSTITUTE(_xlpm.s3, " htp ", " hypertension pulmonaire "), _xlpm.s5, SUBSTITUTE(_xlpm.s4, " bpco ", " bronchopneumopathie chronique obstructive "), _xlpm.s6, SUBSTITUTE(_xlpm.s5, " dmla ", " degenerescence maculaire liee a l age "), TRIM(_xlpm.s6))} -> occlusion de l'artere centrale de la retine | AF21: {=_xlfn.LET(_xlpm.base, " " & LOWER(TRIM($AE21)) & " ", _xlpm.s1, SUBSTITUTE(_xlpm.base, " omi ", " oedemes des membres inferieurs "), _xlpm.s2, SUBSTITUTE(_xlpm.s1, " idm ", " infarctus du myocarde "), _xlpm.s3, SUBSTITUTE(_xlpm.s2, " tvp ", " thrombose veineuse profonde "), _xlpm.s4, SUBSTITUTE(_xlpm.s3, " geu ", " grossesse extra-uterine "), _xlpm.s5, SUBSTITUTE(_xlpm.s4, " fuo ", " fievre d origine indeterminee "), TRIM(_xlpm.s5))} -> occlusion de l'artere centrale de la retine
A22: 2011 | B22: 🧬 Maladies infectieuses | D22: 45 | E22: =IF(D22="","",IFERROR(INDEX(SSP!$E$2:$E$266, MATCH(D22, SSP!$F$2:$F$266, 0)),"")) -> Toux, expectoration, hémoptysie | F22: =Feuil1!E22 -> Toux | G22: Angine à streptocoque | H22: Angine Streptocoque | N22: Angine Streptocoque | O22: =IFERROR(_xlfn.XLOOKUP($D22, SSP!$F:$F, SSP!$E:$E, "Inconnu"), "") -> Toux, expectoration, hémoptysie | P22: =IF(OR(E22="", O22=""), "", IF(LOWER(E22)=LOWER(O22), "OK", "⚠️ Libellé ≠ n°")) -> OK | Q22: =IF(Feuil1!$E22="", "", IF(LOWER(Feuil1!$E22)=LOWER(E22), "Identique", "Différent")) -> Différent | R22: =IF(OR(P22="⚠️ Libellé ≠ n°", O22="Inconnu"), "⚠️", IF(Q22="Différent", "ℹ️", "")) -> ℹ️ | S22: {=_xlfn.LET(_xlpm.genCat,IFERROR(LOWER(TRIM(G22)),""),_xlpm.principal,IFERROR(LOWER(TRIM(H22)),""),_xlpm.orig,IFERROR(LOWER(TRIM(N22)),""),IF(OR(_xlpm.genCat="",_xlpm.principal=""),"",IF(LEFT(LOWER(G22),5)="autre","OK (Autre)",IF(OR(ISNUMBER(SEARCH(_xlpm.genCat,_xlpm.principal)),ISNUMBER(SEARCH(_xlpm.principal,_xlpm.genCat)),AND(_xlpm.orig<>"",OR(ISNUMBER(SEARCH(_xlpm.genCat,_xlpm.orig)),ISNUMBER(SEARCH(_xlpm.orig,_xlpm.genCat))))),"OK","⚠️ À vérifier"))))} -> ⚠️ À vérifier | T22: =IF(S22="","",IF(S22="OK (Autre)","Diagnostic générique = 'Autre – …'",IF(S22="OK","Concordance générique/principal","Écart entre générique et principal"))) -> Écart entre générique et principal | U22: {=_xlfn.LET(_xlpm.yr, A22, _xlpm.diag, IF(N22<>"", N22, H22), _xlpm.base, TRIM(SUBSTITUTE(SUBSTITUTE(SUBSTITUTE(SUBSTITUTE(_xlpm.diag,"•"," "),CHAR(160)," "),CHAR(10)," ")," "," ")), LOWER(_xlpm.yr&"|"&_xlpm.base))} -> 2011|angine streptocoque | V22: =IFERROR(_xlfn.XLOOKUP($AB22,'Cas 2013-2017'!$K:$K,'Cas 2013-2017'!$D:$D,""),"") | W22: =IFERROR(_xlfn.XLOOKUP($AB22,'Cas 2013-2017'!$K:$K,'Cas 2013-2017'!$E:$E,""),"") | X22: =IFERROR(_xlfn.XLOOKUP($AB22,'Cas 2013-2017'!$K:$K,'Cas 2013-2017'!$F:$F,""),"") | Y22: =IFERROR(_xlfn.XLOOKUP($AB22,'Cas 2013-2017'!$K:$K,'Cas 2013-2017'!$G:$G,""),"") | Z22: =IFERROR(_xlfn.XLOOKUP($AB22,'Cas 2013-2017'!$K:$K,'Cas 2013-2017'!$I:$I,""),"") | AA22: =IFERROR(_xlfn.XLOOKUP($AB22,'Cas 2013-2017'!$K:$K,'Cas 2013-2017'!$H:$H,""),"") | AB22: =LOWER($A22 & "|" & $AF22) -> 2011|angine streptocoque | AC22: =TRIM(SUBSTITUTE(SUBSTITUTE(SUBSTITUTE(SUBSTITUTE(" " & LOWER(TRIM(IF($N22<>"", $N22, $H22))) & " ", " aomi ", " arteriopathie des membres inferieurs "), " hta ", " hypertension arterielle "), " saos ", " syndrome d'apnees obstructives du sommeil "), " rgo ", " reflux gastro-oesophagien ") ) -> angine streptocoque | AD22: =TRIM(SUBSTITUTE(SUBSTITUTE(SUBSTITUTE(SUBSTITUTE(" " & LOWER(TRIM($AC22)) & " ", " oacr ", " occlusion de l'artere centrale de la retine "), " hsd ", " hematome sous-dural "), " fa ", " fibrillation auriculaire "), " ep ", " embolie pulmonaire ") ) -> angine streptocoque | AE22: {=_xlfn.LET(_xlpm.base, " " & LOWER(TRIM($AD22)) & " ", _xlpm.s1, SUBSTITUTE(_xlpm.base, " ic ", " insuffisance cardiaque "), _xlpm.s2, SUBSTITUTE(_xlpm.s1, " avc ", " accident vasculaire cerebral "), _xlpm.s3, SUBSTITUTE(_xlpm.s2, " hsa ", " hemorragie sous-arachnoidienne "), _xlpm.s4, SUBSTITUTE(_xlpm.s3, " htp ", " hypertension pulmonaire "), _xlpm.s5, SUBSTITUTE(_xlpm.s4, " bpco ", " bronchopneumopathie chronique obstructive "), _xlpm.s6, SUBSTITUTE(_xlpm.s5, " dmla ", " degenerescence maculaire liee a l age "), TRIM(_xlpm.s6))} -> angine streptocoque | AF22: {=_xlfn.LET(_xlpm.base, " " & LOWER(TRIM($AE22)) & " ", _xlpm.s1, SUBSTITUTE(_xlpm.base, " omi ", " oedemes des membres inferieurs "), _xlpm.s2, SUBSTITUTE(_xlpm.s1, " idm ", " infarctus du myocarde "), _xlpm.s3, SUBSTITUTE(_xlpm.s2, " tvp ", " thrombose veineuse profonde "), _xlpm.s4, SUBSTITUTE(_xlpm.s3, " geu ", " grossesse extra-uterine "), _xlpm.s5, SUBSTITUTE(_xlpm.s4, " fuo ", " fievre d origine indeterminee "), TRIM(_xlpm.s5))} -> angine streptocoque
A23: 2011 | B23: 🧪 Endocrinologie / Métabolisme | D23: 4 | E23: =IF(D23="","",IFERROR(INDEX(SSP!$E$2:$E$266, MATCH(D23, SSP!$F$2:$F$266, 0)),"")) -> Fatigue, asthénie | F23: =Feuil1!E23 -> Fatigue | G23: Autre – Endocrinologie / Métabolisme | H23: Acido-cétose sur diabète inaugural | J23: Enfant de 10 ans, apathie, perte de poids, respi profonde, polydipsie | K23: Anamnèse, discussion des diagnostics, résultats de laboratoire à confirmer. | N23: Acido-cétose sur diabète inaugural | O23: =IFERROR(_xlfn.XLOOKUP($D23, SSP!$F:$F, SSP!$E:$E, "Inconnu"), "") -> Fatigue, asthénie | P23: =IF(OR(E23="", O23=""), "", IF(LOWER(E23)=LOWER(O23), "OK", "⚠️ Libellé ≠ n°")) -> OK | Q23: =IF(Feuil1!$E23="", "", IF(LOWER(Feuil1!$E23)=LOWER(E23), "Identique", "Différent")) -> Différent | R23: =IF(OR(P23="⚠️ Libellé ≠ n°", O23="Inconnu"), "⚠️", IF(Q23="Différent", "ℹ️", "")) -> ℹ️ | S23: {=_xlfn.LET(_xlpm.genCat,IFERROR(LOWER(TRIM(G23)),""),_xlpm.principal,IFERROR(LOWER(TRIM(H23)),""),_xlpm.orig,IFERROR(LOWER(TRIM(N23)),""),IF(OR(_xlpm.genCat="",_xlpm.principal=""),"",IF(LEFT(LOWER(G23),5)="autre","OK (Autre)",IF(OR(ISNUMBER(SEARCH(_xlpm.genCat,_xlpm.principal)),ISNUMBER(SEARCH(_xlpm.principal,_xlpm.genCat)),AND(_xlpm.orig<>"",OR(ISNUMBER(SEARCH(_xlpm.genCat,_xlpm.orig)),ISNUMBER(SEARCH(_xlpm.orig,_xlpm.genCat))))),"OK","⚠️ À vérifier"))))} -> OK (Autre) | T23: =IF(S23="","",IF(S23="OK (Autre)","Diagnostic générique = 'Autre – …'",IF(S23="OK","Concordance générique/principal","Écart entre générique et principal"))) -> Diagnostic générique = 'Autre – …' | U23: {=_xlfn.LET(_xlpm.yr, A23, _xlpm.diag, IF(N23<>"", N23, H23), _xlpm.base, TRIM(SUBSTITUTE(SUBSTITUTE(SUBSTITUTE(SUBSTITUTE(_xlpm.diag,"•"," "),CHAR(160)," "),CHAR(10)," ")," "," ")), LOWER(_xlpm.yr&"|"&_xlpm.base))} -> 2011|acido-cétose sur diabète inaugural | V23: =IFERROR(_xlfn.XLOOKUP($AB23,'Cas 2013-2017'!$K:$K,'Cas 2013-2017'!$D:$D,""),"") | W23: =IFERROR(_xlfn.XLOOKUP($AB23,'Cas 2013-2017'!$K:$K,'Cas 2013-2017'!$E:$E,""),"") | X23: =IFERROR(_xlfn.XLOOKUP($AB23,'Cas 2013-2017'!$K:$K,'Cas 2013-2017'!$F:$F,""),"") | Y23: =IFERROR(_xlfn.XLOOKUP($AB23,'Cas 2013-2017'!$K:$K,'Cas 2013-2017'!$G:$G,""),"") | Z23: =IFERROR(_xlfn.XLOOKUP($AB23,'Cas 2013-2017'!$K:$K,'Cas 2013-2017'!$I:$I,""),"") | AA23: =IFERROR(_xlfn.XLOOKUP($AB23,'Cas 2013-2017'!$K:$K,'Cas 2013-2017'!$H:$H,""),"") | AB23: =LOWER($A23 & "|" & $AF23) -> 2011|acido-cétose sur diabète inaugural | AC23: =TRIM(SUBSTITUTE(SUBSTITUTE(SUBSTITUTE(SUBSTITUTE(" " & LOWER(TRIM(IF($N23<>"", $N23, $H23))) & " ", " aomi ", " arteriopathie des membres inferieurs "), " hta ", " hypertension arterielle "), " saos ", " syndrome d'apnees obstructives du sommeil "), " rgo ", " reflux gastro-oesophagien ") ) -> acido-cétose sur diabète inaugural | AD23: =TRIM(SUBSTITUTE(SUBSTITUTE(SUBSTITUTE(SUBSTITUTE(" " & LOWER(TRIM($AC23)) & " ", " oacr ", " occlusion de l'artere centrale de la retine "), " hsd ", " hematome sous-dural "), " fa ", " fibrillation auriculaire "), " ep ", " embolie pulmonaire ") ) -> acido-cétose sur diabète inaugural | AE23: {=_xlfn.LET(_xlpm.base, " " & LOWER(TRIM($AD23)) & " ", _xlpm.s1, SUBSTITUTE(_xlpm.base, " ic ", " insuffisance cardiaque "), _xlpm.s2, SUBSTITUTE(_xlpm.s1, " avc ", " accident vasculaire cerebral "), _xlpm.s3, SUBSTITUTE(_xlpm.s2, " hsa ", " hemorragie sous-arachnoidienne "), _xlpm.s4, SUBSTITUTE(_xlpm.s3, " htp ", " hypertension pulmonaire "), _xlpm.s5, SUBSTITUTE(_xlpm.s4, " bpco ", " bronchopneumopathie chronique obstructive "), _xlpm.s6, SUBSTITUTE(_xlpm.s5, " dmla ", " degenerescence maculaire liee a l age "), TRIM(_xlpm.s6))} -> acido-cétose sur diabète inaugural | AF23: {=_xlfn.LET(_xlpm.base, " " & LOWER(TRIM($AE23)) & " ", _xlpm.s1, SUBSTITUTE(_xlpm.base, " omi ", " oedemes des membres inferieurs "), _xlpm.s2, SUBSTITUTE(_xlpm.s1, " idm ", " infarctus du myocarde "), _xlpm.s3, SUBSTITUTE(_xlpm.s2, " tvp ", " thrombose veineuse profonde "), _xlpm.s4, SUBSTITUTE(_xlpm.s3, " geu ", " grossesse extra-uterine "), _xlpm.s5, SUBSTITUTE(_xlpm.s4, " fuo ", " fievre d origine indeterminee "), TRIM(_xlpm.s5))} -> acido-cétose sur diabète inaugural
A24: 2011 | B24: Autres diagnostics / non classés | D24: 58 | E24: =IF(D24="","",IFERROR(INDEX(SSP!$E$2:$E$266, MATCH(D24, SSP!$F$2:$F$266, 0)),"")) -> Constipation | F24: =Feuil1!E24 -> Constipation | G24: Autre – Autre | H24: Mucoviscidose | J24: Enfant de 3 ans avec constipation, prolapsus anal, toux, polypes nasaux | K24: Symptômes classiques avec photo des polypes nasaux. | N24: Mucoviscidose | O24: =IFERROR(_xlfn.XLOOKUP($D24, SSP!$F:$F, SSP!$E:$E, "Inconnu"), "") -> Constipation | P24: =IF(OR(E24="", O24=""), "", IF(LOWER(E24)=LOWER(O24), "OK", "⚠️ Libellé ≠ n°")) -> OK | Q24: =IF(Feuil1!$E24="", "", IF(LOWER(Feuil1!$E24)=LOWER(E24), "Identique", "Différent")) -> Identique | R24: =IF(OR(P24="⚠️ Libellé ≠ n°", O24="Inconnu"), "⚠️", IF(Q24="Différent", "ℹ️", "")) | S24: {=_xlfn.LET(_xlpm.genCat,IFERROR(LOWER(TRIM(G24)),""),_xlpm.principal,IFERROR(LOWER(TRIM(H24)),""),_xlpm.orig,IFERROR(LOWER(TRIM(N24)),""),IF(OR(_xlpm.genCat="",_xlpm.principal=""),"",IF(LEFT(LOWER(G24),5)="autre","OK (Autre)",IF(OR(ISNUMBER(SEARCH(_xlpm.genCat,_xlpm.principal)),ISNUMBER(SEARCH(_xlpm.principal,_xlpm.genCat)),AND(_xlpm.orig<>"",OR(ISNUMBER(SEARCH(_xlpm.genCat,_xlpm.orig)),ISNUMBER(SEARCH(_xlpm.orig,_xlpm.genCat))))),"OK","⚠️ À vérifier"))))} -> OK (Autre) | T24: =IF(S24="","",IF(S24="OK (Autre)","Diagnostic générique = 'Autre – …'",IF(S24="OK","Concordance générique/principal","Écart entre générique et principal"))) -> Diagnostic générique = 'Autre – …' | U24: {=_xlfn.LET(_xlpm.yr, A24, _xlpm.diag, IF(N24<>"", N24, H24), _xlpm.base, TRIM(SUBSTITUTE(SUBSTITUTE(SUBSTITUTE(SUBSTITUTE(_xlpm.diag,"•"," "),CHAR(160)," "),CHAR(10)," ")," "," ")), LOWER(_xlpm.yr&"|"&_xlpm.base))} -> 2011|mucoviscidose | V24: =IFERROR(_xlfn.XLOOKUP($AB24,'Cas 2013-2017'!$K:$K,'Cas 2013-2017'!$D:$D,""),"") | W24: =IFERROR(_xlfn.XLOOKUP($AB24,'Cas 2013-2017'!$K:$K,'Cas 2013-2017'!$E:$E,""),"") | X24: =IFERROR(_xlfn.XLOOKUP($AB24,'Cas 2013-2017'!$K:$K,'Cas 2013-2017'!$F:$F,""),"") | Y24: =IFERROR(_xlfn.XLOOKUP($AB24,'Cas 2013-2017'!$K:$K,'Cas 2013-2017'!$G:$G,""),"") | Z24: =IFERROR(_xlfn.XLOOKUP($AB24,'Cas 2013-2017'!$K:$K,'Cas 2013-2017'!$I:$I,""),"") | AA24: =IFERROR(_xlfn.XLOOKUP($AB24,'Cas 2013-2017'!$K:$K,'Cas 2013-2017'!$H:$H,""),"") | AB24: =LOWER($A24 & "|" & $AF24) -> 2011|mucoviscidose | AC24: =TRIM(SUBSTITUTE(SUBSTITUTE(SUBSTITUTE(SUBSTITUTE(" " & LOWER(TRIM(IF($N24<>"", $N24, $H24))) & " ", " aomi ", " arteriopathie des membres inferieurs "), " hta ", " hypertension arterielle "), " saos ", " syndrome d'apnees obstructives du sommeil "), " rgo ", " reflux gastro-oesophagien ") ) -> mucoviscidose | AD24: =TRIM(SUBSTITUTE(SUBSTITUTE(SUBSTITUTE(SUBSTITUTE(" " & LOWER(TRIM($AC24)) & " ", " oacr ", " occlusion de l'artere centrale de la retine "), " hsd ", " hematome sous-dural "), " fa ", " fibrillation auriculaire "), " ep ", " embolie pulmonaire ") ) -> mucoviscidose | AE24: {=_xlfn.LET(_xlpm.base, " " & LOWER(TRIM($AD24)) & " ", _xlpm.s1, SUBSTITUTE(_xlpm.base, " ic ", " insuffisance cardiaque "), _xlpm.s2, SUBSTITUTE(_xlpm.s1, " avc ", " accident vasculaire cerebral "), _xlpm.s3, SUBSTITUTE(_xlpm.s2, " hsa ", " hemorragie sous-arachnoidienne "), _xlpm.s4, SUBSTITUTE(_xlpm.s3, " htp ", " hypertension pulmonaire "), _xlpm.s5, SUBSTITUTE(_xlpm.s4, " bpco ", " bronchopneumopathie chronique obstructive "), _xlpm.s6, SUBSTITUTE(_xlpm.s5, " dmla ", " degenerescence maculaire liee a l age "), TRIM(_xlpm.s6))} -> mucoviscidose | AF24: {=_xlfn.LET(_xlpm.base, " " & LOWER(TRIM($AE24)) & " ", _xlpm.s1, SUBSTITUTE(_xlpm.base, " omi ", " oedemes des membres inferieurs "), _xlpm.s2, SUBSTITUTE(_xlpm.s1, " idm ", " infarctus du myocarde "), _xlpm.s3, SUBSTITUTE(_xlpm.s2, " tvp ", " thrombose veineuse profonde "), _xlpm.s4, SUBSTITUTE(_xlpm.s3, " geu ", " grossesse extra-uterine "), _xlpm.s5, SUBSTITUTE(_xlpm.s4, " fuo ", " fievre d origine indeterminee "), TRIM(_xlpm.s5))} -> mucoviscidose
A25: 2011 | B25: Autres diagnostics / non classés | D25: 10 | E25: =IF(D25="","",IFERROR(INDEX(SSP!$E$2:$E$266, MATCH(D25, SSP!$F$2:$F$266, 0)),"")) -> Douleur (toutes localisations et types confondus) | F25: =Feuil1!E25 -> Douleur testiculaire | G25: Autre – Autre | H25: Torsion testiculaire | J25: Nouveau-né de 3 mois avec scrotum rouge et sensible | K25: Urgence pédiatrique avec évaluation négative de la fluoroscopie. | N25: Torsion testiculaire | O25: =IFERROR(_xlfn.XLOOKUP($D25, SSP!$F:$F, SSP!$E:$E, "Inconnu"), "") -> Douleur (toutes localisations et types confondus) | P25: =IF(OR(E25="", O25=""), "", IF(LOWER(E25)=LOWER(O25), "OK", "⚠️ Libellé ≠ n°")) -> OK | Q25: =IF(Feuil1!$E25="", "", IF(LOWER(Feuil1!$E25)=LOWER(E25), "Identique", "Différent")) -> Différent | R25: =IF(OR(P25="⚠️ Libellé ≠ n°", O25="Inconnu"), "⚠️", IF(Q25="Différent", "ℹ️", "")) -> ℹ️ | S25: {=_xlfn.LET(_xlpm.genCat,IFERROR(LOWER(TRIM(G25)),""),_xlpm.principal,IFERROR(LOWER(TRIM(H25)),""),_xlpm.orig,IFERROR(LOWER(TRIM(N25)),""),IF(OR(_xlpm.genCat="",_xlpm.principal=""),"",IF(LEFT(LOWER(G25),5)="autre","OK (Autre)",IF(OR(ISNUMBER(SEARCH(_xlpm.genCat,_xlpm.principal)),ISNUMBER(SEARCH(_xlpm.principal,_xlpm.genCat)),AND(_xlpm.orig<>"",OR(ISNUMBER(SEARCH(_xlpm.genCat,_xlpm.orig)),ISNUMBER(SEARCH(_xlpm.orig,_xlpm.genCat))))),"OK","⚠️ À vérifier"))))} -> OK (Autre) | T25: =IF(S25="","",IF(S25="OK (Autre)","Diagnostic générique = 'Autre – …'",IF(S25="OK","Concordance générique/principal","Écart entre générique et principal"))) -> Diagnostic générique = 'Autre – …' | U25: {=_xlfn.LET(_xlpm.yr, A25, _xlpm.diag, IF(N25<>"", N25, H25), _xlpm.base, TRIM(SUBSTITUTE(SUBSTITUTE(SUBSTITUTE(SUBSTITUTE(_xlpm.diag,"•"," "),CHAR(160)," "),CHAR(10)," ")," "," ")), LOWER(_xlpm.yr&"|"&_xlpm.base))} -> 2011|torsion testiculaire | V25: =IFERROR(_xlfn.XLOOKUP($AB25,'Cas 2013-2017'!$K:$K,'Cas 2013-2017'!$D:$D,""),"") | W25: =IFERROR(_xlfn.XLOOKUP($AB25,'Cas 2013-2017'!$K:$K,'Cas 2013-2017'!$E:$E,""),"") | X25: =IFERROR(_xlfn.XLOOKUP($AB25,'Cas 2013-2017'!$K:$K,'Cas 2013-2017'!$F:$F,""),"") | Y25: =IFERROR(_xlfn.XLOOKUP($AB25,'Cas 2013-2017'!$K:$K,'Cas 2013-2017'!$G:$G,""),"") | Z25: =IFERROR(_xlfn.XLOOKUP($AB25,'Cas 2013-2017'!$K:$K,'Cas 2013-2017'!$I:$I,""),"") | AA25: =IFERROR(_xlfn.XLOOKUP($AB25,'Cas 2013-2017'!$K:$K,'Cas 2013-2017'!$H:$H,""),"") | AB25: =LOWER($A25 & "|" & $AF25) -> 2011|torsion testiculaire | AC25: =TRIM(SUBSTITUTE(SUBSTITUTE(SUBSTITUTE(SUBSTITUTE(" " & LOWER(TRIM(IF($N25<>"", $N25, $H25))) & " ", " aomi ", " arteriopathie des membres inferieurs "), " hta ", " hypertension arterielle "), " saos ", " syndrome d'apnees obstructives du sommeil "), " rgo ", " reflux gastro-oesophagien ") ) -> torsion testiculaire | AD25: =TRIM(SUBSTITUTE(SUBSTITUTE(SUBSTITUTE(SUBSTITUTE(" " & LOWER(TRIM($AC25)) & " ", " oacr ", " occlusion de l'artere centrale de la retine "), " hsd ", " hematome sous-dural "), " fa ", " fibrillation auriculaire "), " ep ", " embolie pulmonaire ") ) -> torsion testiculaire | AE25: {=_xlfn.LET(_xlpm.base, " " & LOWER(TRIM($AD25)) & " ", _xlpm.s1, SUBSTITUTE(_xlpm.base, " ic ", " insuffisance cardiaque "), _xlpm.s2, SUBSTITUTE(_xlpm.s1, " avc ", " accident vasculaire cerebral "), _xlpm.s3, SUBSTITUTE(_xlpm.s2, " hsa ", " hemorragie sous-arachnoidienne "), _xlpm.s4, SUBSTITUTE(_xlpm.s3, " htp ", " hypertension pulmonaire "), _xlpm.s5, SUBSTITUTE(_xlpm.s4, " bpco ", " bronchopneumopathie chronique obstructive "), _xlpm.s6, SUBSTITUTE(_xlpm.s5, " dmla ", " degenerescence maculaire liee a l age "), TRIM(_xlpm.s6))} -> torsion testiculaire | AF25: {=_xlfn.LET(_xlpm.base, " " & LOWER(TRIM($AE25)) & " ", _xlpm.s1, SUBSTITUTE(_xlpm.base, " omi ", " oedemes des membres inferieurs "), _xlpm.s2, SUBSTITUTE(_xlpm.s1, " idm ", " infarctus du myocarde "), _xlpm.s3, SUBSTITUTE(_xlpm.s2, " tvp ", " thrombose veineuse profonde "), _xlpm.s4, SUBSTITUTE(_xlpm.s3, " geu ", " grossesse extra-uterine "), _xlpm.s5, SUBSTITUTE(_xlpm.s4, " fuo ", " fievre d origine indeterminee "), TRIM(_xlpm.s5))} -> torsion testiculaire
A26: 2011 | B26: 🫁 Pneumologie | D26: 44 | E26: =IF(D26="","",IFERROR(INDEX(SSP!$E$2:$E$266, MATCH(D26, SSP!$F$2:$F$266, 0)),"")) -> Douleur thoracique | F26: =Feuil1!E26 -> Douleur thoracique | G26: Pneumothorax | H26: Pneumothorax | J26: Homme de 32 ans avec douleur thoracique supérieure droite soudaine. | K26: Signes vitaux : PA légèrement diminuée, pouls légèrement augmenté, fréquence respiratoire 22, température de 36,7 °C. Aucun résultat clinique trouvé lors de l'examen. | N26: Pneumothorax | O26: =IFERROR(_xlfn.XLOOKUP($D26, SSP!$F:$F, SSP!$E:$E, "Inconnu"), "") -> Douleur thoracique | P26: =IF(OR(E26="", O26=""), "", IF(LOWER(E26)=LOWER(O26), "OK", "⚠️ Libellé ≠ n°")) -> OK | Q26: =IF(Feuil1!$E26="", "", IF(LOWER(Feuil1!$E26)=LOWER(E26), "Identique", "Différent")) -> Identique | R26: =IF(OR(P26="⚠️ Libellé ≠ n°", O26="Inconnu"), "⚠️", IF(Q26="Différent", "ℹ️", "")) | S26: {=_xlfn.LET(_xlpm.genCat,IFERROR(LOWER(TRIM(G26)),""),_xlpm.principal,IFERROR(LOWER(TRIM(H26)),""),_xlpm.orig,IFERROR(LOWER(TRIM(N26)),""),IF(OR(_xlpm.genCat="",_xlpm.principal=""),"",IF(LEFT(LOWER(G26),5)="autre","OK (Autre)",IF(OR(ISNUMBER(SEARCH(_xlpm.genCat,_xlpm.principal)),ISNUMBER(SEARCH(_xlpm.principal,_xlpm.genCat)),AND(_xlpm.orig<>"",OR(ISNUMBER(SEARCH(_xlpm.genCat,_xlpm.orig)),ISNUMBER(SEARCH(_xlpm.orig,_xlpm.genCat))))),"OK","⚠️ À vérifier"))))} -> OK | T26: =IF(S26="","",IF(S26="OK (Autre)","Diagnostic générique = 'Autre – …'",IF(S26="OK","Concordance générique/principal","Écart entre générique et principal"))) -> Concordance générique/principal | U26: {=_xlfn.LET(_xlpm.yr, A26, _xlpm.diag, IF(N26<>"", N26, H26), _xlpm.base, TRIM(SUBSTITUTE(SUBSTITUTE(SUBSTITUTE(SUBSTITUTE(_xlpm.diag,"•"," "),CHAR(160)," "),CHAR(10)," ")," "," ")), LOWER(_xlpm.yr&"|"&_xlpm.base))} -> 2011|pneumothorax | V26: =IFERROR(_xlfn.XLOOKUP($AB26,'Cas 2013-2017'!$K:$K,'Cas 2013-2017'!$D:$D,""),"") | W26: =IFERROR(_xlfn.XLOOKUP($AB26,'Cas 2013-2017'!$K:$K,'Cas 2013-2017'!$E:$E,""),"") | X26: =IFERROR(_xlfn.XLOOKUP($AB26,'Cas 2013-2017'!$K:$K,'Cas 2013-2017'!$F:$F,""),"") | Y26: =IFERROR(_xlfn.XLOOKUP($AB26,'Cas 2013-2017'!$K:$K,'Cas 2013-2017'!$G:$G,""),"") | Z26: =IFERROR(_xlfn.XLOOKUP($AB26,'Cas 2013-2017'!$K:$K,'Cas 2013-2017'!$I:$I,""),"") | AA26: =IFERROR(_xlfn.XLOOKUP($AB26,'Cas 2013-2017'!$K:$K,'Cas 2013-2017'!$H:$H,""),"") | AB26: =LOWER($A26 & "|" & $AF26) -> 2011|pneumothorax | AC26: =TRIM(SUBSTITUTE(SUBSTITUTE(SUBSTITUTE(SUBSTITUTE(" " & LOWER(TRIM(IF($N26<>"", $N26, $H26))) & " ", " aomi ", " arteriopathie des membres inferieurs "), " hta ", " hypertension arterielle "), " saos ", " syndrome d'apnees obstructives du sommeil "), " rgo ", " reflux gastro-oesophagien ") ) -> pneumothorax | AD26: =TRIM(SUBSTITUTE(SUBSTITUTE(SUBSTITUTE(SUBSTITUTE(" " & LOWER(TRIM($AC26)) & " ", " oacr ", " occlusion de l'artere centrale de la retine "), " hsd ", " hematome sous-dural "), " fa ", " fibrillation auriculaire "), " ep ", " embolie pulmonaire ") ) -> pneumothorax | AE26: {=_xlfn.LET(_xlpm.base, " " & LOWER(TRIM($AD26)) & " ", _xlpm.s1, SUBSTITUTE(_xlpm.base, " ic ", " insuffisance cardiaque "), _xlpm.s2, SUBSTITUTE(_xlpm.s1, " avc ", " accident vasculaire cerebral "), _xlpm.s3, SUBSTITUTE(_xlpm.s2, " hsa ", " hemorragie sous-arachnoidienne "), _xlpm.s4, SUBSTITUTE(_xlpm.s3, " htp ", " hypertension pulmonaire "), _xlpm.s5, SUBSTITUTE(_xlpm.s4, " bpco ", " bronchopneumopathie chronique obstructive "), _xlpm.s6, SUBSTITUTE(_xlpm.s5, " dmla ", " degenerescence maculaire liee a l age "), TRIM(_xlpm.s6))} -> pneumothorax | AF26: {=_xlfn.LET(_xlpm.base, " " & LOWER(TRIM($AE26)) & " ", _xlpm.s1, SUBSTITUTE(_xlpm.base, " omi ", " oedemes des membres inferieurs "), _xlpm.s2, SUBSTITUTE(_xlpm.s1, " idm ", " infarctus du myocarde "), _xlpm.s3, SUBSTITUTE(_xlpm.s2, " tvp ", " thrombose veineuse profonde "), _xlpm.s4, SUBSTITUTE(_xlpm.s3, " geu ", " grossesse extra-uterine "), _xlpm.s5, SUBSTITUTE(_xlpm.s4, " fuo ", " fievre d origine indeterminee "), TRIM(_xlpm.s5))} -> pneumothorax
A27: 2011 | B27: 🫁 Pneumologie | D27: 4 | E27: =IF(D27="","",IFERROR(INDEX(SSP!$E$2:$E$266, MATCH(D27, SSP!$F$2:$F$266, 0)),"")) -> Fatigue, asthénie | F27: =Feuil1!E27 -> Fatigue | G27: Autre – Pneumologie | H27: Syndrome d'apnées obstructives du sommeil (SAOS) | J27: Homme avec fatigue | N27: SAOS | O27: =IFERROR(_xlfn.XLOOKUP($D27, SSP!$F:$F, SSP!$E:$E, "Inconnu"), "") -> Fatigue, asthénie | P27: =IF(OR(E27="", O27=""), "", IF(LOWER(E27)=LOWER(O27), "OK", "⚠️ Libellé ≠ n°")) -> OK | Q27: =IF(Feuil1!$E27="", "", IF(LOWER(Feuil1!$E27)=LOWER(E27), "Identique", "Différent")) -> Différent | R27: =IF(OR(P27="⚠️ Libellé ≠ n°", O27="Inconnu"), "⚠️", IF(Q27="Différent", "ℹ️", "")) -> ℹ️ | S27: {=_xlfn.LET(_xlpm.genCat,IFERROR(LOWER(TRIM(G27)),""),_xlpm.principal,IFERROR(LOWER(TRIM(H27)),""),_xlpm.orig,IFERROR(LOWER(TRIM(N27)),""),IF(OR(_xlpm.genCat="",_xlpm.principal=""),"",IF(LEFT(LOWER(G27),5)="autre","OK (Autre)",IF(OR(ISNUMBER(SEARCH(_xlpm.genCat,_xlpm.principal)),ISNUMBER(SEARCH(_xlpm.principal,_xlpm.genCat)),AND(_xlpm.orig<>"",OR(ISNUMBER(SEARCH(_xlpm.genCat,_xlpm.orig)),ISNUMBER(SEARCH(_xlpm.orig,_xlpm.genCat))))),"OK","⚠️ À vérifier"))))} -> OK (Autre) | T27: =IF(S27="","",IF(S27="OK (Autre)","Diagnostic générique = 'Autre – …'",IF(S27="OK","Concordance générique/principal","Écart entre générique et principal"))) -> Diagnostic générique = 'Autre – …' | U27: {=_xlfn.LET(_xlpm.yr, A27, _xlpm.diag, IF(N27<>"", N27, H27), _xlpm.base, TRIM(SUBSTITUTE(SUBSTITUTE(SUBSTITUTE(SUBSTITUTE(_xlpm.diag,"•"," "),CHAR(160)," "),CHAR(10)," ")," "," ")), LOWER(_xlpm.yr&"|"&_xlpm.base))} -> 2011|saos | V27: =IFERROR(_xlfn.XLOOKUP($AB27,'Cas 2013-2017'!$K:$K,'Cas 2013-2017'!$D:$D,""),"") | W27: =IFERROR(_xlfn.XLOOKUP($AB27,'Cas 2013-2017'!$K:$K,'Cas 2013-2017'!$E:$E,""),"") | X27: =IFERROR(_xlfn.XLOOKUP($AB27,'Cas 2013-2017'!$K:$K,'Cas 2013-2017'!$F:$F,""),"") | Y27: =IFERROR(_xlfn.XLOOKUP($AB27,'Cas 2013-2017'!$K:$K,'Cas 2013-2017'!$G:$G,""),"") | Z27: =IFERROR(_xlfn.XLOOKUP($AB27,'Cas 2013-2017'!$K:$K,'Cas 2013-2017'!$I:$I,""),"") | AA27: =IFERROR(_xlfn.XLOOKUP($AB27,'Cas 2013-2017'!$K:$K,'Cas 2013-2017'!$H:$H,""),"") | AB27: =LOWER($A27 & "|" & $AF27) -> 2011|syndrome d'apnees obstructives du sommeil | AC27: =TRIM(SUBSTITUTE(SUBSTITUTE(SUBSTITUTE(SUBSTITUTE(" " & LOWER(TRIM(IF($N27<>"", $N27, $H27))) & " ", " aomi ", " arteriopathie des membres inferieurs "), " hta ", " hypertension arterielle "), " saos ", " syndrome d'apnees obstructives du sommeil "), " rgo ", " reflux gastro-oesophagien ") ) -> syndrome d'apnees obstructives du sommeil | AD27: =TRIM(SUBSTITUTE(SUBSTITUTE(SUBSTITUTE(SUBSTITUTE(" " & LOWER(TRIM($AC27)) & " ", " oacr ", " occlusion de l'artere centrale de la retine "), " hsd ", " hematome sous-dural "), " fa ", " fibrillation auriculaire "), " ep ", " embolie pulmonaire ") ) -> syndrome d'apnees obstructives du sommeil | AE27: {=_xlfn.LET(_xlpm.base, " " & LOWER(TRIM($AD27)) & " ", _xlpm.s1, SUBSTITUTE(_xlpm.base, " ic ", " insuffisance cardiaque "), _xlpm.s2, SUBSTITUTE(_xlpm.s1, " avc ", " accident vasculaire cerebral "), _xlpm.s3, SUBSTITUTE(_xlpm.s2, " hsa ", " hemorragie sous-arachnoidienne "), _xlpm.s4, SUBSTITUTE(_xlpm.s3, " htp ", " hypertension pulmonaire "), _xlpm.s5, SUBSTITUTE(_xlpm.s4, " bpco ", " bronchopneumopathie chronique obstructive "), _xlpm.s6, SUBSTITUTE(_xlpm.s5, " dmla ", " degenerescence maculaire liee a l age "), TRIM(_xlpm.s6))} -> syndrome d'apnees obstructives du sommeil | AF27: {=_xlfn.LET(_xlpm.base, " " & LOWER(TRIM($AE27)) & " ", _xlpm.s1, SUBSTITUTE(_xlpm.base, " omi ", " oedemes des membres inferieurs "), _xlpm.s2, SUBSTITUTE(_xlpm.s1, " idm ", " infarctus du myocarde "), _xlpm.s3, SUBSTITUTE(_xlpm.s2, " tvp ", " thrombose veineuse profonde "), _xlpm.s4, SUBSTITUTE(_xlpm.s3, " geu ", " grossesse extra-uterine "), _xlpm.s5, SUBSTITUTE(_xlpm.s4, " fuo ", " fievre d origine indeterminee "), TRIM(_xlpm.s5))} -> syndrome d'apnees obstructives du sommeil
A28: 2011 | B28: 🧠🧑‍⚕️ Psychiatrie / Psychologie | D28: 119 | E28: =IF(D28="","",IFERROR(INDEX(SSP!$E$2:$E$266, MATCH(D28, SSP!$F$2:$F$266, 0)),"")) -> Trouble du déficit de l’attention | F28: =Feuil1!E28 -> Trouble de l'humeur | G28: Trouble bipolaire | H28: Trouble bipolaire | J28: Hypomanie | K28: Sous ad pour depression, probable virage hypomaniaque | N28: Trouble bipolaire | O28: =IFERROR(_xlfn.XLOOKUP($D28, SSP!$F:$F, SSP!$E:$E, "Inconnu"), "") -> Trouble du déficit de l’attention | P28: =IF(OR(E28="", O28=""), "", IF(LOWER(E28)=LOWER(O28), "OK", "⚠️ Libellé ≠ n°")) -> OK | Q28: =IF(Feuil1!$E28="", "", IF(LOWER(Feuil1!$E28)=LOWER(E28), "Identique", "Différent")) -> Différent | R28: =IF(OR(P28="⚠️ Libellé ≠ n°", O28="Inconnu"), "⚠️", IF(Q28="Différent", "ℹ️", "")) -> ℹ️ | S28: {=_xlfn.LET(_xlpm.genCat,IFERROR(LOWER(TRIM(G28)),""),_xlpm.principal,IFERROR(LOWER(TRIM(H28)),""),_xlpm.orig,IFERROR(LOWER(TRIM(N28)),""),IF(OR(_xlpm.genCat="",_xlpm.principal=""),"",IF(LEFT(LOWER(G28),5)="autre","OK (Autre)",IF(OR(ISNUMBER(SEARCH(_xlpm.genCat,_xlpm.principal)),ISNUMBER(SEARCH(_xlpm.principal,_xlpm.genCat)),AND(_xlpm.orig<>"",OR(ISNUMBER(SEARCH(_xlpm.genCat,_xlpm.orig)),ISNUMBER(SEARCH(_xlpm.orig,_xlpm.genCat))))),"OK","⚠️ À vérifier"))))} -> OK | T28: =IF(S28="","",IF(S28="OK (Autre)","Diagnostic générique = 'Autre – …'",IF(S28="OK","Concordance générique/principal","Écart entre générique et principal"))) -> Concordance générique/principal | U28: {=_xlfn.LET(_xlpm.yr, A28, _xlpm.diag, IF(N28<>"", N28, H28), _xlpm.base, TRIM(SUBSTITUTE(SUBSTITUTE(SUBSTITUTE(SUBSTITUTE(_xlpm.diag,"•"," "),CHAR(160)," "),CHAR(10)," ")," "," ")), LOWER(_xlpm.yr&"|"&_xlpm.base))} -> 2011|trouble bipolaire | V28: =IFERROR(_xlfn.XLOOKUP($AB28,'Cas 2013-2017'!$K:$K,'Cas 2013-2017'!$D:$D,""),"") | W28: =IFERROR(_xlfn.XLOOKUP($AB28,'Cas 2013-2017'!$K:$K,'Cas 2013-2017'!$E:$E,""),"") | X28: =IFERROR(_xlfn.XLOOKUP($AB28,'Cas 2013-2017'!$K:$K,'Cas 2013-2017'!$F:$F,""),"") | Y28: =IFERROR(_xlfn.XLOOKUP($AB28,'Cas 2013-2017'!$K:$K,'Cas 2013-2017'!$G:$G,""),"") | Z28: =IFERROR(_xlfn.XLOOKUP($AB28,'Cas 2013-2017'!$K:$K,'Cas 2013-2017'!$I:$I,""),"") | AA28: =IFERROR(_xlfn.XLOOKUP($AB28,'Cas 2013-2017'!$K:$K,'Cas 2013-2017'!$H:$H,""),"") | AB28: =LOWER($A28 & "|" & $AF28) -> 2011|trouble bipolaire | AC28: =TRIM(SUBSTITUTE(SUBSTITUTE(SUBSTITUTE(SUBSTITUTE(" " & LOWER(TRIM(IF($N28<>"", $N28, $H28))) & " ", " aomi ", " arteriopathie des membres inferieurs "), " hta ", " hypertension arterielle "), " saos ", " syndrome d'apnees obstructives du sommeil "), " rgo ", " reflux gastro-oesophagien ") ) -> trouble bipolaire | AD28: =TRIM(SUBSTITUTE(SUBSTITUTE(SUBSTITUTE(SUBSTITUTE(" " & LOWER(TRIM($AC28)) & " ", " oacr ", " occlusion de l'artere centrale de la retine "), " hsd ", " hematome sous-dural "), " fa ", " fibrillation auriculaire "), " ep ", " embolie pulmonaire ") ) -> trouble bipolaire | AE28: {=_xlfn.LET(_xlpm.base, " " & LOWER(TRIM($AD28)) & " ", _xlpm.s1, SUBSTITUTE(_xlpm.base, " ic ", " insuffisance cardiaque "), _xlpm.s2, SUBSTITUTE(_xlpm.s1, " avc ", " accident vasculaire cerebral "), _xlpm.s3, SUBSTITUTE(_xlpm.s2, " hsa ", " hemorragie sous-arachnoidienne "), _xlpm.s4, SUBSTITUTE(_xlpm.s3, " htp ", " hypertension pulmonaire "), _xlpm.s5, SUBSTITUTE(_xlpm.s4, " bpco ", " bronchopneumopathie chronique obstructive "), _xlpm.s6, SUBSTITUTE(_xlpm.s5, " dmla ", " degenerescence maculaire liee a l age "), TRIM(_xlpm.s6))} -> trouble bipolaire | AF28: {=_xlfn.LET(_xlpm.base, " " & LOWER(TRIM($AE28)) & " ", _xlpm.s1, SUBSTITUTE(_xlpm.base, " omi ", " oedemes des membres inferieurs "), _xlpm.s2, SUBSTITUTE(_xlpm.s1, " idm ", " infarctus du myocarde "), _xlpm.s3, SUBSTITUTE(_xlpm.s2, " tvp ", " thrombose veineuse profonde "), _xlpm.s4, SUBSTITUTE(_xlpm.s3, " geu ", " grossesse extra-uterine "), _xlpm.s5, SUBSTITUTE(_xlpm.s4, " fuo ", " fievre d origine indeterminee "), TRIM(_xlpm.s5))} -> trouble bipolaire
A29: 2011 | B29: 🧠🧑‍⚕️ Psychiatrie / Psychologie | D29: 50 | E29: =IF(D29="","",IFERROR(INDEX(SSP!$E$2:$E$266, MATCH(D29, SSP!$F$2:$F$266, 0)),"")) -> Palpitations | F29: =Feuil1!E29 -> Palpitations | G29: Autre – ‍️ Psychiatrie / Psychologie | H29: Phobie sociale | I29: Anxieté / PTSD | J29: Palpitations | N29: Phobie sociale | O29: =IFERROR(_xlfn.XLOOKUP($D29, SSP!$F:$F, SSP!$E:$E, "Inconnu"), "") -> Palpitations | P29: =IF(OR(E29="", O29=""), "", IF(LOWER(E29)=LOWER(O29), "OK", "⚠️ Libellé ≠ n°")) -> OK | Q29: =IF(Feuil1!$E29="", "", IF(LOWER(Feuil1!$E29)=LOWER(E29), "Identique", "Différent")) -> Identique | R29: =IF(OR(P29="⚠️ Libellé ≠ n°", O29="Inconnu"), "⚠️", IF(Q29="Différent", "ℹ️", "")) | S29: {=_xlfn.LET(_xlpm.genCat,IFERROR(LOWER(TRIM(G29)),""),_xlpm.principal,IFERROR(LOWER(TRIM(H29)),""),_xlpm.orig,IFERROR(LOWER(TRIM(N29)),""),IF(OR(_xlpm.genCat="",_xlpm.principal=""),"",IF(LEFT(LOWER(G29),5)="autre","OK (Autre)",IF(OR(ISNUMBER(SEARCH(_xlpm.genCat,_xlpm.principal)),ISNUMBER(SEARCH(_xlpm.principal,_xlpm.genCat)),AND(_xlpm.orig<>"",OR(ISNUMBER(SEARCH(_xlpm.genCat,_xlpm.orig)),ISNUMBER(SEARCH(_xlpm.orig,_xlpm.genCat))))),"OK","⚠️ À vérifier"))))} -> OK (Autre) | T29: =IF(S29="","",IF(S29="OK (Autre)","Diagnostic générique = 'Autre – …'",IF(S29="OK","Concordance générique/principal","Écart entre générique et principal"))) -> Diagnostic générique = 'Autre – …' | U29: {=_xlfn.LET(_xlpm.yr, A29, _xlpm.diag, IF(N29<>"", N29, H29), _xlpm.base, TRIM(SUBSTITUTE(SUBSTITUTE(SUBSTITUTE(SUBSTITUTE(_xlpm.diag,"•"," "),CHAR(160)," "),CHAR(10)," ")," "," ")), LOWER(_xlpm.yr&"|"&_xlpm.base))} -> 2011|phobie sociale | V29: =IFERROR(_xlfn.XLOOKUP($AB29,'Cas 2013-2017'!$K:$K,'Cas 2013-2017'!$D:$D,""),"") | W29: =IFERROR(_xlfn.XLOOKUP($AB29,'Cas 2013-2017'!$K:$K,'Cas 2013-2017'!$E:$E,""),"") | X29: =IFERROR(_xlfn.XLOOKUP($AB29,'Cas 2013-2017'!$K:$K,'Cas 2013-2017'!$F:$F,""),"") | Y29: =IFERROR(_xlfn.XLOOKUP($AB29,'Cas 2013-2017'!$K:$K,'Cas 2013-2017'!$G:$G,""),"") | Z29: =IFERROR(_xlfn.XLOOKUP($AB29,'Cas 2013-2017'!$K:$K,'Cas 2013-2017'!$I:$I,""),"") | AA29: =IFERROR(_xlfn.XLOOKUP($AB29,'Cas 2013-2017'!$K:$K,'Cas 2013-2017'!$H:$H,""),"") | AB29: =LOWER($A29 & "|" & $AF29) -> 2011|phobie sociale | AC29: =TRIM(SUBSTITUTE(SUBSTITUTE(SUBSTITUTE(SUBSTITUTE(" " & LOWER(TRIM(IF($N29<>"", $N29, $H29))) & " ", " aomi ", " arteriopathie des membres inferieurs "), " hta ", " hypertension arterielle "), " saos ", " syndrome d'apnees obstructives du sommeil "), " rgo ", " reflux gastro-oesophagien ") ) -> phobie sociale | AD29: =TRIM(SUBSTITUTE(SUBSTITUTE(SUBSTITUTE(SUBSTITUTE(" " & LOWER(TRIM($AC29)) & " ", " oacr ", " occlusion de l'artere centrale de la retine "), " hsd ", " hematome sous-dural "), " fa ", " fibrillation auriculaire "), " ep ", " embolie pulmonaire ") ) -> phobie sociale | AE29: {=_xlfn.LET(_xlpm.base, " " & LOWER(TRIM($AD29)) & " ", _xlpm.s1, SUBSTITUTE(_xlpm.base, " ic ", " insuffisance cardiaque "), _xlpm.s2, SUBSTITUTE(_xlpm.s1, " avc ", " accident vasculaire cerebral "), _xlpm.s3, SUBSTITUTE(_xlpm.s2, " hsa ", " hemorragie sous-arachnoidienne "), _xlpm.s4, SUBSTITUTE(_xlpm.s3, " htp ", " hypertension pulmonaire "), _xlpm.s5, SUBSTITUTE(_xlpm.s4, " bpco ", " bronchopneumopathie chronique obstructive "), _xlpm.s6, SUBSTITUTE(_xlpm.s5, " dmla ", " degenerescence maculaire liee a l age "), TRIM(_xlpm.s6))} -> phobie sociale | AF29: {=_xlfn.LET(_xlpm.base, " " & LOWER(TRIM($AE29)) & " ", _xlpm.s1, SUBSTITUTE(_xlpm.base, " omi ", " oedemes des membres inferieurs "), _xlpm.s2, SUBSTITUTE(_xlpm.s1, " idm ", " infarctus du myocarde "), _xlpm.s3, SUBSTITUTE(_xlpm.s2, " tvp ", " thrombose veineuse profonde "), _xlpm.s4, SUBSTITUTE(_xlpm.s3, " geu ", " grossesse extra-uterine "), _xlpm.s5, SUBSTITUTE(_xlpm.s4, " fuo ", " fievre d origine indeterminee "), TRIM(_xlpm.s5))} -> phobie sociale
A30: 2011 | B30: 🧪 Endocrinologie / Métabolisme | D30: 224 | E30: =IF(D30="","",IFERROR(INDEX(SSP!$E$2:$E$266, MATCH(D30, SSP!$F$2:$F$266, 0)),"")) -> Demande de bilan de santé, d’examens radiologiques ou biologiques | F30: =Feuil1!E30 -> Bilan | G30: Ostéoporose | H30: Ostéoporose | J30: Femme de 56 ans préoccupée par l'ostéoporose après avoir vu un documentaire. | K30: Anamnèse orientée, examen physique, discussion sur les risques et les procédures supplémentaires. Aucun signe d'ostéoporose détecté, DEXA non recommandée. Discussion sur la TOS à revoir. (évaluation de la nécessité de DEXA, discussion de la thérapie hormonale (TOS) en raison du cancer de l'utérus chez la mère) | N30: Ostéoporose | O30: =IFERROR(_xlfn.XLOOKUP($D30, SSP!$F:$F, SSP!$E:$E, "Inconnu"), "") -> Demande de bilan de santé, d’examens radiologiques ou biologiques | P30: =IF(OR(E30="", O30=""), "", IF(LOWER(E30)=LOWER(O30), "OK", "⚠️ Libellé ≠ n°")) -> OK | Q30: =IF(Feuil1!$E30="", "", IF(LOWER(Feuil1!$E30)=LOWER(E30), "Identique", "Différent")) -> Différent | R30: =IF(OR(P30="⚠️ Libellé ≠ n°", O30="Inconnu"), "⚠️", IF(Q30="Différent", "ℹ️", "")) -> ℹ️ | S30: {=_xlfn.LET(_xlpm.genCat,IFERROR(LOWER(TRIM(G30)),""),_xlpm.principal,IFERROR(LOWER(TRIM(H30)),""),_xlpm.orig,IFERROR(LOWER(TRIM(N30)),""),IF(OR(_xlpm.genCat="",_xlpm.principal=""),"",IF(LEFT(LOWER(G30),5)="autre","OK (Autre)",IF(OR(ISNUMBER(SEARCH(_xlpm.genCat,_xlpm.principal)),ISNUMBER(SEARCH(_xlpm.principal,_xlpm.genCat)),AND(_xlpm.orig<>"",OR(ISNUMBER(SEARCH(_xlpm.genCat,_xlpm.orig)),ISNUMBER(SEARCH(_xlpm.orig,_xlpm.genCat))))),"OK","⚠️ À vérifier"))))} -> OK | T30: =IF(S30="","",IF(S30="OK (Autre)","Diagnostic générique = 'Autre – …'",IF(S30="OK","Concordance générique/principal","Écart entre générique et principal"))) -> Concordance générique/principal | U30: {=_xlfn.LET(_xlpm.yr, A30, _xlpm.diag, IF(N30<>"", N30, H30), _xlpm.base, TRIM(SUBSTITUTE(SUBSTITUTE(SUBSTITUTE(SUBSTITUTE(_xlpm.diag,"•"," "),CHAR(160)," "),CHAR(10)," ")," "," ")), LOWER(_xlpm.yr&"|"&_xlpm.base))} -> 2011|ostéoporose | V30: =IFERROR(_xlfn.XLOOKUP($AB30,'Cas 2013-2017'!$K:$K,'Cas 2013-2017'!$D:$D,""),"") | W30: =IFERROR(_xlfn.XLOOKUP($AB30,'Cas 2013-2017'!$K:$K,'Cas 2013-2017'!$E:$E,""),"") | X30: =IFERROR(_xlfn.XLOOKUP($AB30,'Cas 2013-2017'!$K:$K,'Cas 2013-2017'!$F:$F,""),"") | Y30: =IFERROR(_xlfn.XLOOKUP($AB30,'Cas 2013-2017'!$K:$K,'Cas 2013-2017'!$G:$G,""),"") | Z30: =IFERROR(_xlfn.XLOOKUP($AB30,'Cas 2013-2017'!$K:$K,'Cas 2013-2017'!$I:$I,""),"") | AA30: =IFERROR(_xlfn.XLOOKUP($AB30,'Cas 2013-2017'!$K:$K,'Cas 2013-2017'!$H:$H,""),"") | AB30: =LOWER($A30 & "|" & $AF30) -> 2011|ostéoporose | AC30: =TRIM(SUBSTITUTE(SUBSTITUTE(SUBSTITUTE(SUBSTITUTE(" " & LOWER(TRIM(IF($N30<>"", $N30, $H30))) & " ", " aomi ", " arteriopathie des membres inferieurs "), " hta ", " hypertension arterielle "), " saos ", " syndrome d'apnees obstructives du sommeil "), " rgo ", " reflux gastro-oesophagien ") ) -> ostéoporose | AD30: =TRIM(SUBSTITUTE(SUBSTITUTE(SUBSTITUTE(SUBSTITUTE(" " & LOWER(TRIM($AC30)) & " ", " oacr ", " occlusion de l'artere centrale de la retine "), " hsd ", " hematome sous-dural "), " fa ", " fibrillation auriculaire "), " ep ", " embolie pulmonaire ") ) -> ostéoporose | AE30: {=_xlfn.LET(_xlpm.base, " " & LOWER(TRIM($AD30)) & " ", _xlpm.s1, SUBSTITUTE(_xlpm.base, " ic ", " insuffisance cardiaque "), _xlpm.s2, SUBSTITUTE(_xlpm.s1, " avc ", " accident vasculaire cerebral "), _xlpm.s3, SUBSTITUTE(_xlpm.s2, " hsa ", " hemorragie sous-arachnoidienne "), _xlpm.s4, SUBSTITUTE(_xlpm.s3, " htp ", " hypertension pulmonaire "), _xlpm.s5, SUBSTITUTE(_xlpm.s4, " bpco ", " bronchopneumopathie chronique obstructive "), _xlpm.s6, SUBSTITUTE(_xlpm.s5, " dmla ", " degenerescence maculaire liee a l age "), TRIM(_xlpm.s6))} -> ostéoporose | AF30: {=_xlfn.LET(_xlpm.base, " " & LOWER(TRIM($AE30)) & " ", _xlpm.s1, SUBSTITUTE(_xlpm.base, " omi ", " oedemes des membres inferieurs "), _xlpm.s2, SUBSTITUTE(_xlpm.s1, " idm ", " infarctus du myocarde "), _xlpm.s3, SUBSTITUTE(_xlpm.s2, " tvp ", " thrombose veineuse profonde "), _xlpm.s4, SUBSTITUTE(_xlpm.s3, " geu ", " grossesse extra-uterine "), _xlpm.s5, SUBSTITUTE(_xlpm.s4, " fuo ", " fievre d origine indeterminee "), TRIM(_xlpm.s5))} -> ostéoporose
A31: 2011 | B31: 👩‍🦰 Gynéco / Obstétrique / Urologie | D31: 55 | E31: =IF(D31="","",IFERROR(INDEX(SSP!$E$2:$E$266, MATCH(D31, SSP!$F$2:$F$266, 0)),"")) -> Troubles du transit intestinal, incontinence, douleur à la défécation | F31: =Feuil1!E31 -> Incontinence | G31: Incontinence urinaire | H31: Incontinence urinaire d'effort | I31: Cystocèle / Rectocèle | J31: Femme avec incontinence d'effort. | K31: Résultats de l'examen fournis par écrit par l'examinateur. | N31: Incontinence urinaire d'effort | O31: =IFERROR(_xlfn.XLOOKUP($D31, SSP!$F:$F, SSP!$E:$E, "Inconnu"), "") -> Troubles du transit intestinal, incontinence, douleur à la défécation | P31: =IF(OR(E31="", O31=""), "", IF(LOWER(E31)=LOWER(O31), "OK", "⚠️ Libellé ≠ n°")) -> OK | Q31: =IF(Feuil1!$E31="", "", IF(LOWER(Feuil1!$E31)=LOWER(E31), "Identique", "Différent")) -> Différent | R31: =IF(OR(P31="⚠️ Libellé ≠ n°", O31="Inconnu"), "⚠️", IF(Q31="Différent", "ℹ️", "")) -> ℹ️ | S31: {=_xlfn.LET(_xlpm.genCat,IFERROR(LOWER(TRIM(G31)),""),_xlpm.principal,IFERROR(LOWER(TRIM(H31)),""),_xlpm.orig,IFERROR(LOWER(TRIM(N31)),""),IF(OR(_xlpm.genCat="",_xlpm.principal=""),"",IF(LEFT(LOWER(G31),5)="autre","OK (Autre)",IF(OR(ISNUMBER(SEARCH(_xlpm.genCat,_xlpm.principal)),ISNUMBER(SEARCH(_xlpm.principal,_xlpm.genCat)),AND(_xlpm.orig<>"",OR(ISNUMBER(SEARCH(_xlpm.genCat,_xlpm.orig)),ISNUMBER(SEARCH(_xlpm.orig,_xlpm.genCat))))),"OK","⚠️ À vérifier"))))} -> OK | T31: =IF(S31="","",IF(S31="OK (Autre)","Diagnostic générique = 'Autre – …'",IF(S31="OK","Concordance générique/principal","Écart entre générique et principal"))) -> Concordance générique/principal | U31: {=_xlfn.LET(_xlpm.yr, A31, _xlpm.diag, IF(N31<>"", N31, H31), _xlpm.base, TRIM(SUBSTITUTE(SUBSTITUTE(SUBSTITUTE(SUBSTITUTE(_xlpm.diag,"•"," "),CHAR(160)," "),CHAR(10)," ")," "," ")), LOWER(_xlpm.yr&"|"&_xlpm.base))} -> 2011|incontinence urinaire d'effort | V31: =IFERROR(_xlfn.XLOOKUP($AB31,'Cas 2013-2017'!$K:$K,'Cas 2013-2017'!$D:$D,""),"") | W31: =IFERROR(_xlfn.XLOOKUP($AB31,'Cas 2013-2017'!$K:$K,'Cas 2013-2017'!$E:$E,""),"") | X31: =IFERROR(_xlfn.XLOOKUP($AB31,'Cas 2013-2017'!$K:$K,'Cas 2013-2017'!$F:$F,""),"") | Y31: =IFERROR(_xlfn.XLOOKUP($AB31,'Cas 2013-2017'!$K:$K,'Cas 2013-2017'!$G:$G,""),"") | Z31: =IFERROR(_xlfn.XLOOKUP($AB31,'Cas 2013-2017'!$K:$K,'Cas 2013-2017'!$I:$I,""),"") | AA31: =IFERROR(_xlfn.XLOOKUP($AB31,'Cas 2013-2017'!$K:$K,'Cas 2013-2017'!$H:$H,""),"") | AB31: =LOWER($A31 & "|" & $AF31) -> 2011|incontinence urinaire d'effort | AC31: =TRIM(SUBSTITUTE(SUBSTITUTE(SUBSTITUTE(SUBSTITUTE(" " & LOWER(TRIM(IF($N31<>"", $N31, $H31))) & " ", " aomi ", " arteriopathie des membres inferieurs "), " hta ", " hypertension arterielle "), " saos ", " syndrome d'apnees obstructives du sommeil "), " rgo ", " reflux gastro-oesophagien ") ) -> incontinence urinaire d'effort | AD31: =TRIM(SUBSTITUTE(SUBSTITUTE(SUBSTITUTE(SUBSTITUTE(" " & LOWER(TRIM($AC31)) & " ", " oacr ", " occlusion de l'artere centrale de la retine "), " hsd ", " hematome sous-dural "), " fa ", " fibrillation auriculaire "), " ep ", " embolie pulmonaire ") ) -> incontinence urinaire d'effort | AE31: {=_xlfn.LET(_xlpm.base, " " & LOWER(TRIM($AD31)) & " ", _xlpm.s1, SUBSTITUTE(_xlpm.base, " ic ", " insuffisance cardiaque "), _xlpm.s2, SUBSTITUTE(_xlpm.s1, " avc ", " accident vasculaire cerebral "), _xlpm.s3, SUBSTITUTE(_xlpm.s2, " hsa ", " hemorragie sous-arachnoidienne "), _xlpm.s4, SUBSTITUTE(_xlpm.s3, " htp ", " hypertension pulmonaire "), _xlpm.s5, SUBSTITUTE(_xlpm.s4, " bpco ", " bronchopneumopathie chronique obstructive "), _xlpm.s6, SUBSTITUTE(_xlpm.s5, " dmla ", " degenerescence maculaire liee a l age "), TRIM(_xlpm.s6))} -> incontinence urinaire d'effort | AF31: {=_xlfn.LET(_xlpm.base, " " & LOWER(TRIM($AE31)) & " ", _xlpm.s1, SUBSTITUTE(_xlpm.base, " omi ", " oedemes des membres inferieurs "), _xlpm.s2, SUBSTITUTE(_xlpm.s1, " idm ", " infarctus du myocarde "), _xlpm.s3, SUBSTITUTE(_xlpm.s2, " tvp ", " thrombose veineuse profonde "), _xlpm.s4, SUBSTITUTE(_xlpm.s3, " geu ", " grossesse extra-uterine "), _xlpm.s5, SUBSTITUTE(_xlpm.s4, " fuo ", " fievre d origine indeterminee "), TRIM(_xlpm.s5))} -> incontinence urinaire d'effort
A32: 2011 | B32: Autres diagnostics / non classés | D32: 10 | E32: =IF(D32="","",IFERROR(INDEX(SSP!$E$2:$E$266, MATCH(D32, SSP!$F$2:$F$266, 0)),"")) -> Douleur (toutes localisations et types confondus) | F32: =Feuil1!E32 -> Douleur dorsale | G32: Autre – Autre | H32: Néphrolithiase | J32: Femme avec douleur au dos, calculs rénaux à gauche. | N32: Néphrolithiase. | O32: =IFERROR(_xlfn.XLOOKUP($D32, SSP!$F:$F, SSP!$E:$E, "Inconnu"), "") -> Douleur (toutes localisations et types confondus) | P32: =IF(OR(E32="", O32=""), "", IF(LOWER(E32)=LOWER(O32), "OK", "⚠️ Libellé ≠ n°")) -> OK | Q32: =IF(Feuil1!$E32="", "", IF(LOWER(Feuil1!$E32)=LOWER(E32), "Identique", "Différent")) -> Différent | R32: =IF(OR(P32="⚠️ Libellé ≠ n°", O32="Inconnu"), "⚠️", IF(Q32="Différent", "ℹ️", "")) -> ℹ️ | S32: {=_xlfn.LET(_xlpm.genCat,IFERROR(LOWER(TRIM(G32)),""),_xlpm.principal,IFERROR(LOWER(TRIM(H32)),""),_xlpm.orig,IFERROR(LOWER(TRIM(N32)),""),IF(OR(_xlpm.genCat="",_xlpm.principal=""),"",IF(LEFT(LOWER(G32),5)="autre","OK (Autre)",IF(OR(ISNUMBER(SEARCH(_xlpm.genCat,_xlpm.principal)),ISNUMBER(SEARCH(_xlpm.principal,_xlpm.genCat)),AND(_xlpm.orig<>"",OR(ISNUMBER(SEARCH(_xlpm.genCat,_xlpm.orig)),ISNUMBER(SEARCH(_xlpm.orig,_xlpm.genCat))))),"OK","⚠️ À vérifier"))))} -> OK (Autre) | T32: =IF(S32="","",IF(S32="OK (Autre)","Diagnostic générique = 'Autre – …'",IF(S32="OK","Concordance générique/principal","Écart entre générique et principal"))) -> Diagnostic générique = 'Autre – …' | U32: {=_xlfn.LET(_xlpm.yr, A32, _xlpm.diag, IF(N32<>"", N32, H32), _xlpm.base, TRIM(SUBSTITUTE(SUBSTITUTE(SUBSTITUTE(SUBSTITUTE(_xlpm.diag,"•"," "),CHAR(160)," "),CHAR(10)," ")," "," ")), LOWER(_xlpm.yr&"|"&_xlpm.base))} -> 2011|néphrolithiase. | V32: =IFERROR(_xlfn.XLOOKUP($AB32,'Cas 2013-2017'!$K:$K,'Cas 2013-2017'!$D:$D,""),"") | W32: =IFERROR(_xlfn.XLOOKUP($AB32,'Cas 2013-2017'!$K:$K,'Cas 2013-2017'!$E:$E,""),"") | X32: =IFERROR(_xlfn.XLOOKUP($AB32,'Cas 2013-2017'!$K:$K,'Cas 2013-2017'!$F:$F,""),"") | Y32: =IFERROR(_xlfn.XLOOKUP($AB32,'Cas 2013-2017'!$K:$K,'Cas 2013-2017'!$G:$G,""),"") | Z32: =IFERROR(_xlfn.XLOOKUP($AB32,'Cas 2013-2017'!$K:$K,'Cas 2013-2017'!$I:$I,""),"") | AA32: =IFERROR(_xlfn.XLOOKUP($AB32,'Cas 2013-2017'!$K:$K,'Cas 2013-2017'!$H:$H,""),"") | AB32: =LOWER($A32 & "|" & $AF32) -> 2011|néphrolithiase. | AC32: =TRIM(SUBSTITUTE(SUBSTITUTE(SUBSTITUTE(SUBSTITUTE(" " & LOWER(TRIM(IF($N32<>"", $N32, $H32))) & " ", " aomi ", " arteriopathie des membres inferieurs "), " hta ", " hypertension arterielle "), " saos ", " syndrome d'apnees obstructives du sommeil "), " rgo ", " reflux gastro-oesophagien ") ) -> néphrolithiase. | AD32: =TRIM(SUBSTITUTE(SUBSTITUTE(SUBSTITUTE(SUBSTITUTE(" " & LOWER(TRIM($AC32)) & " ", " oacr ", " occlusion de l'artere centrale de la retine "), " hsd ", " hematome sous-dural "), " fa ", " fibrillation auriculaire "), " ep ", " embolie pulmonaire ") ) -> néphrolithiase. | AE32: {=_xlfn.LET(_xlpm.base, " " & LOWER(TRIM($AD32)) & " ", _xlpm.s1, SUBSTITUTE(_xlpm.base, " ic ", " insuffisance cardiaque "), _xlpm.s2, SUBSTITUTE(_xlpm.s1, " avc ", " accident vasculaire cerebral "), _xlpm.s3, SUBSTITUTE(_xlpm.s2, " hsa ", " hemorragie sous-arachnoidienne "), _xlpm.s4, SUBSTITUTE(_xlpm.s3, " htp ", " hypertension pulmonaire "), _xlpm.s5, SUBSTITUTE(_xlpm.s4, " bpco ", " bronchopneumopathie chronique obstructive "), _xlpm.s6, SUBSTITUTE(_xlpm.s5, " dmla ", " degenerescence maculaire liee a l age "), TRIM(_xlpm.s6))} -> néphrolithiase. | AF32: {=_xlfn.LET(_xlpm.base, " " & LOWER(TRIM($AE32)) & " ", _xlpm.s1, SUBSTITUTE(_xlpm.base, " omi ", " oedemes des membres inferieurs "), _xlpm.s2, SUBSTITUTE(_xlpm.s1, " idm ", " infarctus du myocarde "), _xlpm.s3, SUBSTITUTE(_xlpm.s2, " tvp ", " thrombose veineuse profonde "), _xlpm.s4, SUBSTITUTE(_xlpm.s3, " geu ", " grossesse extra-uterine "), _xlpm.s5, SUBSTITUTE(_xlpm.s4, " fuo ", " fievre d origine indeterminee "), TRIM(_xlpm.s5))} -> néphrolithiase.
A33: 2011 | B33: 🧬 Maladies infectieuses | D33: 47 | E33: =IF(D33="","",IFERROR(INDEX(SSP!$E$2:$E$266, MATCH(D33, SSP!$F$2:$F$266, 0)),"")) -> Pyrosis (brûlures rétrosternales) | F33: =Feuil1!E33 -> Brûlures mictionnelles | G33: Autre – Maladies infectieuses | H33: Prostatite | J33: Homme de 40 ans avec brûlure pendant la miction (algurie). | N33: Prostatite | O33: =IFERROR(_xlfn.XLOOKUP($D33, SSP!$F:$F, SSP!$E:$E, "Inconnu"), "") -> Pyrosis (brûlures rétrosternales) | P33: =IF(OR(E33="", O33=""), "", IF(LOWER(E33)=LOWER(O33), "OK", "⚠️ Libellé ≠ n°")) -> OK | Q33: =IF(Feuil1!$E33="", "", IF(LOWER(Feuil1!$E33)=LOWER(E33), "Identique", "Différent")) -> Différent | R33: =IF(OR(P33="⚠️ Libellé ≠ n°", O33="Inconnu"), "⚠️", IF(Q33="Différent", "ℹ️", "")) -> ℹ️ | S33: {=_xlfn.LET(_xlpm.genCat,IFERROR(LOWER(TRIM(G33)),""),_xlpm.principal,IFERROR(LOWER(TRIM(H33)),""),_xlpm.orig,IFERROR(LOWER(TRIM(N33)),""),IF(OR(_xlpm.genCat="",_xlpm.principal=""),"",IF(LEFT(LOWER(G33),5)="autre","OK (Autre)",IF(OR(ISNUMBER(SEARCH(_xlpm.genCat,_xlpm.principal)),ISNUMBER(SEARCH(_xlpm.principal,_xlpm.genCat)),AND(_xlpm.orig<>"",OR(ISNUMBER(SEARCH(_xlpm.genCat,_xlpm.orig)),ISNUMBER(SEARCH(_xlpm.orig,_xlpm.genCat))))),"OK","⚠️ À vérifier"))))} -> OK (Autre) | T33: =IF(S33="","",IF(S33="OK (Autre)","Diagnostic générique = 'Autre – …'",IF(S33="OK","Concordance générique/principal","Écart entre générique et principal"))) -> Diagnostic générique = 'Autre – …' | U33: {=_xlfn.LET(_xlpm.yr, A33, _xlpm.diag, IF(N33<>"", N33, H33), _xlpm.base, TRIM(SUBSTITUTE(SUBSTITUTE(SUBSTITUTE(SUBSTITUTE(_xlpm.diag,"•"," "),CHAR(160)," "),CHAR(10)," ")," "," ")), LOWER(_xlpm.yr&"|"&_xlpm.base))} -> 2011|prostatite | V33: =IFERROR(_xlfn.XLOOKUP($AB33,'Cas 2013-2017'!$K:$K,'Cas 2013-2017'!$D:$D,""),"") | W33: =IFERROR(_xlfn.XLOOKUP($AB33,'Cas 2013-2017'!$K:$K,'Cas 2013-2017'!$E:$E,""),"") | X33: =IFERROR(_xlfn.XLOOKUP($AB33,'Cas 2013-2017'!$K:$K,'Cas 2013-2017'!$F:$F,""),"") | Y33: =IFERROR(_xlfn.XLOOKUP($AB33,'Cas 2013-2017'!$K:$K,'Cas 2013-2017'!$G:$G,""),"") | Z33: =IFERROR(_xlfn.XLOOKUP($AB33,'Cas 2013-2017'!$K:$K,'Cas 2013-2017'!$I:$I,""),"") | AA33: =IFERROR(_xlfn.XLOOKUP($AB33,'Cas 2013-2017'!$K:$K,'Cas 2013-2017'!$H:$H,""),"") | AB33: =LOWER($A33 & "|" & $AF33) -> 2011|prostatite | AC33: =TRIM(SUBSTITUTE(SUBSTITUTE(SUBSTITUTE(SUBSTITUTE(" " & LOWER(TRIM(IF($N33<>"", $N33, $H33))) & " ", " aomi ", " arteriopathie des membres inferieurs "), " hta ", " hypertension arterielle "), " saos ", " syndrome d'apnees obstructives du sommeil "), " rgo ", " reflux gastro-oesophagien ") ) -> prostatite | AD33: =TRIM(SUBSTITUTE(SUBSTITUTE(SUBSTITUTE(SUBSTITUTE(" " & LOWER(TRIM($AC33)) & " ", " oacr ", " occlusion de l'artere centrale de la retine "), " hsd ", " hematome sous-dural "), " fa ", " fibrillation auriculaire "), " ep ", " embolie pulmonaire ") ) -> prostatite | AE33: {=_xlfn.LET(_xlpm.base, " " & LOWER(TRIM($AD33)) & " ", _xlpm.s1, SUBSTITUTE(_xlpm.base, " ic ", " insuffisance cardiaque "), _xlpm.s2, SUBSTITUTE(_xlpm.s1, " avc ", " accident vasculaire cerebral "), _xlpm.s3, SUBSTITUTE(_xlpm.s2, " hsa ", " hemorragie sous-arachnoidienne "), _xlpm.s4, SUBSTITUTE(_xlpm.s3, " htp ", " hypertension pulmonaire "), _xlpm.s5, SUBSTITUTE(_xlpm.s4, " bpco ", " bronchopneumopathie chronique obstructive "), _xlpm.s6, SUBSTITUTE(_xlpm.s5, " dmla ", " degenerescence maculaire liee a l age "), TRIM(_xlpm.s6))} -> prostatite | AF33: {=_xlfn.LET(_xlpm.base, " " & LOWER(TRIM($AE33)) & " ", _xlpm.s1, SUBSTITUTE(_xlpm.base, " omi ", " oedemes des membres inferieurs "), _xlpm.s2, SUBSTITUTE(_xlpm.s1, " idm ", " infarctus du myocarde "), _xlpm.s3, SUBSTITUTE(_xlpm.s2, " tvp ", " thrombose veineuse profonde "), _xlpm.s4, SUBSTITUTE(_xlpm.s3, " geu ", " grossesse extra-uterine "), _xlpm.s5, SUBSTITUTE(_xlpm.s4, " fuo ", " fievre d origine indeterminee "), TRIM(_xlpm.s5))} -> prostatite
A34: 2013 | B34: ❤️ Cardiologie / Vasculaire | D34: 85 | E34: =IF(D34="","",IFERROR(INDEX(SSP!$E$2:$E$266, MATCH(D34, SSP!$F$2:$F$266, 0)),"")) -> Douleur, sensation de brûlure, crampes ou engourdissement des extrémités | F34: =Feuil1!E34 -> Engourdissement / faiblesse musculaire | G34: Artériopathie des membres inférieurs | H34: AOMI | J34: Souffle iliaque. | N34: AOMI | O34: =IFERROR(_xlfn.XLOOKUP($D34, SSP!$F:$F, SSP!$E:$E, "Inconnu"), "") -> Douleur, sensation de brûlure, crampes ou engourdissement des extrémités | P34: =IF(OR(E34="", O34=""), "", IF(LOWER(E34)=LOWER(O34), "OK", "⚠️ Libellé ≠ n°")) -> OK | Q34: =IF(Feuil1!$E34="", "", IF(LOWER(Feuil1!$E34)=LOWER(E34), "Identique", "Différent")) -> Différent | R34: =IF(OR(P34="⚠️ Libellé ≠ n°", O34="Inconnu"), "⚠️", IF(Q34="Différent", "ℹ️", "")) -> ℹ️ | S34: {=_xlfn.LET(_xlpm.genCat,IFERROR(LOWER(TRIM(G34)),""),_xlpm.principal,IFERROR(LOWER(TRIM(H34)),""),_xlpm.orig,IFERROR(LOWER(TRIM(N34)),""),IF(OR(_xlpm.genCat="",_xlpm.principal=""),"",IF(LEFT(LOWER(G34),5)="autre","OK (Autre)",IF(OR(ISNUMBER(SEARCH(_xlpm.genCat,_xlpm.principal)),ISNUMBER(SEARCH(_xlpm.principal,_xlpm.genCat)),AND(_xlpm.orig<>"",OR(ISNUMBER(SEARCH(_xlpm.genCat,_xlpm.orig)),ISNUMBER(SEARCH(_xlpm.orig,_xlpm.genCat))))),"OK","⚠️ À vérifier"))))} -> ⚠️ À vérifier | T34: =IF(S34="","",IF(S34="OK (Autre)","Diagnostic générique = 'Autre – …'",IF(S34="OK","Concordance générique/principal","Écart entre générique et principal"))) -> Écart entre générique et principal | U34: {=_xlfn.LET(_xlpm.yr, A34, _xlpm.diag, IF(N34<>"", N34, H34), _xlpm.base, TRIM(SUBSTITUTE(SUBSTITUTE(SUBSTITUTE(SUBSTITUTE(_xlpm.diag,"•"," "),CHAR(160)," "),CHAR(10)," ")," "," ")), LOWER(_xlpm.yr&"|"&_xlpm.base))} -> 2013|aomi | V34: =IFERROR(_xlfn.XLOOKUP($AB34,'Cas 2013-2017'!$K:$K,'Cas 2013-2017'!$D:$D,""),"") | W34: =IFERROR(_xlfn.XLOOKUP($AB34,'Cas 2013-2017'!$K:$K,'Cas 2013-2017'!$E:$E,""),"") | X34: =IFERROR(_xlfn.XLOOKUP($AB34,'Cas 2013-2017'!$K:$K,'Cas 2013-2017'!$F:$F,""),"") | Y34: =IFERROR(_xlfn.XLOOKUP($AB34,'Cas 2013-2017'!$K:$K,'Cas 2013-2017'!$G:$G,""),"") | Z34: =IFERROR(_xlfn.XLOOKUP($AB34,'Cas 2013-2017'!$K:$K,'Cas 2013-2017'!$I:$I,""),"") | AA34: =IFERROR(_xlfn.XLOOKUP($AB34,'Cas 2013-2017'!$K:$K,'Cas 2013-2017'!$H:$H,""),"") | AB34: =LOWER($A34 & "|" & $AF34) -> 2013|arteriopathie des membres inferieurs | AC34: =TRIM(SUBSTITUTE(SUBSTITUTE(SUBSTITUTE(SUBSTITUTE(" " & LOWER(TRIM(IF($N34<>"", $N34, $H34))) & " ", " aomi ", " arteriopathie des membres inferieurs "), " hta ", " hypertension arterielle "), " saos ", " syndrome d'apnees obstructives du sommeil "), " rgo ", " reflux gastro-oesophagien ") ) -> arteriopathie des membres inferieurs | AD34: =TRIM(SUBSTITUTE(SUBSTITUTE(SUBSTITUTE(SUBSTITUTE(" " & LOWER(TRIM($AC34)) & " ", " oacr ", " occlusion de l'artere centrale de la retine "), " hsd ", " hematome sous-dural "), " fa ", " fibrillation auriculaire "), " ep ", " embolie pulmonaire ") ) -> arteriopathie des membres inferieurs | AE34: {=_xlfn.LET(_xlpm.base, " " & LOWER(TRIM($AD34)) & " ", _xlpm.s1, SUBSTITUTE(_xlpm.base, " ic ", " insuffisance cardiaque "), _xlpm.s2, SUBSTITUTE(_xlpm.s1, " avc ", " accident vasculaire cerebral "), _xlpm.s3, SUBSTITUTE(_xlpm.s2, " hsa ", " hemorragie sous-arachnoidienne "), _xlpm.s4, SUBSTITUTE(_xlpm.s3, " htp ", " hypertension pulmonaire "), _xlpm.s5, SUBSTITUTE(_xlpm.s4, " bpco ", " bronchopneumopathie chronique obstructive "), _xlpm.s6, SUBSTITUTE(_xlpm.s5, " dmla ", " degenerescence maculaire liee a l age "), TRIM(_xlpm.s6))} -> arteriopathie des membres inferieurs | AF34: {=_xlfn.LET(_xlpm.base, " " & LOWER(TRIM($AE34)) & " ", _xlpm.s1, SUBSTITUTE(_xlpm.base, " omi ", " oedemes des membres inferieurs "), _xlpm.s2, SUBSTITUTE(_xlpm.s1, " idm ", " infarctus du myocarde "), _xlpm.s3, SUBSTITUTE(_xlpm.s2, " tvp ", " thrombose veineuse profonde "), _xlpm.s4, SUBSTITUTE(_xlpm.s3, " geu ", " grossesse extra-uterine "), _xlpm.s5, SUBSTITUTE(_xlpm.s4, " fuo ", " fievre d origine indeterminee "), TRIM(_xlpm.s5))} -> arteriopathie des membres inferieurs
A35: 2013 | B35: ❤️ Cardiologie / Vasculaire | D35: 6 | E35: =IF(D35="","",IFERROR(INDEX(SSP!$E$2:$E$266, MATCH(D35, SSP!$F$2:$F$266, 0)),"")) -> Fièvre, frissons, hyperthermie | F35: =Feuil1!E35 -> Fièvre | G35: Autre – ️ Cardiologie / Vasculaire | H35: Endocardite | J35: - | N35: Endocardite | O35: =IFERROR(_xlfn.XLOOKUP($D35, SSP!$F:$F, SSP!$E:$E, "Inconnu"), "") -> Fièvre, frissons, hyperthermie | P35: =IF(OR(E35="", O35=""), "", IF(LOWER(E35)=LOWER(O35), "OK", "⚠️ Libellé ≠ n°")) -> OK | Q35: =IF(Feuil1!$E35="", "", IF(LOWER(Feuil1!$E35)=LOWER(E35), "Identique", "Différent")) -> Différent | R35: =IF(OR(P35="⚠️ Libellé ≠ n°", O35="Inconnu"), "⚠️", IF(Q35="Différent", "ℹ️", "")) -> ℹ️ | S35: {=_xlfn.LET(_xlpm.genCat,IFERROR(LOWER(TRIM(G35)),""),_xlpm.principal,IFERROR(LOWER(TRIM(H35)),""),_xlpm.orig,IFERROR(LOWER(TRIM(N35)),""),IF(OR(_xlpm.genCat="",_xlpm.principal=""),"",IF(LEFT(LOWER(G35),5)="autre","OK (Autre)",IF(OR(ISNUMBER(SEARCH(_xlpm.genCat,_xlpm.principal)),ISNUMBER(SEARCH(_xlpm.principal,_xlpm.genCat)),AND(_xlpm.orig<>"",OR(ISNUMBER(SEARCH(_xlpm.genCat,_xlpm.orig)),ISNUMBER(SEARCH(_xlpm.orig,_xlpm.genCat))))),"OK","⚠️ À vérifier"))))} -> OK (Autre) | T35: =IF(S35="","",IF(S35="OK (Autre)","Diagnostic générique = 'Autre – …'",IF(S35="OK","Concordance générique/principal","Écart entre générique et principal"))) -> Diagnostic générique = 'Autre – …' | U35: {=_xlfn.LET(_xlpm.yr, A35, _xlpm.diag, IF(N35<>"", N35, H35), _xlpm.base, TRIM(SUBSTITUTE(SUBSTITUTE(SUBSTITUTE(SUBSTITUTE(_xlpm.diag,"•"," "),CHAR(160)," "),CHAR(10)," ")," "," ")), LOWER(_xlpm.yr&"|"&_xlpm.base))} -> 2013|endocardite | V35: =IFERROR(_xlfn.XLOOKUP($AB35,'Cas 2013-2017'!$K:$K,'Cas 2013-2017'!$D:$D,""),"") -> 0 | W35: =IFERROR(_xlfn.XLOOKUP($AB35,'Cas 2013-2017'!$K:$K,'Cas 2013-2017'!$E:$E,""),"") -> 0 | X35: =IFERROR(_xlfn.XLOOKUP($AB35,'Cas 2013-2017'!$K:$K,'Cas 2013-2017'!$F:$F,""),"") -> 0 | Y35: =IFERROR(_xlfn.XLOOKUP($AB35,'Cas 2013-2017'!$K:$K,'Cas 2013-2017'!$G:$G,""),"") -> 0 | Z35: =IFERROR(_xlfn.XLOOKUP($AB35,'Cas 2013-2017'!$K:$K,'Cas 2013-2017'!$I:$I,""),"") -> 0 | AA35: =IFERROR(_xlfn.XLOOKUP($AB35,'Cas 2013-2017'!$K:$K,'Cas 2013-2017'!$H:$H,""),"") -> Hemocs + TTE/TEE | AB35: =LOWER($A35 & "|" & $AF35) -> 2013|endocardite | AC35: =TRIM(SUBSTITUTE(SUBSTITUTE(SUBSTITUTE(SUBSTITUTE(" " & LOWER(TRIM(IF($N35<>"", $N35, $H35))) & " ", " aomi ", " arteriopathie des membres inferieurs "), " hta ", " hypertension arterielle "), " saos ", " syndrome d'apnees obstructives du sommeil "), " rgo ", " reflux gastro-oesophagien ") ) -> endocardite | AD35: =TRIM(SUBSTITUTE(SUBSTITUTE(SUBSTITUTE(SUBSTITUTE(" " & LOWER(TRIM($AC35)) & " ", " oacr ", " occlusion de l'artere centrale de la retine "), " hsd ", " hematome sous-dural "), " fa ", " fibrillation auriculaire "), " ep ", " embolie pulmonaire ") ) -> endocardite | AE35: {=_xlfn.LET(_xlpm.base, " " & LOWER(TRIM($AD35)) & " ", _xlpm.s1, SUBSTITUTE(_xlpm.base, " ic ", " insuffisance cardiaque "), _xlpm.s2, SUBSTITUTE(_xlpm.s1, " avc ", " accident vasculaire cerebral "), _xlpm.s3, SUBSTITUTE(_xlpm.s2, " hsa ", " hemorragie sous-arachnoidienne "), _xlpm.s4, SUBSTITUTE(_xlpm.s3, " htp ", " hypertension pulmonaire "), _xlpm.s5, SUBSTITUTE(_xlpm.s4, " bpco ", " bronchopneumopathie chronique obstructive "), _xlpm.s6, SUBSTITUTE(_xlpm.s5, " dmla ", " degenerescence maculaire liee a l age "), TRIM(_xlpm.s6))} -> endocardite | AF35: {=_xlfn.LET(_xlpm.base, " " & LOWER(TRIM($AE35)) & " ", _xlpm.s1, SUBSTITUTE(_xlpm.base, " omi ", " oedemes des membres inferieurs "), _xlpm.s2, SUBSTITUTE(_xlpm.s1, " idm ", " infarctus du myocarde "), _xlpm.s3, SUBSTITUTE(_xlpm.s2, " tvp ", " thrombose veineuse profonde "), _xlpm.s4, SUBSTITUTE(_xlpm.s3, " geu ", " grossesse extra-uterine "), _xlpm.s5, SUBSTITUTE(_xlpm.s4, " fuo ", " fievre d origine indeterminee "), TRIM(_xlpm.s5))} -> endocardite
A36: 2013 | B36: ❤️ Cardiologie / Vasculaire | D36: 5 | E36: =IF(D36="","",IFERROR(INDEX(SSP!$E$2:$E$266, MATCH(D36, SSP!$F$2:$F$266, 0)),"")) -> Sensation de malaise, altération de l’état général | F36: =Feuil1!E36 -> Malaise | G36: Syndrome coronarien aigu | H36: Infarctus du myocarde | J36: Petite vieille amenée aux urgences en ambulance, retrouvée par son mari par terre chez elle, vertige en se levant. | K36: Prend amlodipine et ramipril. ECG, mise sous ETT et ETO pour vérifier si cause des médicaments ou autre problème cardiaque. Sous-décalage ST, QRS large et T inversées, FC à 40. | N36: Infarctus du myocarde | O36: =IFERROR(_xlfn.XLOOKUP($D36, SSP!$F:$F, SSP!$E:$E, "Inconnu"), "") -> Sensation de malaise, altération de l’état général | P36: =IF(OR(E36="", O36=""), "", IF(LOWER(E36)=LOWER(O36), "OK", "⚠️ Libellé ≠ n°")) -> OK | Q36: =IF(Feuil1!$E36="", "", IF(LOWER(Feuil1!$E36)=LOWER(E36), "Identique", "Différent")) -> Différent | R36: =IF(OR(P36="⚠️ Libellé ≠ n°", O36="Inconnu"), "⚠️", IF(Q36="Différent", "ℹ️", "")) -> ℹ️ | S36: {=_xlfn.LET(_xlpm.genCat,IFERROR(LOWER(TRIM(G36)),""),_xlpm.principal,IFERROR(LOWER(TRIM(H36)),""),_xlpm.orig,IFERROR(LOWER(TRIM(N36)),""),IF(OR(_xlpm.genCat="",_xlpm.principal=""),"",IF(LEFT(LOWER(G36),5)="autre","OK (Autre)",IF(OR(ISNUMBER(SEARCH(_xlpm.genCat,_xlpm.principal)),ISNUMBER(SEARCH(_xlpm.principal,_xlpm.genCat)),AND(_xlpm.orig<>"",OR(ISNUMBER(SEARCH(_xlpm.genCat,_xlpm.orig)),ISNUMBER(SEARCH(_xlpm.orig,_xlpm.genCat))))),"OK","⚠️ À vérifier"))))} -> ⚠️ À vérifier | T36: =IF(S36="","",IF(S36="OK (Autre)","Diagnostic générique = 'Autre – …'",IF(S36="OK","Concordance générique/principal","Écart entre générique et principal"))) -> Écart entre générique et principal | U36: {=_xlfn.LET(_xlpm.yr, A36, _xlpm.diag, IF(N36<>"", N36, H36), _xlpm.base, TRIM(SUBSTITUTE(SUBSTITUTE(SUBSTITUTE(SUBSTITUTE(_xlpm.diag,"•"," "),CHAR(160)," "),CHAR(10)," ")," "," ")), LOWER(_xlpm.yr&"|"&_xlpm.base))} -> 2013|infarctus du myocarde | V36: =IFERROR(_xlfn.XLOOKUP($AB36,'Cas 2013-2017'!$K:$K,'Cas 2013-2017'!$D:$D,""),"") | W36: =IFERROR(_xlfn.XLOOKUP($AB36,'Cas 2013-2017'!$K:$K,'Cas 2013-2017'!$E:$E,""),"") | X36: =IFERROR(_xlfn.XLOOKUP($AB36,'Cas 2013-2017'!$K:$K,'Cas 2013-2017'!$F:$F,""),"") | Y36: =IFERROR(_xlfn.XLOOKUP($AB36,'Cas 2013-2017'!$K:$K,'Cas 2013-2017'!$G:$G,""),"") | Z36: =IFERROR(_xlfn.XLOOKUP($AB36,'Cas 2013-2017'!$K:$K,'Cas 2013-2017'!$I:$I,""),"") | AA36: =IFERROR(_xlfn.XLOOKUP($AB36,'Cas 2013-2017'!$K:$K,'Cas 2013-2017'!$H:$H,""),"") | AB36: =LOWER($A36 & "|" & $AF36) -> 2013|infarctus du myocarde | AC36: =TRIM(SUBSTITUTE(SUBSTITUTE(SUBSTITUTE(SUBSTITUTE(" " & LOWER(TRIM(IF($N36<>"", $N36, $H36))) & " ", " aomi ", " arteriopathie des membres inferieurs "), " hta ", " hypertension arterielle "), " saos ", " syndrome d'apnees obstructives du sommeil "), " rgo ", " reflux gastro-oesophagien ") ) -> infarctus du myocarde | AD36: =TRIM(SUBSTITUTE(SUBSTITUTE(SUBSTITUTE(SUBSTITUTE(" " & LOWER(TRIM($AC36)) & " ", " oacr ", " occlusion de l'artere centrale de la retine "), " hsd ", " hematome sous-dural "), " fa ", " fibrillation auriculaire "), " ep ", " embolie pulmonaire ") ) -> infarctus du myocarde | AE36: {=_xlfn.LET(_xlpm.base, " " & LOWER(TRIM($AD36)) & " ", _xlpm.s1, SUBSTITUTE(_xlpm.base, " ic ", " insuffisance cardiaque "), _xlpm.s2, SUBSTITUTE(_xlpm.s1, " avc ", " accident vasculaire cerebral "), _xlpm.s3, SUBSTITUTE(_xlpm.s2, " hsa ", " hemorragie sous-arachnoidienne "), _xlpm.s4, SUBSTITUTE(_xlpm.s3, " htp ", " hypertension pulmonaire "), _xlpm.s5, SUBSTITUTE(_xlpm.s4, " bpco ", " bronchopneumopathie chronique obstructive "), _xlpm.s6, SUBSTITUTE(_xlpm.s5, " dmla ", " degenerescence maculaire liee a l age "), TRIM(_xlpm.s6))} -> infarctus du myocarde | AF36: {=_xlfn.LET(_xlpm.base, " " & LOWER(TRIM($AE36)) & " ", _xlpm.s1, SUBSTITUTE(_xlpm.base, " omi ", " oedemes des membres inferieurs "), _xlpm.s2, SUBSTITUTE(_xlpm.s1, " idm ", " infarctus du myocarde "), _xlpm.s3, SUBSTITUTE(_xlpm.s2, " tvp ", " thrombose veineuse profonde "), _xlpm.s4, SUBSTITUTE(_xlpm.s3, " geu ", " grossesse extra-uterine "), _xlpm.s5, SUBSTITUTE(_xlpm.s4, " fuo ", " fievre d origine indeterminee "), TRIM(_xlpm.s5))} -> infarctus du myocarde
A37: 2013 | B37: ❤️ Cardiologie / Vasculaire | D37: 4 | E37: =IF(D37="","",IFERROR(INDEX(SSP!$E$2:$E$266, MATCH(D37, SSP!$F$2:$F$266, 0)),"")) -> Fatigue, asthénie | F37: =Feuil1!E37 -> Fatigue | G37: Insuffisance cardiaque | H37: Insuffisance cardiaque | I37: EP • Insuffisance rénale • Insuffisance hépatique | J37: Femme de 60 ans avec fatigue, arythmie, œdème avec godet, dyspnée max. | K37: Insuffisance cardiaque, état non complètement évalué. | L37: CV (ne pas oublier reflux hépatojugulaire, oedèmes!, auscultation carotides) • Homans • Palpation mollets Pulmonaire | M37: Hospitalisation si décompensation→ O2, position assise, Morphine, Nitroglycérinesi oedème poumon et pas d’hypotension, furosémide iv. Si stable chgt habitudes de vie (diète pauvre en sel, réduction poids, restriction hydrique,diminuer OH et nicotine) Médics: IECA, Bbloquant, Diurétique, evt antago aldostérone | N37: Insuffisance cardiaque | O37: =IFERROR(_xlfn.XLOOKUP($D37, SSP!$F:$F, SSP!$E:$E, "Inconnu"), "") -> Fatigue, asthénie | P37: =IF(OR(E37="", O37=""), "", IF(LOWER(E37)=LOWER(O37), "OK", "⚠️ Libellé ≠ n°")) -> OK | Q37: =IF(Feuil1!$E37="", "", IF(LOWER(Feuil1!$E37)=LOWER(E37), "Identique", "Différent")) -> Différent | R37: =IF(OR(P37="⚠️ Libellé ≠ n°", O37="Inconnu"), "⚠️", IF(Q37="Différent", "ℹ️", "")) -> ℹ️ | S37: {=_xlfn.LET(_xlpm.genCat,IFERROR(LOWER(TRIM(G37)),""),_xlpm.principal,IFERROR(LOWER(TRIM(H37)),""),_xlpm.orig,IFERROR(LOWER(TRIM(N37)),""),IF(OR(_xlpm.genCat="",_xlpm.principal=""),"",IF(LEFT(LOWER(G37),5)="autre","OK (Autre)",IF(OR(ISNUMBER(SEARCH(_xlpm.genCat,_xlpm.principal)),ISNUMBER(SEARCH(_xlpm.principal,_xlpm.genCat)),AND(_xlpm.orig<>"",OR(ISNUMBER(SEARCH(_xlpm.genCat,_xlpm.orig)),ISNUMBER(SEARCH(_xlpm.orig,_xlpm.genCat))))),"OK","⚠️ À vérifier"))))} -> OK | T37: =IF(S37="","",IF(S37="OK (Autre)","Diagnostic générique = 'Autre – …'",IF(S37="OK","Concordance générique/principal","Écart entre générique et principal"))) -> Concordance générique/principal | U37: {=_xlfn.LET(_xlpm.yr, A37, _xlpm.diag, IF(N37<>"", N37, H37), _xlpm.base, TRIM(SUBSTITUTE(SUBSTITUTE(SUBSTITUTE(SUBSTITUTE(_xlpm.diag,"•"," "),CHAR(160)," "),CHAR(10)," ")," "," ")), LOWER(_xlpm.yr&"|"&_xlpm.base))} -> 2013|insuffisance cardiaque | V37: =IFERROR(_xlfn.XLOOKUP($AB37,'Cas 2013-2017'!$K:$K,'Cas 2013-2017'!$D:$D,""),"") -> femme avec fatigue, arythmie, oedème prenant le godet, dyspnée | W37: =IFERROR(_xlfn.XLOOKUP($AB37,'Cas 2013-2017'!$K:$K,'Cas 2013-2017'!$E:$E,""),"") -> dyspnée nouvelle ? progression ? facteur aggravant soulageant ? angor ? orthopnée ? dyspnée paroxystique nocturne? Prise de poids? oedème ? quand ? Nycturie ? fatigue ? FRCV tabac-OH • Voyage, néoplasie, op, varices, COC, ATCD de MTE, oedème, douleur, AF... | X37: =IFERROR(_xlfn.XLOOKUP($AB37,'Cas 2013-2017'!$K:$K,'Cas 2013-2017'!$F:$F,""),"") -> CV (ne pas oublier reflux hépatojugulaire, oedèmes!, auscultation carotides) • Homans • Palpation mollets Pulmonaire | Y37: =IFERROR(_xlfn.XLOOKUP($AB37,'Cas 2013-2017'!$K:$K,'Cas 2013-2017'!$G:$G,""),"") -> EP • Insuffisance rénale • Insuffisance hépatique | Z37: =IFERROR(_xlfn.XLOOKUP($AB37,'Cas 2013-2017'!$K:$K,'Cas 2013-2017'!$I:$I,""),"") -> Hospitalisation si décompensation→ O2, position assise, Morphine, Nitroglycérinesi oedème poumon et pas d’hypotension, furosémide iv. Si stable chgt habitudes de vie (diète pauvre en sel, réduction poids, restriction hydrique,diminuer OH et nicotine) Médics: IECA, Bbloquant, Diurétique, evt antago aldostérone | AA37: =IFERROR(_xlfn.XLOOKUP($AB37,'Cas 2013-2017'!$K:$K,'Cas 2013-2017'!$H:$H,""),"") -> ECG • Gazométrie • Sat02% • FSS, BNP, pro-BNP • US cardio • Rx thorax (cardiomégalie, gros VG, congestion pulmonaire voir œdème pulmo) | AB37: =LOWER($A37 & "|" & $AF37) -> 2013|insuffisance cardiaque | AC37: =TRIM(SUBSTITUTE(SUBSTITUTE(SUBSTITUTE(SUBSTITUTE(" " & LOWER(TRIM(IF($N37<>"", $N37, $H37))) & " ", " aomi ", " arteriopathie des membres inferieurs "), " hta ", " hypertension arterielle "), " saos ", " syndrome d'apnees obstructives du sommeil "), " rgo ", " reflux gastro-oesophagien ") ) -> insuffisance cardiaque | AD37: =TRIM(SUBSTITUTE(SUBSTITUTE(SUBSTITUTE(SUBSTITUTE(" " & LOWER(TRIM($AC37)) & " ", " oacr ", " occlusion de l'artere centrale de la retine "), " hsd ", " hematome sous-dural "), " fa ", " fibrillation auriculaire "), " ep ", " embolie pulmonaire ") ) -> insuffisance cardiaque | AE37: {=_xlfn.LET(_xlpm.base, " " & LOWER(TRIM($AD37)) & " ", _xlpm.s1, SUBSTITUTE(_xlpm.base, " ic ", " insuffisance cardiaque "), _xlpm.s2, SUBSTITUTE(_xlpm.s1, " avc ", " accident vasculaire cerebral "), _xlpm.s3, SUBSTITUTE(_xlpm.s2, " hsa ", " hemorragie sous-arachnoidienne "), _xlpm.s4, SUBSTITUTE(_xlpm.s3, " htp ", " hypertension pulmonaire "), _xlpm.s5, SUBSTITUTE(_xlpm.s4, " bpco ", " bronchopneumopathie chronique obstructive "), _xlpm.s6, SUBSTITUTE(_xlpm.s5, " dmla ", " degenerescence maculaire liee a l age "), TRIM(_xlpm.s6))} -> insuffisance cardiaque | AF37: {=_xlfn.LET(_xlpm.base, " " & LOWER(TRIM($AE37)) & " ", _xlpm.s1, SUBSTITUTE(_xlpm.base, " omi ", " oedemes des membres inferieurs "), _xlpm.s2, SUBSTITUTE(_xlpm.s1, " idm ", " infarctus du myocarde "), _xlpm.s3, SUBSTITUTE(_xlpm.s2, " tvp ", " thrombose veineuse profonde "), _xlpm.s4, SUBSTITUTE(_xlpm.s3, " geu ", " grossesse extra-uterine "), _xlpm.s5, SUBSTITUTE(_xlpm.s4, " fuo ", " fievre d origine indeterminee "), TRIM(_xlpm.s5))} -> insuffisance cardiaque
A38: 2013 | B38: 🧴 Dermatologie | D38: 10 | E38: =IF(D38="","",IFERROR(INDEX(SSP!$E$2:$E$266, MATCH(D38, SSP!$F$2:$F$266, 0)),"")) -> Douleur (toutes localisations et types confondus) | F38: =Feuil1!E38 -> Douleur jambe | G38: Infection cutanée bactérienne | H38: Dermohypodermite | I38: Eczéma de contact allergique aigu • Thrombophlébite • Acrodermatite chronique atrophiante • Fasciite nécrosante | J38: Douleur + rougeur à la jambe, fièvre, œdème et ADP fémorales | K38: Douleur et rougeur à la jambe avec œdème et fièvre. | L38: Inspection, palpation (y.c ganglions !) • Rougeur-chaleur-œdème-douleur • Marquer la lésion pour voir la réponse aux ATB • Regarder entre les orteils pour porte d’entrée | M38: Si visage : • Hospitalisation • Risque de thrombose du sinus caverneux • Mise au repos • Surélévation • Pansement frais et humide • Co-Amox 10j | N38: Dermohypodermite | O38: =IFERROR(_xlfn.XLOOKUP($D38, SSP!$F:$F, SSP!$E:$E, "Inconnu"), "") -> Douleur (toutes localisations et types confondus) | P38: =IF(OR(E38="", O38=""), "", IF(LOWER(E38)=LOWER(O38), "OK", "⚠️ Libellé ≠ n°")) -> OK | Q38: =IF(Feuil1!$E38="", "", IF(LOWER(Feuil1!$E38)=LOWER(E38), "Identique", "Différent")) -> Différent | R38: =IF(OR(P38="⚠️ Libellé ≠ n°", O38="Inconnu"), "⚠️", IF(Q38="Différent", "ℹ️", "")) -> ℹ️ | S38: {=_xlfn.LET(_xlpm.genCat,IFERROR(LOWER(TRIM(G38)),""),_xlpm.principal,IFERROR(LOWER(TRIM(H38)),""),_xlpm.orig,IFERROR(LOWER(TRIM(N38)),""),IF(OR(_xlpm.genCat="",_xlpm.principal=""),"",IF(LEFT(LOWER(G38),5)="autre","OK (Autre)",IF(OR(ISNUMBER(SEARCH(_xlpm.genCat,_xlpm.principal)),ISNUMBER(SEARCH(_xlpm.principal,_xlpm.genCat)),AND(_xlpm.orig<>"",OR(ISNUMBER(SEARCH(_xlpm.genCat,_xlpm.orig)),ISNUMBER(SEARCH(_xlpm.orig,_xlpm.genCat))))),"OK","⚠️ À vérifier"))))} -> ⚠️ À vérifier | T38: =IF(S38="","",IF(S38="OK (Autre)","Diagnostic générique = 'Autre – …'",IF(S38="OK","Concordance générique/principal","Écart entre générique et principal"))) -> Écart entre générique et principal | U38: {=_xlfn.LET(_xlpm.yr, A38, _xlpm.diag, IF(N38<>"", N38, H38), _xlpm.base, TRIM(SUBSTITUTE(SUBSTITUTE(SUBSTITUTE(SUBSTITUTE(_xlpm.diag,"•"," "),CHAR(160)," "),CHAR(10)," ")," "," ")), LOWER(_xlpm.yr&"|"&_xlpm.base))} -> 2013|dermohypodermite | V38: =IFERROR(_xlfn.XLOOKUP($AB38,'Cas 2013-2017'!$K:$K,'Cas 2013-2017'!$D:$D,""),"") -> Femme 65 ans qui vient pour douleur et rougeur de la jambe depuis 2J avec EF, œdème et ADP fémorale | W38: =IFERROR(_xlfn.XLOOKUP($AB38,'Cas 2013-2017'!$K:$K,'Cas 2013-2017'!$E:$E,""),"") -> Anamnèse : • Localisation ? • Étendue ? • Évolution ? • Douleur ? Chaleur ? Rougeur ? • Œdème ? • FIEVRE ? Frissons ? • Blessures (porte d’entrée) • Immunosuppression ? Diabète ? Hygiène ? | X38: =IFERROR(_xlfn.XLOOKUP($AB38,'Cas 2013-2017'!$K:$K,'Cas 2013-2017'!$F:$F,""),"") -> Inspection, palpation (y.c ganglions !) • Rougeur-chaleur-œdème-douleur • Marquer la lésion pour voir la réponse aux ATB • Regarder entre les orteils pour porte d’entrée | Y38: =IFERROR(_xlfn.XLOOKUP($AB38,'Cas 2013-2017'!$K:$K,'Cas 2013-2017'!$G:$G,""),"") -> Eczéma de contact allergique aigu • Thrombophlébite • Acrodermatite chronique atrophiante • Fasciite nécrosante | Z38: =IFERROR(_xlfn.XLOOKUP($AB38,'Cas 2013-2017'!$K:$K,'Cas 2013-2017'!$I:$I,""),"") -> Si visage : • Hospitalisation • Risque de thrombose du sinus caverneux • Mise au repos • Surélévation • Pansement frais et humide • Co-Amox 10j | AA38: =IFERROR(_xlfn.XLOOKUP($AB38,'Cas 2013-2017'!$K:$K,'Cas 2013-2017'!$H:$H,""),"") -> Labo : VS, CRP leuco • US si suspicion de thrombose • Frottis bactério au niveau de la porte d’entrée probable • Hémocultures si fièvre | AB38: =LOWER($A38 & "|" & $AF38) -> 2013|dermohypodermite | AC38: =TRIM(SUBSTITUTE(SUBSTITUTE(SUBSTITUTE(SUBSTITUTE(" " & LOWER(TRIM(IF($N38<>"", $N38, $H38))) & " ", " aomi ", " arteriopathie des membres inferieurs "), " hta ", " hypertension arterielle "), " saos ", " syndrome d'apnees obstructives du sommeil "), " rgo ", " reflux gastro-oesophagien ") ) -> dermohypodermite | AD38: =TRIM(SUBSTITUTE(SUBSTITUTE(SUBSTITUTE(SUBSTITUTE(" " & LOWER(TRIM($AC38)) & " ", " oacr ", " occlusion de l'artere centrale de la retine "), " hsd ", " hematome sous-dural "), " fa ", " fibrillation auriculaire "), " ep ", " embolie pulmonaire ") ) -> dermohypodermite | AE38: {=_xlfn.LET(_xlpm.base, " " & LOWER(TRIM($AD38)) & " ", _xlpm.s1, SUBSTITUTE(_xlpm.base, " ic ", " insuffisance cardiaque "), _xlpm.s2, SUBSTITUTE(_xlpm.s1, " avc ", " accident vasculaire cerebral "), _xlpm.s3, SUBSTITUTE(_xlpm.s2, " hsa ", " hemorragie sous-arachnoidienne "), _xlpm.s4, SUBSTITUTE(_xlpm.s3, " htp ", " hypertension pulmonaire "), _xlpm.s5, SUBSTITUTE(_xlpm.s4, " bpco ", " bronchopneumopathie chronique obstructive "), _xlpm.s6, SUBSTITUTE(_xlpm.s5, " dmla ", " degenerescence maculaire liee a l age "), TRIM(_xlpm.s6))} -> dermohypodermite | AF38: {=_xlfn.LET(_xlpm.base, " " & LOWER(TRIM($AE38)) & " ", _xlpm.s1, SUBSTITUTE(_xlpm.base, " omi ", " oedemes des membres inferieurs "), _xlpm.s2, SUBSTITUTE(_xlpm.s1, " idm ", " infarctus du myocarde "), _xlpm.s3, SUBSTITUTE(_xlpm.s2, " tvp ", " thrombose veineuse profonde "), _xlpm.s4, SUBSTITUTE(_xlpm.s3, " geu ", " grossesse extra-uterine "), _xlpm.s5, SUBSTITUTE(_xlpm.s4, " fuo ", " fievre d origine indeterminee "), TRIM(_xlpm.s5))} -> dermohypodermite
A39: 2013 | B39: 🧴 Dermatologie | D39: 93 | E39: =IF(D39="","",IFERROR(INDEX(SSP!$E$2:$E$266, MATCH(D39, SSP!$F$2:$F$266, 0)),"")) -> Macules, papules, pustules, vésicules, ulcères, abcès, bulles, épaississement cutané, nécrose, tumeur cutanée | F39: =Feuil1!E39 -> Éruption cutanée | G39: Dermatite eczématiforme | H39: Eczéma | I39: Dermatite séborrhéique • Eczéma de contact allergique • Gale | J39: - | K39: Diagnostic d'eczéma | L39: Cf autres cas, bien regarder dans plis, derrière genou etc… • Xérose cutanée • Chéilite sèche • Dermographisme blanc • Signe de Hertoghe : Perte tier externe des sourcils (aussi dans hypothyroïdie • Pli de Dennie-Morgan : Doubles plis sous palpébraux augmenté | M39: Émollients, • Produits non irritants pour hygiène de la peau • Poussées : • Dermocorticoïdes • Immunomodulateurs topiques • Cas graves : • Photothérapie • Corticoïdes systémique courte durée | N39: Eczéma | O39: =IFERROR(_xlfn.XLOOKUP($D39, SSP!$F:$F, SSP!$E:$E, "Inconnu"), "") -> Macules, papules, pustules, vésicules, ulcères, abcès, bulles, épaississement cutané, nécrose, tumeur cutanée | P39: =IF(OR(E39="", O39=""), "", IF(LOWER(E39)=LOWER(O39), "OK", "⚠️ Libellé ≠ n°")) -> OK | Q39: =IF(Feuil1!$E39="", "", IF(LOWER(Feuil1!$E39)=LOWER(E39), "Identique", "Différent")) -> Différent | R39: =IF(OR(P39="⚠️ Libellé ≠ n°", O39="Inconnu"), "⚠️", IF(Q39="Différent", "ℹ️", "")) -> ℹ️ | S39: {=_xlfn.LET(_xlpm.genCat,IFERROR(LOWER(TRIM(G39)),""),_xlpm.principal,IFERROR(LOWER(TRIM(H39)),""),_xlpm.orig,IFERROR(LOWER(TRIM(N39)),""),IF(OR(_xlpm.genCat="",_xlpm.principal=""),"",IF(LEFT(LOWER(G39),5)="autre","OK (Autre)",IF(OR(ISNUMBER(SEARCH(_xlpm.genCat,_xlpm.principal)),ISNUMBER(SEARCH(_xlpm.principal,_xlpm.genCat)),AND(_xlpm.orig<>"",OR(ISNUMBER(SEARCH(_xlpm.genCat,_xlpm.orig)),ISNUMBER(SEARCH(_xlpm.orig,_xlpm.genCat))))),"OK","⚠️ À vérifier"))))} -> OK | T39: =IF(S39="","",IF(S39="OK (Autre)","Diagnostic générique = 'Autre – …'",IF(S39="OK","Concordance générique/principal","Écart entre générique et principal"))) -> Concordance générique/principal | U39: {=_xlfn.LET(_xlpm.yr, A39, _xlpm.diag, IF(N39<>"", N39, H39), _xlpm.base, TRIM(SUBSTITUTE(SUBSTITUTE(SUBSTITUTE(SUBSTITUTE(_xlpm.diag,"•"," "),CHAR(160)," "),CHAR(10)," ")," "," ")), LOWER(_xlpm.yr&"|"&_xlpm.base))} -> 2013|eczéma | V39: =IFERROR(_xlfn.XLOOKUP($AB39,'Cas 2013-2017'!$K:$K,'Cas 2013-2017'!$D:$D,""),"") -> Enfant de 10 ans avec lésions dans les plis des coudes | W39: =IFERROR(_xlfn.XLOOKUP($AB39,'Cas 2013-2017'!$K:$K,'Cas 2013-2017'!$E:$E,""),"") -> Anamnèse : • Localisation ? • Évolution ? • Caractère migratoire et éphémère ? • Facteur déclenchant/aggravant/soulageant ? • Épisode précédent ? • Symptôme associé ? Douleur ? Prurit ? • Anamnèse familiale (atopie) • Allergie ? • Asthme, Rhinoconjonctivite ou autres ? | X39: =IFERROR(_xlfn.XLOOKUP($AB39,'Cas 2013-2017'!$K:$K,'Cas 2013-2017'!$F:$F,""),"") -> Cf autres cas, bien regarder dans plis, derrière genou etc… • Xérose cutanée • Chéilite sèche • Dermographisme blanc • Signe de Hertoghe : Perte tier externe des sourcils (aussi dans hypothyroïdie • Pli de Dennie-Morgan : Doubles plis sous palpébraux augmenté | Y39: =IFERROR(_xlfn.XLOOKUP($AB39,'Cas 2013-2017'!$K:$K,'Cas 2013-2017'!$G:$G,""),"") -> Dermatite séborrhéique • Eczéma de contact allergique • Gale | Z39: =IFERROR(_xlfn.XLOOKUP($AB39,'Cas 2013-2017'!$K:$K,'Cas 2013-2017'!$I:$I,""),"") -> Émollients, • Produits non irritants pour hygiène de la peau • Poussées : • Dermocorticoïdes • Immunomodulateurs topiques • Cas graves : • Photothérapie • Corticoïdes systémique courte durée | AA39: =IFERROR(_xlfn.XLOOKUP($AB39,'Cas 2013-2017'!$K:$K,'Cas 2013-2017'!$H:$H,""),"") -> IgE totaux • Prick tests • Tests épicutanés avec allergènes respiratoires | AB39: =LOWER($A39 & "|" & $AF39) -> 2013|eczéma | AC39: =TRIM(SUBSTITUTE(SUBSTITUTE(SUBSTITUTE(SUBSTITUTE(" " & LOWER(TRIM(IF($N39<>"", $N39, $H39))) & " ", " aomi ", " arteriopathie des membres inferieurs "), " hta ", " hypertension arterielle "), " saos ", " syndrome d'apnees obstructives du sommeil "), " rgo ", " reflux gastro-oesophagien ") ) -> eczéma | AD39: =TRIM(SUBSTITUTE(SUBSTITUTE(SUBSTITUTE(SUBSTITUTE(" " & LOWER(TRIM($AC39)) & " ", " oacr ", " occlusion de l'artere centrale de la retine "), " hsd ", " hematome sous-dural "), " fa ", " fibrillation auriculaire "), " ep ", " embolie pulmonaire ") ) -> eczéma | AE39: {=_xlfn.LET(_xlpm.base, " " & LOWER(TRIM($AD39)) & " ", _xlpm.s1, SUBSTITUTE(_xlpm.base, " ic ", " insuffisance cardiaque "), _xlpm.s2, SUBSTITUTE(_xlpm.s1, " avc ", " accident vasculaire cerebral "), _xlpm.s3, SUBSTITUTE(_xlpm.s2, " hsa ", " hemorragie sous-arachnoidienne "), _xlpm.s4, SUBSTITUTE(_xlpm.s3, " htp ", " hypertension pulmonaire "), _xlpm.s5, SUBSTITUTE(_xlpm.s4, " bpco ", " bronchopneumopathie chronique obstructive "), _xlpm.s6, SUBSTITUTE(_xlpm.s5, " dmla ", " degenerescence maculaire liee a l age "), TRIM(_xlpm.s6))} -> eczéma | AF39: {=_xlfn.LET(_xlpm.base, " " & LOWER(TRIM($AE39)) & " ", _xlpm.s1, SUBSTITUTE(_xlpm.base, " omi ", " oedemes des membres inferieurs "), _xlpm.s2, SUBSTITUTE(_xlpm.s1, " idm ", " infarctus du myocarde "), _xlpm.s3, SUBSTITUTE(_xlpm.s2, " tvp ", " thrombose veineuse profonde "), _xlpm.s4, SUBSTITUTE(_xlpm.s3, " geu ", " grossesse extra-uterine "), _xlpm.s5, SUBSTITUTE(_xlpm.s4, " fuo ", " fievre d origine indeterminee "), TRIM(_xlpm.s5))} -> eczéma
A40: 2013 | B40: 🧴 Dermatologie | D40: 9 | E40: =IF(D40="","",IFERROR(INDEX(SSP!$E$2:$E$266, MATCH(D40, SSP!$F$2:$F$266, 0)),"")) -> Prurit | F40: =Feuil1!E40 -> Prurit | G40: Urticaire | H40: Urticaire allergique | I40: Eczéma | J40: Prurit généralisé après un repas de crevettes | K40: Réaction après ingestion de crevettes, traitement antihistaminique et corticostéroïde. | N40: Urticaire allergique | O40: =IFERROR(_xlfn.XLOOKUP($D40, SSP!$F:$F, SSP!$E:$E, "Inconnu"), "") -> Prurit | P40: =IF(OR(E40="", O40=""), "", IF(LOWER(E40)=LOWER(O40), "OK", "⚠️ Libellé ≠ n°")) -> OK | Q40: =IF(Feuil1!$E40="", "", IF(LOWER(Feuil1!$E40)=LOWER(E40), "Identique", "Différent")) -> Identique | R40: =IF(OR(P40="⚠️ Libellé ≠ n°", O40="Inconnu"), "⚠️", IF(Q40="Différent", "ℹ️", "")) | S40: {=_xlfn.LET(_xlpm.genCat,IFERROR(LOWER(TRIM(G40)),""),_xlpm.principal,IFERROR(LOWER(TRIM(H40)),""),_xlpm.orig,IFERROR(LOWER(TRIM(N40)),""),IF(OR(_xlpm.genCat="",_xlpm.principal=""),"",IF(LEFT(LOWER(G40),5)="autre","OK (Autre)",IF(OR(ISNUMBER(SEARCH(_xlpm.genCat,_xlpm.principal)),ISNUMBER(SEARCH(_xlpm.principal,_xlpm.genCat)),AND(_xlpm.orig<>"",OR(ISNUMBER(SEARCH(_xlpm.genCat,_xlpm.orig)),ISNUMBER(SEARCH(_xlpm.orig,_xlpm.genCat))))),"OK","⚠️ À vérifier"))))} -> OK | T40: =IF(S40="","",IF(S40="OK (Autre)","Diagnostic générique = 'Autre – …'",IF(S40="OK","Concordance générique/principal","Écart entre générique et principal"))) -> Concordance générique/principal | U40: {=_xlfn.LET(_xlpm.yr, A40, _xlpm.diag, IF(N40<>"", N40, H40), _xlpm.base, TRIM(SUBSTITUTE(SUBSTITUTE(SUBSTITUTE(SUBSTITUTE(_xlpm.diag,"•"," "),CHAR(160)," "),CHAR(10)," ")," "," ")), LOWER(_xlpm.yr&"|"&_xlpm.base))} -> 2013|urticaire allergique | V40: =IFERROR(_xlfn.XLOOKUP($AB40,'Cas 2013-2017'!$K:$K,'Cas 2013-2017'!$D:$D,""),"") | W40: =IFERROR(_xlfn.XLOOKUP($AB40,'Cas 2013-2017'!$K:$K,'Cas 2013-2017'!$E:$E,""),"") | X40: =IFERROR(_xlfn.XLOOKUP($AB40,'Cas 2013-2017'!$K:$K,'Cas 2013-2017'!$F:$F,""),"") | Y40: =IFERROR(_xlfn.XLOOKUP($AB40,'Cas 2013-2017'!$K:$K,'Cas 2013-2017'!$G:$G,""),"") | Z40: =IFERROR(_xlfn.XLOOKUP($AB40,'Cas 2013-2017'!$K:$K,'Cas 2013-2017'!$I:$I,""),"") | AA40: =IFERROR(_xlfn.XLOOKUP($AB40,'Cas 2013-2017'!$K:$K,'Cas 2013-2017'!$H:$H,""),"") | AB40: =LOWER($A40 & "|" & $AF40) -> 2013|urticaire allergique | AC40: =TRIM(SUBSTITUTE(SUBSTITUTE(SUBSTITUTE(SUBSTITUTE(" " & LOWER(TRIM(IF($N40<>"", $N40, $H40))) & " ", " aomi ", " arteriopathie des membres inferieurs "), " hta ", " hypertension arterielle "), " saos ", " syndrome d'apnees obstructives du sommeil "), " rgo ", " reflux gastro-oesophagien ") ) -> urticaire allergique | AD40: =TRIM(SUBSTITUTE(SUBSTITUTE(SUBSTITUTE(SUBSTITUTE(" " & LOWER(TRIM($AC40)) & " ", " oacr ", " occlusion de l'artere centrale de la retine "), " hsd ", " hematome sous-dural "), " fa ", " fibrillation auriculaire "), " ep ", " embolie pulmonaire ") ) -> urticaire allergique | AE40: {=_xlfn.LET(_xlpm.base, " " & LOWER(TRIM($AD40)) & " ", _xlpm.s1, SUBSTITUTE(_xlpm.base, " ic ", " insuffisance cardiaque "), _xlpm.s2, SUBSTITUTE(_xlpm.s1, " avc ", " accident vasculaire cerebral "), _xlpm.s3, SUBSTITUTE(_xlpm.s2, " hsa ", " hemorragie sous-arachnoidienne "), _xlpm.s4, SUBSTITUTE(_xlpm.s3, " htp ", " hypertension pulmonaire "), _xlpm.s5, SUBSTITUTE(_xlpm.s4, " bpco ", " bronchopneumopathie chronique obstructive "), _xlpm.s6, SUBSTITUTE(_xlpm.s5, " dmla ", " degenerescence maculaire liee a l age "), TRIM(_xlpm.s6))} -> urticaire allergique | AF40: {=_xlfn.LET(_xlpm.base, " " & LOWER(TRIM($AE40)) & " ", _xlpm.s1, SUBSTITUTE(_xlpm.base, " omi ", " oedemes des membres inferieurs "), _xlpm.s2, SUBSTITUTE(_xlpm.s1, " idm ", " infarctus du myocarde "), _xlpm.s3, SUBSTITUTE(_xlpm.s2, " tvp ", " thrombose veineuse profonde "), _xlpm.s4, SUBSTITUTE(_xlpm.s3, " geu ", " grossesse extra-uterine "), _xlpm.s5, SUBSTITUTE(_xlpm.s4, " fuo ", " fievre d origine indeterminee "), TRIM(_xlpm.s5))} -> urticaire allergique
A41: 2013 | B41: Autres diagnostics / non classés | C41: Entretien motivationnel | D41: 224 | E41: =IF(D41="","",IFERROR(INDEX(SSP!$E$2:$E$266, MATCH(D41, SSP!$F$2:$F$266, 0)),"")) -> Demande de bilan de santé, d’examens radiologiques ou biologiques | F41: =Feuil1!E41 -> Bilan | G41: Autre – Autre | J41: Compliance DBT2 | K41: entretien motivationnel pour le diabète chez une migrante espagnol, qui a mal aux deux jambes à cause de sa neuropathie, prends pas ses médicaments, et il fallait aussi investiguer tous les facteurs socio culturels... | O41: =IFERROR(_xlfn.XLOOKUP($D41, SSP!$F:$F, SSP!$E:$E, "Inconnu"), "") -> Demande de bilan de santé, d’examens radiologiques ou biologiques | P41: =IF(OR(E41="", O41=""), "", IF(LOWER(E41)=LOWER(O41), "OK", "⚠️ Libellé ≠ n°")) -> OK | Q41: =IF(Feuil1!$E41="", "", IF(LOWER(Feuil1!$E41)=LOWER(E41), "Identique", "Différent")) -> Différent | R41: =IF(OR(P41="⚠️ Libellé ≠ n°", O41="Inconnu"), "⚠️", IF(Q41="Différent", "ℹ️", "")) -> ℹ️ | S41: {=_xlfn.LET(_xlpm.genCat,IFERROR(LOWER(TRIM(G41)),""),_xlpm.principal,IFERROR(LOWER(TRIM(H41)),""),_xlpm.orig,IFERROR(LOWER(TRIM(N41)),""),IF(OR(_xlpm.genCat="",_xlpm.principal=""),"",IF(LEFT(LOWER(G41),5)="autre","OK (Autre)",IF(OR(ISNUMBER(SEARCH(_xlpm.genCat,_xlpm.principal)),ISNUMBER(SEARCH(_xlpm.principal,_xlpm.genCat)),AND(_xlpm.orig<>"",OR(ISNUMBER(SEARCH(_xlpm.genCat,_xlpm.orig)),ISNUMBER(SEARCH(_xlpm.orig,_xlpm.genCat))))),"OK","⚠️ À vérifier"))))} | T41: =IF(S41="","",IF(S41="OK (Autre)","Diagnostic générique = 'Autre – …'",IF(S41="OK","Concordance générique/principal","Écart entre générique et principal"))) | U41: {=_xlfn.LET(_xlpm.yr, A41, _xlpm.diag, IF(N41<>"", N41, H41), _xlpm.base, TRIM(SUBSTITUTE(SUBSTITUTE(SUBSTITUTE(SUBSTITUTE(_xlpm.diag,"•"," "),CHAR(160)," "),CHAR(10)," ")," "," ")), LOWER(_xlpm.yr&"|"&_xlpm.base))} -> 2013| | V41: =IFERROR(_xlfn.XLOOKUP($AB41,'Cas 2013-2017'!$K:$K,'Cas 2013-2017'!$D:$D,""),"") | W41: =IFERROR(_xlfn.XLOOKUP($AB41,'Cas 2013-2017'!$K:$K,'Cas 2013-2017'!$E:$E,""),"") | X41: =IFERROR(_xlfn.XLOOKUP($AB41,'Cas 2013-2017'!$K:$K,'Cas 2013-2017'!$F:$F,""),"") | Y41: =IFERROR(_xlfn.XLOOKUP($AB41,'Cas 2013-2017'!$K:$K,'Cas 2013-2017'!$G:$G,""),"") | Z41: =IFERROR(_xlfn.XLOOKUP($AB41,'Cas 2013-2017'!$K:$K,'Cas 2013-2017'!$I:$I,""),"") | AA41: =IFERROR(_xlfn.XLOOKUP($AB41,'Cas 2013-2017'!$K:$K,'Cas 2013-2017'!$H:$H,""),"") | AB41: =LOWER($A41 & "|" & $AF41) -> 2013| | AC41: =TRIM(SUBSTITUTE(SUBSTITUTE(SUBSTITUTE(SUBSTITUTE(" " & LOWER(TRIM(IF($N41<>"", $N41, $H41))) & " ", " aomi ", " arteriopathie des membres inferieurs "), " hta ", " hypertension arterielle "), " saos ", " syndrome d'apnees obstructives du sommeil "), " rgo ", " reflux gastro-oesophagien ") ) | AD41: =TRIM(SUBSTITUTE(SUBSTITUTE(SUBSTITUTE(SUBSTITUTE(" " & LOWER(TRIM($AC41)) & " ", " oacr ", " occlusion de l'artere centrale de la retine "), " hsd ", " hematome sous-dural "), " fa ", " fibrillation auriculaire "), " ep ", " embolie pulmonaire ") ) | AE41: {=_xlfn.LET(_xlpm.base, " " & LOWER(TRIM($AD41)) & " ", _xlpm.s1, SUBSTITUTE(_xlpm.base, " ic ", " insuffisance cardiaque "), _xlpm.s2, SUBSTITUTE(_xlpm.s1, " avc ", " accident vasculaire cerebral "), _xlpm.s3, SUBSTITUTE(_xlpm.s2, " hsa ", " hemorragie sous-arachnoidienne "), _xlpm.s4, SUBSTITUTE(_xlpm.s3, " htp ", " hypertension pulmonaire "), _xlpm.s5, SUBSTITUTE(_xlpm.s4, " bpco ", " bronchopneumopathie chronique obstructive "), _xlpm.s6, SUBSTITUTE(_xlpm.s5, " dmla ", " degenerescence maculaire liee a l age "), TRIM(_xlpm.s6))} | AF41: {=_xlfn.LET(_xlpm.base, " " & LOWER(TRIM($AE41)) & " ", _xlpm.s1, SUBSTITUTE(_xlpm.base, " omi ", " oedemes des membres inferieurs "), _xlpm.s2, SUBSTITUTE(_xlpm.s1, " idm ", " infarctus du myocarde "), _xlpm.s3, SUBSTITUTE(_xlpm.s2, " tvp ", " thrombose veineuse profonde "), _xlpm.s4, SUBSTITUTE(_xlpm.s3, " geu ", " grossesse extra-uterine "), _xlpm.s5, SUBSTITUTE(_xlpm.s4, " fuo ", " fievre d origine indeterminee "), TRIM(_xlpm.s5))}
A42: 2013 | B42: Autres diagnostics / non classés | C42: Entretien motivationnel | D42: 224 | E42: =IF(D42="","",IFERROR(INDEX(SSP!$E$2:$E$266, MATCH(D42, SSP!$F$2:$F$266, 0)),"")) -> Demande de bilan de santé, d’examens radiologiques ou biologiques | F42: =Feuil1!E42 -> Bilan | G42: Autre – Autre | J42: Sevrage OH | O42: =IFERROR(_xlfn.XLOOKUP($D42, SSP!$F:$F, SSP!$E:$E, "Inconnu"), "") -> Demande de bilan de santé, d’examens radiologiques ou biologiques | P42: =IF(OR(E42="", O42=""), "", IF(LOWER(E42)=LOWER(O42), "OK", "⚠️ Libellé ≠ n°")) -> OK | Q42: =IF(Feuil1!$E42="", "", IF(LOWER(Feuil1!$E42)=LOWER(E42), "Identique", "Différent")) -> Différent | R42: =IF(OR(P42="⚠️ Libellé ≠ n°", O42="Inconnu"), "⚠️", IF(Q42="Différent", "ℹ️", "")) -> ℹ️ | S42: {=_xlfn.LET(_xlpm.genCat,IFERROR(LOWER(TRIM(G42)),""),_xlpm.principal,IFERROR(LOWER(TRIM(H42)),""),_xlpm.orig,IFERROR(LOWER(TRIM(N42)),""),IF(OR(_xlpm.genCat="",_xlpm.principal=""),"",IF(LEFT(LOWER(G42),5)="autre","OK (Autre)",IF(OR(ISNUMBER(SEARCH(_xlpm.genCat,_xlpm.principal)),ISNUMBER(SEARCH(_xlpm.principal,_xlpm.genCat)),AND(_xlpm.orig<>"",OR(ISNUMBER(SEARCH(_xlpm.genCat,_xlpm.orig)),ISNUMBER(SEARCH(_xlpm.orig,_xlpm.genCat))))),"OK","⚠️ À vérifier"))))} | T42: =IF(S42="","",IF(S42="OK (Autre)","Diagnostic générique = 'Autre – …'",IF(S42="OK","Concordance générique/principal","Écart entre générique et principal"))) | U42: {=_xlfn.LET(_xlpm.yr, A42, _xlpm.diag, IF(N42<>"", N42, H42), _xlpm.base, TRIM(SUBSTITUTE(SUBSTITUTE(SUBSTITUTE(SUBSTITUTE(_xlpm.diag,"•"," "),CHAR(160)," "),CHAR(10)," ")," "," ")), LOWER(_xlpm.yr&"|"&_xlpm.base))} -> 2013| | V42: =IFERROR(_xlfn.XLOOKUP($AB42,'Cas 2013-2017'!$K:$K,'Cas 2013-2017'!$D:$D,""),"") | W42: =IFERROR(_xlfn.XLOOKUP($AB42,'Cas 2013-2017'!$K:$K,'Cas 2013-2017'!$E:$E,""),"") | X42: =IFERROR(_xlfn.XLOOKUP($AB42,'Cas 2013-2017'!$K:$K,'Cas 2013-2017'!$F:$F,""),"") | Y42: =IFERROR(_xlfn.XLOOKUP($AB42,'Cas 2013-2017'!$K:$K,'Cas 2013-2017'!$G:$G,""),"") | Z42: =IFERROR(_xlfn.XLOOKUP($AB42,'Cas 2013-2017'!$K:$K,'Cas 2013-2017'!$I:$I,""),"") | AA42: =IFERROR(_xlfn.XLOOKUP($AB42,'Cas 2013-2017'!$K:$K,'Cas 2013-2017'!$H:$H,""),"") | AB42: =LOWER($A42 & "|" & $AF42) -> 2013| | AC42: =TRIM(SUBSTITUTE(SUBSTITUTE(SUBSTITUTE(SUBSTITUTE(" " & LOWER(TRIM(IF($N42<>"", $N42, $H42))) & " ", " aomi ", " arteriopathie des membres inferieurs "), " hta ", " hypertension arterielle "), " saos ", " syndrome d'apnees obstructives du sommeil "), " rgo ", " reflux gastro-oesophagien ") ) | AD42: =TRIM(SUBSTITUTE(SUBSTITUTE(SUBSTITUTE(SUBSTITUTE(" " & LOWER(TRIM($AC42)) & " ", " oacr ", " occlusion de l'artere centrale de la retine "), " hsd ", " hematome sous-dural "), " fa ", " fibrillation auriculaire "), " ep ", " embolie pulmonaire ") ) | AE42: {=_xlfn.LET(_xlpm.base, " " & LOWER(TRIM($AD42)) & " ", _xlpm.s1, SUBSTITUTE(_xlpm.base, " ic ", " insuffisance cardiaque "), _xlpm.s2, SUBSTITUTE(_xlpm.s1, " avc ", " accident vasculaire cerebral "), _xlpm.s3, SUBSTITUTE(_xlpm.s2, " hsa ", " hemorragie sous-arachnoidienne "), _xlpm.s4, SUBSTITUTE(_xlpm.s3, " htp ", " hypertension pulmonaire "), _xlpm.s5, SUBSTITUTE(_xlpm.s4, " bpco ", " bronchopneumopathie chronique obstructive "), _xlpm.s6, SUBSTITUTE(_xlpm.s5, " dmla ", " degenerescence maculaire liee a l age "), TRIM(_xlpm.s6))} | AF42: {=_xlfn.LET(_xlpm.base, " " & LOWER(TRIM($AE42)) & " ", _xlpm.s1, SUBSTITUTE(_xlpm.base, " omi ", " oedemes des membres inferieurs "), _xlpm.s2, SUBSTITUTE(_xlpm.s1, " idm ", " infarctus du myocarde "), _xlpm.s3, SUBSTITUTE(_xlpm.s2, " tvp ", " thrombose veineuse profonde "), _xlpm.s4, SUBSTITUTE(_xlpm.s3, " geu ", " grossesse extra-uterine "), _xlpm.s5, SUBSTITUTE(_xlpm.s4, " fuo ", " fievre d origine indeterminee "), TRIM(_xlpm.s5))}
A43: 2013 | B43: 🧪 Endocrinologie / Métabolisme | D43: 4 | E43: =IF(D43="","",IFERROR(INDEX(SSP!$E$2:$E$266, MATCH(D43, SSP!$F$2:$F$266, 0)),"")) -> Fatigue, asthénie | F43: =Feuil1!E43 -> Fatigue | G43: Hyperthyroïdie | H43: Hyperthyroïdie | J43: Fatigue chez une femme 45 ans | K43: pas de changement de vie, mais intolérance au chaud, palpitations, thyroide augmentée en taille, hyper-reflexie, et cie, donc typo-thyroidie, mais en fait je sais pas si c'est pas plutôt hyper, sur le moment j'ai eu un sérieux doute. | N43: Hyperthyroidie | O43: =IFERROR(_xlfn.XLOOKUP($D43, SSP!$F:$F, SSP!$E:$E, "Inconnu"), "") -> Fatigue, asthénie | P43: =IF(OR(E43="", O43=""), "", IF(LOWER(E43)=LOWER(O43), "OK", "⚠️ Libellé ≠ n°")) -> OK | Q43: =IF(Feuil1!$E43="", "", IF(LOWER(Feuil1!$E43)=LOWER(E43), "Identique", "Différent")) -> Différent | R43: =IF(OR(P43="⚠️ Libellé ≠ n°", O43="Inconnu"), "⚠️", IF(Q43="Différent", "ℹ️", "")) -> ℹ️ | S43: {=_xlfn.LET(_xlpm.genCat,IFERROR(LOWER(TRIM(G43)),""),_xlpm.principal,IFERROR(LOWER(TRIM(H43)),""),_xlpm.orig,IFERROR(LOWER(TRIM(N43)),""),IF(OR(_xlpm.genCat="",_xlpm.principal=""),"",IF(LEFT(LOWER(G43),5)="autre","OK (Autre)",IF(OR(ISNUMBER(SEARCH(_xlpm.genCat,_xlpm.principal)),ISNUMBER(SEARCH(_xlpm.principal,_xlpm.genCat)),AND(_xlpm.orig<>"",OR(ISNUMBER(SEARCH(_xlpm.genCat,_xlpm.orig)),ISNUMBER(SEARCH(_xlpm.orig,_xlpm.genCat))))),"OK","⚠️ À vérifier"))))} -> OK | T43: =IF(S43="","",IF(S43="OK (Autre)","Diagnostic générique = 'Autre – …'",IF(S43="OK","Concordance générique/principal","Écart entre générique et principal"))) -> Concordance générique/principal | U43: {=_xlfn.LET(_xlpm.yr, A43, _xlpm.diag, IF(N43<>"", N43, H43), _xlpm.base, TRIM(SUBSTITUTE(SUBSTITUTE(SUBSTITUTE(SUBSTITUTE(_xlpm.diag,"•"," "),CHAR(160)," "),CHAR(10)," ")," "," ")), LOWER(_xlpm.yr&"|"&_xlpm.base))} -> 2013|hyperthyroidie | V43: =IFERROR(_xlfn.XLOOKUP($AB43,'Cas 2013-2017'!$K:$K,'Cas 2013-2017'!$D:$D,""),"") | W43: =IFERROR(_xlfn.XLOOKUP($AB43,'Cas 2013-2017'!$K:$K,'Cas 2013-2017'!$E:$E,""),"") | X43: =IFERROR(_xlfn.XLOOKUP($AB43,'Cas 2013-2017'!$K:$K,'Cas 2013-2017'!$F:$F,""),"") | Y43: =IFERROR(_xlfn.XLOOKUP($AB43,'Cas 2013-2017'!$K:$K,'Cas 2013-2017'!$G:$G,""),"") | Z43: =IFERROR(_xlfn.XLOOKUP($AB43,'Cas 2013-2017'!$K:$K,'Cas 2013-2017'!$I:$I,""),"") | AA43: =IFERROR(_xlfn.XLOOKUP($AB43,'Cas 2013-2017'!$K:$K,'Cas 2013-2017'!$H:$H,""),"") | AB43: =LOWER($A43 & "|" & $AF43) -> 2013|hyperthyroidie | AC43: =TRIM(SUBSTITUTE(SUBSTITUTE(SUBSTITUTE(SUBSTITUTE(" " & LOWER(TRIM(IF($N43<>"", $N43, $H43))) & " ", " aomi ", " arteriopathie des membres inferieurs "), " hta ", " hypertension arterielle "), " saos ", " syndrome d'apnees obstructives du sommeil "), " rgo ", " reflux gastro-oesophagien ") ) -> hyperthyroidie | AD43: =TRIM(SUBSTITUTE(SUBSTITUTE(SUBSTITUTE(SUBSTITUTE(" " & LOWER(TRIM($AC43)) & " ", " oacr ", " occlusion de l'artere centrale de la retine "), " hsd ", " hematome sous-dural "), " fa ", " fibrillation auriculaire "), " ep ", " embolie pulmonaire ") ) -> hyperthyroidie | AE43: {=_xlfn.LET(_xlpm.base, " " & LOWER(TRIM($AD43)) & " ", _xlpm.s1, SUBSTITUTE(_xlpm.base, " ic ", " insuffisance cardiaque "), _xlpm.s2, SUBSTITUTE(_xlpm.s1, " avc ", " accident vasculaire cerebral "), _xlpm.s3, SUBSTITUTE(_xlpm.s2, " hsa ", " hemorragie sous-arachnoidienne "), _xlpm.s4, SUBSTITUTE(_xlpm.s3, " htp ", " hypertension pulmonaire "), _xlpm.s5, SUBSTITUTE(_xlpm.s4, " bpco ", " bronchopneumopathie chronique obstructive "), _xlpm.s6, SUBSTITUTE(_xlpm.s5, " dmla ", " degenerescence maculaire liee a l age "), TRIM(_xlpm.s6))} -> hyperthyroidie | AF43: {=_xlfn.LET(_xlpm.base, " " & LOWER(TRIM($AE43)) & " ", _xlpm.s1, SUBSTITUTE(_xlpm.base, " omi ", " oedemes des membres inferieurs "), _xlpm.s2, SUBSTITUTE(_xlpm.s1, " idm ", " infarctus du myocarde "), _xlpm.s3, SUBSTITUTE(_xlpm.s2, " tvp ", " thrombose veineuse profonde "), _xlpm.s4, SUBSTITUTE(_xlpm.s3, " geu ", " grossesse extra-uterine "), _xlpm.s5, SUBSTITUTE(_xlpm.s4, " fuo ", " fievre d origine indeterminee "), TRIM(_xlpm.s5))} -> hyperthyroidie
A44: 2013 | B44: Autres diagnostics / non classés | D44: 52 | E44: =IF(D44="","",IFERROR(INDEX(SSP!$E$2:$E$266, MATCH(D44, SSP!$F$2:$F$266, 0)),"")) -> Douleur abdominale ou épigastrique | F44: =Feuil1!E44 -> Douleur abdominale | G44: Autre – Autre | H44: Diverticulites | J44: Vieille dame avec douleurs abdominales en fosse iliaque gauche (FIG), CRP 80 et leucocytes augmentés. | K44: Add CT et coloscopie à distance | N44: Diverticulites | O44: =IFERROR(_xlfn.XLOOKUP($D44, SSP!$F:$F, SSP!$E:$E, "Inconnu"), "") -> Douleur abdominale ou épigastrique | P44: =IF(OR(E44="", O44=""), "", IF(LOWER(E44)=LOWER(O44), "OK", "⚠️ Libellé ≠ n°")) -> OK | Q44: =IF(Feuil1!$E44="", "", IF(LOWER(Feuil1!$E44)=LOWER(E44), "Identique", "Différent")) -> Différent | R44: =IF(OR(P44="⚠️ Libellé ≠ n°", O44="Inconnu"), "⚠️", IF(Q44="Différent", "ℹ️", "")) -> ℹ️ | S44: {=_xlfn.LET(_xlpm.genCat,IFERROR(LOWER(TRIM(G44)),""),_xlpm.principal,IFERROR(LOWER(TRIM(H44)),""),_xlpm.orig,IFERROR(LOWER(TRIM(N44)),""),IF(OR(_xlpm.genCat="",_xlpm.principal=""),"",IF(LEFT(LOWER(G44),5)="autre","OK (Autre)",IF(OR(ISNUMBER(SEARCH(_xlpm.genCat,_xlpm.principal)),ISNUMBER(SEARCH(_xlpm.principal,_xlpm.genCat)),AND(_xlpm.orig<>"",OR(ISNUMBER(SEARCH(_xlpm.genCat,_xlpm.orig)),ISNUMBER(SEARCH(_xlpm.orig,_xlpm.genCat))))),"OK","⚠️ À vérifier"))))} -> OK (Autre) | T44: =IF(S44="","",IF(S44="OK (Autre)","Diagnostic générique = 'Autre – …'",IF(S44="OK","Concordance générique/principal","Écart entre générique et principal"))) -> Diagnostic générique = 'Autre – …' | U44: {=_xlfn.LET(_xlpm.yr, A44, _xlpm.diag, IF(N44<>"", N44, H44), _xlpm.base, TRIM(SUBSTITUTE(SUBSTITUTE(SUBSTITUTE(SUBSTITUTE(_xlpm.diag,"•"," "),CHAR(160)," "),CHAR(10)," ")," "," ")), LOWER(_xlpm.yr&"|"&_xlpm.base))} -> 2013|diverticulites | V44: =IFERROR(_xlfn.XLOOKUP($AB44,'Cas 2013-2017'!$K:$K,'Cas 2013-2017'!$D:$D,""),"") | W44: =IFERROR(_xlfn.XLOOKUP($AB44,'Cas 2013-2017'!$K:$K,'Cas 2013-2017'!$E:$E,""),"") | X44: =IFERROR(_xlfn.XLOOKUP($AB44,'Cas 2013-2017'!$K:$K,'Cas 2013-2017'!$F:$F,""),"") | Y44: =IFERROR(_xlfn.XLOOKUP($AB44,'Cas 2013-2017'!$K:$K,'Cas 2013-2017'!$G:$G,""),"") | Z44: =IFERROR(_xlfn.XLOOKUP($AB44,'Cas 2013-2017'!$K:$K,'Cas 2013-2017'!$I:$I,""),"") | AA44: =IFERROR(_xlfn.XLOOKUP($AB44,'Cas 2013-2017'!$K:$K,'Cas 2013-2017'!$H:$H,""),"") | AB44: =LOWER($A44 & "|" & $AF44) -> 2013|diverticulites | AC44: =TRIM(SUBSTITUTE(SUBSTITUTE(SUBSTITUTE(SUBSTITUTE(" " & LOWER(TRIM(IF($N44<>"", $N44, $H44))) & " ", " aomi ", " arteriopathie des membres inferieurs "), " hta ", " hypertension arterielle "), " saos ", " syndrome d'apnees obstructives du sommeil "), " rgo ", " reflux gastro-oesophagien ") ) -> diverticulites | AD44: =TRIM(SUBSTITUTE(SUBSTITUTE(SUBSTITUTE(SUBSTITUTE(" " & LOWER(TRIM($AC44)) & " ", " oacr ", " occlusion de l'artere centrale de la retine "), " hsd ", " hematome sous-dural "), " fa ", " fibrillation auriculaire "), " ep ", " embolie pulmonaire ") ) -> diverticulites | AE44: {=_xlfn.LET(_xlpm.base, " " & LOWER(TRIM($AD44)) & " ", _xlpm.s1, SUBSTITUTE(_xlpm.base, " ic ", " insuffisance cardiaque "), _xlpm.s2, SUBSTITUTE(_xlpm.s1, " avc ", " accident vasculaire cerebral "), _xlpm.s3, SUBSTITUTE(_xlpm.s2, " hsa ", " hemorragie sous-arachnoidienne "), _xlpm.s4, SUBSTITUTE(_xlpm.s3, " htp ", " hypertension pulmonaire "), _xlpm.s5, SUBSTITUTE(_xlpm.s4, " bpco ", " bronchopneumopathie chronique obstructive "), _xlpm.s6, SUBSTITUTE(_xlpm.s5, " dmla ", " degenerescence maculaire liee a l age "), TRIM(_xlpm.s6))} -> diverticulites | AF44: {=_xlfn.LET(_xlpm.base, " " & LOWER(TRIM($AE44)) & " ", _xlpm.s1, SUBSTITUTE(_xlpm.base, " omi ", " oedemes des membres inferieurs "), _xlpm.s2, SUBSTITUTE(_xlpm.s1, " idm ", " infarctus du myocarde "), _xlpm.s3, SUBSTITUTE(_xlpm.s2, " tvp ", " thrombose veineuse profonde "), _xlpm.s4, SUBSTITUTE(_xlpm.s3, " geu ", " grossesse extra-uterine "), _xlpm.s5, SUBSTITUTE(_xlpm.s4, " fuo ", " fievre d origine indeterminee "), TRIM(_xlpm.s5))} -> diverticulites
A45: 2013 | B45: 🍴 Gastro-entérologie / Hépatologie | D45: 52 | E45: =IF(D45="","",IFERROR(INDEX(SSP!$E$2:$E$266, MATCH(D45, SSP!$F$2:$F$266, 0)),"")) -> Douleur abdominale ou épigastrique | F45: =Feuil1!E45 -> Douleur abdominale | G45: Pancréatite | H45: Pancréatite biliaire | J45: Dlr épigastrique, distension, ileus → baisse des bruits abdo | K45: Ictère et signe de Cullen | L45: Dlr épigastrique, distension, ileus→ baisse des bruits abdo • Examen de la peau → ictère, signe de Cullen... | M45: Hosp. • Fluides (cristalloïdes), analgésie • Bowel rest • ERCP + cholecystectomie | N45: Pancréatite biliaire | O45: =IFERROR(_xlfn.XLOOKUP($D45, SSP!$F:$F, SSP!$E:$E, "Inconnu"), "") -> Douleur abdominale ou épigastrique | P45: =IF(OR(E45="", O45=""), "", IF(LOWER(E45)=LOWER(O45), "OK", "⚠️ Libellé ≠ n°")) -> OK | Q45: =IF(Feuil1!$E45="", "", IF(LOWER(Feuil1!$E45)=LOWER(E45), "Identique", "Différent")) -> Différent | R45: =IF(OR(P45="⚠️ Libellé ≠ n°", O45="Inconnu"), "⚠️", IF(Q45="Différent", "ℹ️", "")) -> ℹ️ | S45: {=_xlfn.LET(_xlpm.genCat,IFERROR(LOWER(TRIM(G45)),""),_xlpm.principal,IFERROR(LOWER(TRIM(H45)),""),_xlpm.orig,IFERROR(LOWER(TRIM(N45)),""),IF(OR(_xlpm.genCat="",_xlpm.principal=""),"",IF(LEFT(LOWER(G45),5)="autre","OK (Autre)",IF(OR(ISNUMBER(SEARCH(_xlpm.genCat,_xlpm.principal)),ISNUMBER(SEARCH(_xlpm.principal,_xlpm.genCat)),AND(_xlpm.orig<>"",OR(ISNUMBER(SEARCH(_xlpm.genCat,_xlpm.orig)),ISNUMBER(SEARCH(_xlpm.orig,_xlpm.genCat))))),"OK","⚠️ À vérifier"))))} -> OK | T45: =IF(S45="","",IF(S45="OK (Autre)","Diagnostic générique = 'Autre – …'",IF(S45="OK","Concordance générique/principal","Écart entre générique et principal"))) -> Concordance générique/principal | U45: {=_xlfn.LET(_xlpm.yr, A45, _xlpm.diag, IF(N45<>"", N45, H45), _xlpm.base, TRIM(SUBSTITUTE(SUBSTITUTE(SUBSTITUTE(SUBSTITUTE(_xlpm.diag,"•"," "),CHAR(160)," "),CHAR(10)," ")," "," ")), LOWER(_xlpm.yr&"|"&_xlpm.base))} -> 2013|pancréatite biliaire | V45: =IFERROR(_xlfn.XLOOKUP($AB45,'Cas 2013-2017'!$K:$K,'Cas 2013-2017'!$D:$D,""),"") -> 0 | W45: =IFERROR(_xlfn.XLOOKUP($AB45,'Cas 2013-2017'!$K:$K,'Cas 2013-2017'!$E:$E,""),"") -> lithiase biliaire • Alcool • Chirurgie récente • Douleur en ceinture typique, irradiant au dos, pire après les repas et couché, amélioré si se penche en avant. • N/V • Ictère | X45: =IFERROR(_xlfn.XLOOKUP($AB45,'Cas 2013-2017'!$K:$K,'Cas 2013-2017'!$F:$F,""),"") -> Dlr épigastrique, distension, ileus→ baisse des bruits abdo • Examen de la peau → ictère, signe de Cullen... | Y45: =IFERROR(_xlfn.XLOOKUP($AB45,'Cas 2013-2017'!$K:$K,'Cas 2013-2017'!$G:$G,""),"") -> 0 | Z45: =IFERROR(_xlfn.XLOOKUP($AB45,'Cas 2013-2017'!$K:$K,'Cas 2013-2017'!$I:$I,""),"") -> Hosp. • Fluides (cristalloïdes), analgésie • Bowel rest • ERCP + cholecystectomie | AA45: =IFERROR(_xlfn.XLOOKUP($AB45,'Cas 2013-2017'!$K:$K,'Cas 2013-2017'!$H:$H,""),"") -> Labo: FSS, urée, CRP, créat, ALAT, ASAT, PA, bili, Ca, TG, amylase, lipase • Lipases augmentée 3x! • US (CT rarement utilisé) • ERCP | AB45: =LOWER($A45 & "|" & $AF45) -> 2013|pancréatite biliaire | AC45: =TRIM(SUBSTITUTE(SUBSTITUTE(SUBSTITUTE(SUBSTITUTE(" " & LOWER(TRIM(IF($N45<>"", $N45, $H45))) & " ", " aomi ", " arteriopathie des membres inferieurs "), " hta ", " hypertension arterielle "), " saos ", " syndrome d'apnees obstructives du sommeil "), " rgo ", " reflux gastro-oesophagien ") ) -> pancréatite biliaire | AD45: =TRIM(SUBSTITUTE(SUBSTITUTE(SUBSTITUTE(SUBSTITUTE(" " & LOWER(TRIM($AC45)) & " ", " oacr ", " occlusion de l'artere centrale de la retine "), " hsd ", " hematome sous-dural "), " fa ", " fibrillation auriculaire "), " ep ", " embolie pulmonaire ") ) -> pancréatite biliaire | AE45: {=_xlfn.LET(_xlpm.base, " " & LOWER(TRIM($AD45)) & " ", _xlpm.s1, SUBSTITUTE(_xlpm.base, " ic ", " insuffisance cardiaque "), _xlpm.s2, SUBSTITUTE(_xlpm.s1, " avc ", " accident vasculaire cerebral "), _xlpm.s3, SUBSTITUTE(_xlpm.s2, " hsa ", " hemorragie sous-arachnoidienne "), _xlpm.s4, SUBSTITUTE(_xlpm.s3, " htp ", " hypertension pulmonaire "), _xlpm.s5, SUBSTITUTE(_xlpm.s4, " bpco ", " bronchopneumopathie chronique obstructive "), _xlpm.s6, SUBSTITUTE(_xlpm.s5, " dmla ", " degenerescence maculaire liee a l age "), TRIM(_xlpm.s6))} -> pancréatite biliaire | AF45: {=_xlfn.LET(_xlpm.base, " " & LOWER(TRIM($AE45)) & " ", _xlpm.s1, SUBSTITUTE(_xlpm.base, " omi ", " oedemes des membres inferieurs "), _xlpm.s2, SUBSTITUTE(_xlpm.s1, " idm ", " infarctus du myocarde "), _xlpm.s3, SUBSTITUTE(_xlpm.s2, " tvp ", " thrombose veineuse profonde "), _xlpm.s4, SUBSTITUTE(_xlpm.s3, " geu ", " grossesse extra-uterine "), _xlpm.s5, SUBSTITUTE(_xlpm.s4, " fuo ", " fievre d origine indeterminee "), TRIM(_xlpm.s5))} -> pancréatite biliaire
A46: 2013 | B46: 👩‍🦰 Gynéco / Obstétrique / Urologie | D46: 69 | E46: =IF(D46="","",IFERROR(INDEX(SSP!$E$2:$E$266, MATCH(D46, SSP!$F$2:$F$266, 0)),"")) -> Demande de contraception, contraception d’urgence | F46: =Feuil1!E46 -> Contraception | G46: Conseil de grossesse | H46: Grossesse (conseils) | J46: Femme de 38 ans avec premier test de grossesse positif. | K46: Aucun examen à réaliser. | N46: Grossesse (conseils) | O46: =IFERROR(_xlfn.XLOOKUP($D46, SSP!$F:$F, SSP!$E:$E, "Inconnu"), "") -> Demande de contraception, contraception d’urgence | P46: =IF(OR(E46="", O46=""), "", IF(LOWER(E46)=LOWER(O46), "OK", "⚠️ Libellé ≠ n°")) -> OK | Q46: =IF(Feuil1!$E46="", "", IF(LOWER(Feuil1!$E46)=LOWER(E46), "Identique", "Différent")) -> Différent | R46: =IF(OR(P46="⚠️ Libellé ≠ n°", O46="Inconnu"), "⚠️", IF(Q46="Différent", "ℹ️", "")) -> ℹ️ | S46: {=_xlfn.LET(_xlpm.genCat,IFERROR(LOWER(TRIM(G46)),""),_xlpm.principal,IFERROR(LOWER(TRIM(H46)),""),_xlpm.orig,IFERROR(LOWER(TRIM(N46)),""),IF(OR(_xlpm.genCat="",_xlpm.principal=""),"",IF(LEFT(LOWER(G46),5)="autre","OK (Autre)",IF(OR(ISNUMBER(SEARCH(_xlpm.genCat,_xlpm.principal)),ISNUMBER(SEARCH(_xlpm.principal,_xlpm.genCat)),AND(_xlpm.orig<>"",OR(ISNUMBER(SEARCH(_xlpm.genCat,_xlpm.orig)),ISNUMBER(SEARCH(_xlpm.orig,_xlpm.genCat))))),"OK","⚠️ À vérifier"))))} -> ⚠️ À vérifier | T46: =IF(S46="","",IF(S46="OK (Autre)","Diagnostic générique = 'Autre – …'",IF(S46="OK","Concordance générique/principal","Écart entre générique et principal"))) -> Écart entre générique et principal | U46: {=_xlfn.LET(_xlpm.yr, A46, _xlpm.diag, IF(N46<>"", N46, H46), _xlpm.base, TRIM(SUBSTITUTE(SUBSTITUTE(SUBSTITUTE(SUBSTITUTE(_xlpm.diag,"•"," "),CHAR(160)," "),CHAR(10)," ")," "," ")), LOWER(_xlpm.yr&"|"&_xlpm.base))} -> 2013|grossesse (conseils) | V46: =IFERROR(_xlfn.XLOOKUP($AB46,'Cas 2013-2017'!$K:$K,'Cas 2013-2017'!$D:$D,""),"") | W46: =IFERROR(_xlfn.XLOOKUP($AB46,'Cas 2013-2017'!$K:$K,'Cas 2013-2017'!$E:$E,""),"") | X46: =IFERROR(_xlfn.XLOOKUP($AB46,'Cas 2013-2017'!$K:$K,'Cas 2013-2017'!$F:$F,""),"") | Y46: =IFERROR(_xlfn.XLOOKUP($AB46,'Cas 2013-2017'!$K:$K,'Cas 2013-2017'!$G:$G,""),"") | Z46: =IFERROR(_xlfn.XLOOKUP($AB46,'Cas 2013-2017'!$K:$K,'Cas 2013-2017'!$I:$I,""),"") | AA46: =IFERROR(_xlfn.XLOOKUP($AB46,'Cas 2013-2017'!$K:$K,'Cas 2013-2017'!$H:$H,""),"") | AB46: =LOWER($A46 & "|" & $AF46) -> 2013|grossesse (conseils) | AC46: =TRIM(SUBSTITUTE(SUBSTITUTE(SUBSTITUTE(SUBSTITUTE(" " & LOWER(TRIM(IF($N46<>"", $N46, $H46))) & " ", " aomi ", " arteriopathie des membres inferieurs "), " hta ", " hypertension arterielle "), " saos ", " syndrome d'apnees obstructives du sommeil "), " rgo ", " reflux gastro-oesophagien ") ) -> grossesse (conseils) | AD46: =TRIM(SUBSTITUTE(SUBSTITUTE(SUBSTITUTE(SUBSTITUTE(" " & LOWER(TRIM($AC46)) & " ", " oacr ", " occlusion de l'artere centrale de la retine "), " hsd ", " hematome sous-dural "), " fa ", " fibrillation auriculaire "), " ep ", " embolie pulmonaire ") ) -> grossesse (conseils) | AE46: {=_xlfn.LET(_xlpm.base, " " & LOWER(TRIM($AD46)) & " ", _xlpm.s1, SUBSTITUTE(_xlpm.base, " ic ", " insuffisance cardiaque "), _xlpm.s2, SUBSTITUTE(_xlpm.s1, " avc ", " accident vasculaire cerebral "), _xlpm.s3, SUBSTITUTE(_xlpm.s2, " hsa ", " hemorragie sous-arachnoidienne "), _xlpm.s4, SUBSTITUTE(_xlpm.s3, " htp ", " hypertension pulmonaire "), _xlpm.s5, SUBSTITUTE(_xlpm.s4, " bpco ", " bronchopneumopathie chronique obstructive "), _xlpm.s6, SUBSTITUTE(_xlpm.s5, " dmla ", " degenerescence maculaire liee a l age "), TRIM(_xlpm.s6))} -> grossesse (conseils) | AF46: {=_xlfn.LET(_xlpm.base, " " & LOWER(TRIM($AE46)) & " ", _xlpm.s1, SUBSTITUTE(_xlpm.base, " omi ", " oedemes des membres inferieurs "), _xlpm.s2, SUBSTITUTE(_xlpm.s1, " idm ", " infarctus du myocarde "), _xlpm.s3, SUBSTITUTE(_xlpm.s2, " tvp ", " thrombose veineuse profonde "), _xlpm.s4, SUBSTITUTE(_xlpm.s3, " geu ", " grossesse extra-uterine "), _xlpm.s5, SUBSTITUTE(_xlpm.s4, " fuo ", " fievre d origine indeterminee "), TRIM(_xlpm.s5))} -> grossesse (conseils)
A47: 2013 | B47: 👩‍🦰 Gynéco / Obstétrique / Urologie | D47: 207 | E47: =IF(D47="","",IFERROR(INDEX(SSP!$E$2:$E$266, MATCH(D47, SSP!$F$2:$F$266, 0)),"")) -> Céphalée aiguë intense, syndrome méningé | F47: =Feuil1!E47 -> Céphalée | G47: Autre – ‍ Gynéco / Obstétrique / Urologie | H47: Prééclampsie | J47: Céphalées chez femme enceinte, exclusion de la prééclampsie. | N47: Prééclampsie | O47: =IFERROR(_xlfn.XLOOKUP($D47, SSP!$F:$F, SSP!$E:$E, "Inconnu"), "") -> Céphalée aiguë intense, syndrome méningé | P47: =IF(OR(E47="", O47=""), "", IF(LOWER(E47)=LOWER(O47), "OK", "⚠️ Libellé ≠ n°")) -> OK | Q47: =IF(Feuil1!$E47="", "", IF(LOWER(Feuil1!$E47)=LOWER(E47), "Identique", "Différent")) -> Différent | R47: =IF(OR(P47="⚠️ Libellé ≠ n°", O47="Inconnu"), "⚠️", IF(Q47="Différent", "ℹ️", "")) -> ℹ️ | S47: {=_xlfn.LET(_xlpm.genCat,IFERROR(LOWER(TRIM(G47)),""),_xlpm.principal,IFERROR(LOWER(TRIM(H47)),""),_xlpm.orig,IFERROR(LOWER(TRIM(N47)),""),IF(OR(_xlpm.genCat="",_xlpm.principal=""),"",IF(LEFT(LOWER(G47),5)="autre","OK (Autre)",IF(OR(ISNUMBER(SEARCH(_xlpm.genCat,_xlpm.principal)),ISNUMBER(SEARCH(_xlpm.principal,_xlpm.genCat)),AND(_xlpm.orig<>"",OR(ISNUMBER(SEARCH(_xlpm.genCat,_xlpm.orig)),ISNUMBER(SEARCH(_xlpm.orig,_xlpm.genCat))))),"OK","⚠️ À vérifier"))))} -> OK (Autre) | T47: =IF(S47="","",IF(S47="OK (Autre)","Diagnostic générique = 'Autre – …'",IF(S47="OK","Concordance générique/principal","Écart entre générique et principal"))) -> Diagnostic générique = 'Autre – …' | U47: {=_xlfn.LET(_xlpm.yr, A47, _xlpm.diag, IF(N47<>"", N47, H47), _xlpm.base, TRIM(SUBSTITUTE(SUBSTITUTE(SUBSTITUTE(SUBSTITUTE(_xlpm.diag,"•"," "),CHAR(160)," "),CHAR(10)," ")," "," ")), LOWER(_xlpm.yr&"|"&_xlpm.base))} -> 2013|prééclampsie | V47: =IFERROR(_xlfn.XLOOKUP($AB47,'Cas 2013-2017'!$K:$K,'Cas 2013-2017'!$D:$D,""),"") | W47: =IFERROR(_xlfn.XLOOKUP($AB47,'Cas 2013-2017'!$K:$K,'Cas 2013-2017'!$E:$E,""),"") | X47: =IFERROR(_xlfn.XLOOKUP($AB47,'Cas 2013-2017'!$K:$K,'Cas 2013-2017'!$F:$F,""),"") | Y47: =IFERROR(_xlfn.XLOOKUP($AB47,'Cas 2013-2017'!$K:$K,'Cas 2013-2017'!$G:$G,""),"") | Z47: =IFERROR(_xlfn.XLOOKUP($AB47,'Cas 2013-2017'!$K:$K,'Cas 2013-2017'!$I:$I,""),"") | AA47: =IFERROR(_xlfn.XLOOKUP($AB47,'Cas 2013-2017'!$K:$K,'Cas 2013-2017'!$H:$H,""),"") | AB47: =LOWER($A47 & "|" & $AF47) -> 2013|prééclampsie | AC47: =TRIM(SUBSTITUTE(SUBSTITUTE(SUBSTITUTE(SUBSTITUTE(" " & LOWER(TRIM(IF($N47<>"", $N47, $H47))) & " ", " aomi ", " arteriopathie des membres inferieurs "), " hta ", " hypertension arterielle "), " saos ", " syndrome d'apnees obstructives du sommeil "), " rgo ", " reflux gastro-oesophagien ") ) -> prééclampsie | AD47: =TRIM(SUBSTITUTE(SUBSTITUTE(SUBSTITUTE(SUBSTITUTE(" " & LOWER(TRIM($AC47)) & " ", " oacr ", " occlusion de l'artere centrale de la retine "), " hsd ", " hematome sous-dural "), " fa ", " fibrillation auriculaire "), " ep ", " embolie pulmonaire ") ) -> prééclampsie | AE47: {=_xlfn.LET(_xlpm.base, " " & LOWER(TRIM($AD47)) & " ", _xlpm.s1, SUBSTITUTE(_xlpm.base, " ic ", " insuffisance cardiaque "), _xlpm.s2, SUBSTITUTE(_xlpm.s1, " avc ", " accident vasculaire cerebral "), _xlpm.s3, SUBSTITUTE(_xlpm.s2, " hsa ", " hemorragie sous-arachnoidienne "), _xlpm.s4, SUBSTITUTE(_xlpm.s3, " htp ", " hypertension pulmonaire "), _xlpm.s5, SUBSTITUTE(_xlpm.s4, " bpco ", " bronchopneumopathie chronique obstructive "), _xlpm.s6, SUBSTITUTE(_xlpm.s5, " dmla ", " degenerescence maculaire liee a l age "), TRIM(_xlpm.s6))} -> prééclampsie | AF47: {=_xlfn.LET(_xlpm.base, " " & LOWER(TRIM($AE47)) & " ", _xlpm.s1, SUBSTITUTE(_xlpm.base, " omi ", " oedemes des membres inferieurs "), _xlpm.s2, SUBSTITUTE(_xlpm.s1, " idm ", " infarctus du myocarde "), _xlpm.s3, SUBSTITUTE(_xlpm.s2, " tvp ", " thrombose veineuse profonde "), _xlpm.s4, SUBSTITUTE(_xlpm.s3, " geu ", " grossesse extra-uterine "), _xlpm.s5, SUBSTITUTE(_xlpm.s4, " fuo ", " fievre d origine indeterminee "), TRIM(_xlpm.s5))} -> prééclampsie
A48: 2013 | B48: 🫁 Pneumologie | D48: 45 | E48: =IF(D48="","",IFERROR(INDEX(SSP!$E$2:$E$266, MATCH(D48, SSP!$F$2:$F$266, 0)),"")) -> Toux, expectoration, hémoptysie | F48: =Feuil1!E48 -> Toux | G48: Tuberculose | H48: Tuberculose | J48: Jeune femme de 30 ans avec fièvre et toux persistante | K48: Symptômes de tuberculose avec confirmations diagnostiques. | N48: Tuberculose | O48: =IFERROR(_xlfn.XLOOKUP($D48, SSP!$F:$F, SSP!$E:$E, "Inconnu"), "") -> Toux, expectoration, hémoptysie | P48: =IF(OR(E48="", O48=""), "", IF(LOWER(E48)=LOWER(O48), "OK", "⚠️ Libellé ≠ n°")) -> OK | Q48: =IF(Feuil1!$E48="", "", IF(LOWER(Feuil1!$E48)=LOWER(E48), "Identique", "Différent")) -> Différent | R48: =IF(OR(P48="⚠️ Libellé ≠ n°", O48="Inconnu"), "⚠️", IF(Q48="Différent", "ℹ️", "")) -> ℹ️ | S48: {=_xlfn.LET(_xlpm.genCat,IFERROR(LOWER(TRIM(G48)),""),_xlpm.principal,IFERROR(LOWER(TRIM(H48)),""),_xlpm.orig,IFERROR(LOWER(TRIM(N48)),""),IF(OR(_xlpm.genCat="",_xlpm.principal=""),"",IF(LEFT(LOWER(G48),5)="autre","OK (Autre)",IF(OR(ISNUMBER(SEARCH(_xlpm.genCat,_xlpm.principal)),ISNUMBER(SEARCH(_xlpm.principal,_xlpm.genCat)),AND(_xlpm.orig<>"",OR(ISNUMBER(SEARCH(_xlpm.genCat,_xlpm.orig)),ISNUMBER(SEARCH(_xlpm.orig,_xlpm.genCat))))),"OK","⚠️ À vérifier"))))} -> OK | T48: =IF(S48="","",IF(S48="OK (Autre)","Diagnostic générique = 'Autre – …'",IF(S48="OK","Concordance générique/principal","Écart entre générique et principal"))) -> Concordance générique/principal | U48: {=_xlfn.LET(_xlpm.yr, A48, _xlpm.diag, IF(N48<>"", N48, H48), _xlpm.base, TRIM(SUBSTITUTE(SUBSTITUTE(SUBSTITUTE(SUBSTITUTE(_xlpm.diag,"•"," "),CHAR(160)," "),CHAR(10)," ")," "," ")), LOWER(_xlpm.yr&"|"&_xlpm.base))} -> 2013|tuberculose | V48: =IFERROR(_xlfn.XLOOKUP($AB48,'Cas 2013-2017'!$K:$K,'Cas 2013-2017'!$D:$D,""),"") | W48: =IFERROR(_xlfn.XLOOKUP($AB48,'Cas 2013-2017'!$K:$K,'Cas 2013-2017'!$E:$E,""),"") | X48: =IFERROR(_xlfn.XLOOKUP($AB48,'Cas 2013-2017'!$K:$K,'Cas 2013-2017'!$F:$F,""),"") | Y48: =IFERROR(_xlfn.XLOOKUP($AB48,'Cas 2013-2017'!$K:$K,'Cas 2013-2017'!$G:$G,""),"") | Z48: =IFERROR(_xlfn.XLOOKUP($AB48,'Cas 2013-2017'!$K:$K,'Cas 2013-2017'!$I:$I,""),"") | AA48: =IFERROR(_xlfn.XLOOKUP($AB48,'Cas 2013-2017'!$K:$K,'Cas 2013-2017'!$H:$H,""),"") | AB48: =LOWER($A48 & "|" & $AF48) -> 2013|tuberculose | AC48: =TRIM(SUBSTITUTE(SUBSTITUTE(SUBSTITUTE(SUBSTITUTE(" " & LOWER(TRIM(IF($N48<>"", $N48, $H48))) & " ", " aomi ", " arteriopathie des membres inferieurs "), " hta ", " hypertension arterielle "), " saos ", " syndrome d'apnees obstructives du sommeil "), " rgo ", " reflux gastro-oesophagien ") ) -> tuberculose | AD48: =TRIM(SUBSTITUTE(SUBSTITUTE(SUBSTITUTE(SUBSTITUTE(" " & LOWER(TRIM($AC48)) & " ", " oacr ", " occlusion de l'artere centrale de la retine "), " hsd ", " hematome sous-dural "), " fa ", " fibrillation auriculaire "), " ep ", " embolie pulmonaire ") ) -> tuberculose | AE48: {=_xlfn.LET(_xlpm.base, " " & LOWER(TRIM($AD48)) & " ", _xlpm.s1, SUBSTITUTE(_xlpm.base, " ic ", " insuffisance cardiaque "), _xlpm.s2, SUBSTITUTE(_xlpm.s1, " avc ", " accident vasculaire cerebral "), _xlpm.s3, SUBSTITUTE(_xlpm.s2, " hsa ", " hemorragie sous-arachnoidienne "), _xlpm.s4, SUBSTITUTE(_xlpm.s3, " htp ", " hypertension pulmonaire "), _xlpm.s5, SUBSTITUTE(_xlpm.s4, " bpco ", " bronchopneumopathie chronique obstructive "), _xlpm.s6, SUBSTITUTE(_xlpm.s5, " dmla ", " degenerescence maculaire liee a l age "), TRIM(_xlpm.s6))} -> tuberculose | AF48: {=_xlfn.LET(_xlpm.base, " " & LOWER(TRIM($AE48)) & " ", _xlpm.s1, SUBSTITUTE(_xlpm.base, " omi ", " oedemes des membres inferieurs "), _xlpm.s2, SUBSTITUTE(_xlpm.s1, " idm ", " infarctus du myocarde "), _xlpm.s3, SUBSTITUTE(_xlpm.s2, " tvp ", " thrombose veineuse profonde "), _xlpm.s4, SUBSTITUTE(_xlpm.s3, " geu ", " grossesse extra-uterine "), _xlpm.s5, SUBSTITUTE(_xlpm.s4, " fuo ", " fievre d origine indeterminee "), TRIM(_xlpm.s5))} -> tuberculose
A49: 2013 | B49: 🧬 Oncologie / Hématologie | D49: 224 | E49: =IF(D49="","",IFERROR(INDEX(SSP!$E$2:$E$266, MATCH(D49, SSP!$F$2:$F$266, 0)),"")) -> Demande de bilan de santé, d’examens radiologiques ou biologiques | F49: =Feuil1!E49 -> Bilan | G49: Anémie | H49: Anémie | J49: Anémie macrocytaire chez une végétalienne, déficience en vitamine B12. | K49: Déficience en vit.B12 Anamnèse et status gynécologiques normaux. | N49: Anémie | O49: =IFERROR(_xlfn.XLOOKUP($D49, SSP!$F:$F, SSP!$E:$E, "Inconnu"), "") -> Demande de bilan de santé, d’examens radiologiques ou biologiques | P49: =IF(OR(E49="", O49=""), "", IF(LOWER(E49)=LOWER(O49), "OK", "⚠️ Libellé ≠ n°")) -> OK | Q49: =IF(Feuil1!$E49="", "", IF(LOWER(Feuil1!$E49)=LOWER(E49), "Identique", "Différent")) -> Différent | R49: =IF(OR(P49="⚠️ Libellé ≠ n°", O49="Inconnu"), "⚠️", IF(Q49="Différent", "ℹ️", "")) -> ℹ️ | S49: {=_xlfn.LET(_xlpm.genCat,IFERROR(LOWER(TRIM(G49)),""),_xlpm.principal,IFERROR(LOWER(TRIM(H49)),""),_xlpm.orig,IFERROR(LOWER(TRIM(N49)),""),IF(OR(_xlpm.genCat="",_xlpm.principal=""),"",IF(LEFT(LOWER(G49),5)="autre","OK (Autre)",IF(OR(ISNUMBER(SEARCH(_xlpm.genCat,_xlpm.principal)),ISNUMBER(SEARCH(_xlpm.principal,_xlpm.genCat)),AND(_xlpm.orig<>"",OR(ISNUMBER(SEARCH(_xlpm.genCat,_xlpm.orig)),ISNUMBER(SEARCH(_xlpm.orig,_xlpm.genCat))))),"OK","⚠️ À vérifier"))))} -> OK | T49: =IF(S49="","",IF(S49="OK (Autre)","Diagnostic générique = 'Autre – …'",IF(S49="OK","Concordance générique/principal","Écart entre générique et principal"))) -> Concordance générique/principal | U49: {=_xlfn.LET(_xlpm.yr, A49, _xlpm.diag, IF(N49<>"", N49, H49), _xlpm.base, TRIM(SUBSTITUTE(SUBSTITUTE(SUBSTITUTE(SUBSTITUTE(_xlpm.diag,"•"," "),CHAR(160)," "),CHAR(10)," ")," "," ")), LOWER(_xlpm.yr&"|"&_xlpm.base))} -> 2013|anémie | V49: =IFERROR(_xlfn.XLOOKUP($AB49,'Cas 2013-2017'!$K:$K,'Cas 2013-2017'!$D:$D,""),"") | W49: =IFERROR(_xlfn.XLOOKUP($AB49,'Cas 2013-2017'!$K:$K,'Cas 2013-2017'!$E:$E,""),"") | X49: =IFERROR(_xlfn.XLOOKUP($AB49,'Cas 2013-2017'!$K:$K,'Cas 2013-2017'!$F:$F,""),"") | Y49: =IFERROR(_xlfn.XLOOKUP($AB49,'Cas 2013-2017'!$K:$K,'Cas 2013-2017'!$G:$G,""),"") | Z49: =IFERROR(_xlfn.XLOOKUP($AB49,'Cas 2013-2017'!$K:$K,'Cas 2013-2017'!$I:$I,""),"") | AA49: =IFERROR(_xlfn.XLOOKUP($AB49,'Cas 2013-2017'!$K:$K,'Cas 2013-2017'!$H:$H,""),"") | AB49: =LOWER($A49 & "|" & $AF49) -> 2013|anémie | AC49: =TRIM(SUBSTITUTE(SUBSTITUTE(SUBSTITUTE(SUBSTITUTE(" " & LOWER(TRIM(IF($N49<>"", $N49, $H49))) & " ", " aomi ", " arteriopathie des membres inferieurs "), " hta ", " hypertension arterielle "), " saos ", " syndrome d'apnees obstructives du sommeil "), " rgo ", " reflux gastro-oesophagien ") ) -> anémie | AD49: =TRIM(SUBSTITUTE(SUBSTITUTE(SUBSTITUTE(SUBSTITUTE(" " & LOWER(TRIM($AC49)) & " ", " oacr ", " occlusion de l'artere centrale de la retine "), " hsd ", " hematome sous-dural "), " fa ", " fibrillation auriculaire "), " ep ", " embolie pulmonaire ") ) -> anémie | AE49: {=_xlfn.LET(_xlpm.base, " " & LOWER(TRIM($AD49)) & " ", _xlpm.s1, SUBSTITUTE(_xlpm.base, " ic ", " insuffisance cardiaque "), _xlpm.s2, SUBSTITUTE(_xlpm.s1, " avc ", " accident vasculaire cerebral "), _xlpm.s3, SUBSTITUTE(_xlpm.s2, " hsa ", " hemorragie sous-arachnoidienne "), _xlpm.s4, SUBSTITUTE(_xlpm.s3, " htp ", " hypertension pulmonaire "), _xlpm.s5, SUBSTITUTE(_xlpm.s4, " bpco ", " bronchopneumopathie chronique obstructive "), _xlpm.s6, SUBSTITUTE(_xlpm.s5, " dmla ", " degenerescence maculaire liee a l age "), TRIM(_xlpm.s6))} -> anémie | AF49: {=_xlfn.LET(_xlpm.base, " " & LOWER(TRIM($AE49)) & " ", _xlpm.s1, SUBSTITUTE(_xlpm.base, " omi ", " oedemes des membres inferieurs "), _xlpm.s2, SUBSTITUTE(_xlpm.s1, " idm ", " infarctus du myocarde "), _xlpm.s3, SUBSTITUTE(_xlpm.s2, " tvp ", " thrombose veineuse profonde "), _xlpm.s4, SUBSTITUTE(_xlpm.s3, " geu ", " grossesse extra-uterine "), _xlpm.s5, SUBSTITUTE(_xlpm.s4, " fuo ", " fievre d origine indeterminee "), TRIM(_xlpm.s5))} -> anémie
